  1           0 LOAD_CONST               0 (0)
              2 LOAD_CONST               1 (('annotations',))
              4 IMPORT_NAME              0 (__future__)
              6 IMPORT_FROM              1 (annotations)
              8 STORE_NAME               1 (annotations)
             10 POP_TOP

  3          12 LOAD_CONST               0 (0)
             14 LOAD_CONST               2 (None)
             16 IMPORT_NAME              2 (sys)
             18 STORE_NAME               2 (sys)

  4          20 LOAD_CONST               0 (0)
             22 LOAD_CONST               3 (('deque',))
             24 IMPORT_NAME              3 (collections)
             26 IMPORT_FROM              4 (deque)
             28 STORE_NAME               4 (deque)
             30 POP_TOP

  5          32 LOAD_CONST               0 (0)
             34 LOAD_CONST               4 (('Any', 'Iterable'))
             36 IMPORT_NAME              5 (typing)
             38 IMPORT_FROM              6 (Any)
             40 STORE_NAME               6 (Any)
             42 IMPORT_FROM              7 (Iterable)
             44 STORE_NAME               7 (Iterable)
             46 POP_TOP

  6          48 LOAD_CONST               0 (0)
             50 LOAD_CONST               5 (('mock',))
             52 IMPORT_NAME              8 (unittest)
             54 IMPORT_FROM              9 (mock)
             56 STORE_NAME               9 (mock)
             58 POP_TOP

  8          60 LOAD_CONST               0 (0)
             62 LOAD_CONST               6 (('nodes',))
             64 IMPORT_NAME             10 (interpreted)
             66 IMPORT_FROM             11 (nodes)
             68 STORE_NAME              11 (nodes)
             70 POP_TOP

  9          72 LOAD_CONST               0 (0)
             74 LOAD_CONST               7 (('Assign', 'Attribute', 'AugAssign', 'BinOp', 'BoolOp', 'Call', 'Compare', 'Constant', 'ExprStmt', 'FunctionDef', 'If', 'Import', 'ImportFrom', 'Module', 'Name', 'Node', 'Slice', 'Subscript', 'UnaryOp', 'While', 'alias'))
             76 IMPORT_NAME             12 (interpreted.nodes)
             78 IMPORT_FROM             13 (Assign)
             80 STORE_NAME              13 (Assign)
             82 IMPORT_FROM             14 (Attribute)
             84 STORE_NAME              14 (Attribute)
             86 IMPORT_FROM             15 (AugAssign)
             88 STORE_NAME              15 (AugAssign)
             90 IMPORT_FROM             16 (BinOp)
             92 STORE_NAME              16 (BinOp)
             94 IMPORT_FROM             17 (BoolOp)
             96 STORE_NAME              17 (BoolOp)
             98 IMPORT_FROM             18 (Call)
            100 STORE_NAME              18 (Call)
            102 IMPORT_FROM             19 (Compare)
            104 STORE_NAME              19 (Compare)
            106 IMPORT_FROM             20 (Constant)
            108 STORE_NAME              20 (Constant)
            110 IMPORT_FROM             21 (ExprStmt)
            112 STORE_NAME              21 (ExprStmt)
            114 IMPORT_FROM             22 (FunctionDef)
            116 STORE_NAME              22 (FunctionDef)
            118 IMPORT_FROM             23 (If)
            120 STORE_NAME              23 (If)
            122 IMPORT_FROM             24 (Import)
            124 STORE_NAME              24 (Import)
            126 IMPORT_FROM             25 (ImportFrom)
            128 STORE_NAME              25 (ImportFrom)
            130 IMPORT_FROM             26 (Module)
            132 STORE_NAME              26 (Module)
            134 IMPORT_FROM             27 (Name)
            136 STORE_NAME              27 (Name)
            138 IMPORT_FROM             28 (Node)
            140 STORE_NAME              28 (Node)
            142 IMPORT_FROM             29 (Slice)
            144 STORE_NAME              29 (Slice)
            146 IMPORT_FROM             30 (Subscript)
            148 STORE_NAME              30 (Subscript)
            150 IMPORT_FROM             31 (UnaryOp)
            152 STORE_NAME              31 (UnaryOp)
            154 IMPORT_FROM             32 (While)
            156 STORE_NAME              32 (While)
            158 IMPORT_FROM             33 (alias)
            160 STORE_NAME              33 (alias)
            162 POP_TOP

 32         164 LOAD_CONST               0 (0)
            166 LOAD_CONST               8 (('parse',))
            168 IMPORT_NAME             34 (interpreted.parser)
            170 IMPORT_FROM             35 (parse)
            172 STORE_NAME              35 (parse)
            174 POP_TOP

 34         176 LOAD_NAME               36 (object)
            178 CALL_FUNCTION            0
            180 STORE_NAME              37 (NOT_SET)

 37         182 LOAD_BUILD_CLASS
            184 LOAD_CONST               9 (<code object Scope at 0x100e607c0, file "./interp.py", line 37>)
            186 LOAD_CONST              10 ('Scope')
            188 MAKE_FUNCTION            0
            190 LOAD_CONST              10 ('Scope')
            192 CALL_FUNCTION            2
            194 STORE_NAME              38 (Scope)

 55         196 LOAD_BUILD_CLASS
            198 LOAD_CONST              11 (<code object InterpreterError at 0x100e60870, file "./interp.py", line 55>)
            200 LOAD_CONST              12 ('InterpreterError')
            202 MAKE_FUNCTION            0
            204 LOAD_CONST              12 ('InterpreterError')
            206 LOAD_NAME               39 (Exception)
            208 CALL_FUNCTION            3
            210 STORE_NAME              40 (InterpreterError)

 59         212 LOAD_BUILD_CLASS
            214 LOAD_CONST              13 (<code object Object at 0x100e60b30, file "./interp.py", line 59>)
            216 LOAD_CONST              14 ('Object')
            218 MAKE_FUNCTION            0
            220 LOAD_CONST              14 ('Object')
            222 CALL_FUNCTION            2
            224 STORE_NAME              41 (Object)

 73         226 LOAD_BUILD_CLASS
            228 LOAD_CONST              15 (<code object Module at 0x100e60df0, file "./interp.py", line 73>)
            230 LOAD_CONST              16 ('Module')
            232 MAKE_FUNCTION            0
            234 LOAD_CONST              16 ('Module')
            236 LOAD_NAME               41 (Object)
            238 CALL_FUNCTION            3
            240 STORE_NAME              26 (Module)

 79         242 LOAD_BUILD_CLASS
            244 LOAD_CONST              17 (<code object Function at 0x100e57190, file "./interp.py", line 79>)
            246 LOAD_CONST              18 ('Function')
            248 MAKE_FUNCTION            0
            250 LOAD_CONST              18 ('Function')
            252 LOAD_NAME               41 (Object)
            254 CALL_FUNCTION            3
            256 STORE_NAME              42 (Function)

 96         258 LOAD_BUILD_CLASS
            260 LOAD_CONST              19 (<code object Print at 0x100e57500, file "./interp.py", line 96>)
            262 LOAD_CONST              20 ('Print')
            264 MAKE_FUNCTION            0
            266 LOAD_CONST              20 ('Print')
            268 LOAD_NAME               42 (Function)
            270 CALL_FUNCTION            3
            272 STORE_NAME              43 (Print)

107         274 LOAD_BUILD_CLASS
            276 LOAD_CONST              21 (<code object Len at 0x100e57710, file "./interp.py", line 107>)
            278 LOAD_CONST              22 ('Len')
            280 MAKE_FUNCTION            0
            282 LOAD_CONST              22 ('Len')
            284 LOAD_NAME               42 (Function)
            286 CALL_FUNCTION            3
            288 STORE_NAME              44 (Len)

127         290 LOAD_BUILD_CLASS
            292 LOAD_CONST              23 (<code object Enumerate at 0x100e57be0, file "./interp.py", line 127>)
            294 LOAD_CONST              24 ('Enumerate')
            296 MAKE_FUNCTION            0
            298 LOAD_CONST              24 ('Enumerate')
            300 LOAD_NAME               42 (Function)
            302 CALL_FUNCTION            3
            304 STORE_NAME              45 (Enumerate)

141         306 LOAD_BUILD_CLASS
            308 LOAD_CONST              25 (<code object Int at 0x100e57ea0, file "./interp.py", line 141>)
            310 LOAD_CONST              26 ('Int')
            312 MAKE_FUNCTION            0
            314 LOAD_CONST              26 ('Int')
            316 LOAD_NAME               42 (Function)
            318 CALL_FUNCTION            3
            320 STORE_NAME              46 (Int)

158         322 LOAD_BUILD_CLASS
            324 LOAD_CONST              27 (<code object Float at 0x100e53190, file "./interp.py", line 158>)
            326 LOAD_CONST              28 ('Float')
            328 MAKE_FUNCTION            0
            330 LOAD_CONST              28 ('Float')
            332 LOAD_NAME               42 (Function)
            334 CALL_FUNCTION            3
            336 STORE_NAME              47 (Float)

175         338 LOAD_BUILD_CLASS
            340 LOAD_CONST              29 (<code object Break at 0x100e53240, file "./interp.py", line 175>)
            342 LOAD_CONST              30 ('Break')
            344 MAKE_FUNCTION            0
            346 LOAD_CONST              30 ('Break')
            348 LOAD_NAME               39 (Exception)
            350 CALL_FUNCTION            3
            352 STORE_NAME              48 (Break)

179         354 LOAD_BUILD_CLASS
            356 LOAD_CONST              31 (<code object Continue at 0x100e532f0, file "./interp.py", line 179>)
            358 LOAD_CONST              32 ('Continue')
            360 MAKE_FUNCTION            0
            362 LOAD_CONST              32 ('Continue')
            364 LOAD_NAME               39 (Exception)
            366 CALL_FUNCTION            3
            368 STORE_NAME              49 (Continue)

183         370 LOAD_BUILD_CLASS
            372 LOAD_CONST              33 (<code object Return at 0x100e53450, file "./interp.py", line 183>)
            374 LOAD_CONST              34 ('Return')
            376 MAKE_FUNCTION            0
            378 LOAD_CONST              34 ('Return')
            380 LOAD_NAME               39 (Exception)
            382 CALL_FUNCTION            3
            384 STORE_NAME              50 (Return)

190         386 LOAD_BUILD_CLASS
            388 LOAD_CONST              35 (<code object UserFunction at 0x100e537c0, file "./interp.py", line 190>)
            390 LOAD_CONST              36 ('UserFunction')
            392 MAKE_FUNCTION            0
            394 LOAD_CONST              36 ('UserFunction')
            396 LOAD_NAME               42 (Function)
            398 CALL_FUNCTION            3
            400 STORE_NAME              51 (UserFunction)

234         402 LOAD_BUILD_CLASS
            404 LOAD_CONST              37 (<code object DequeConstructor at 0x100e53a80, file "./interp.py", line 234>)
            406 LOAD_CONST              38 ('DequeConstructor')
            408 MAKE_FUNCTION            0
            410 LOAD_CONST              38 ('DequeConstructor')
            412 LOAD_NAME               42 (Function)
            414 CALL_FUNCTION            3
            416 STORE_NAME              52 (DequeConstructor)

246         418 LOAD_BUILD_CLASS
            420 LOAD_CONST              39 (<code object Deque at 0x100e53d40, file "./interp.py", line 246>)
            422 LOAD_CONST              40 ('Deque')
            424 MAKE_FUNCTION            0
            426 LOAD_CONST              40 ('Deque')
            428 LOAD_NAME               41 (Object)
            430 CALL_FUNCTION            3
            432 STORE_NAME              53 (Deque)

259         434 LOAD_BUILD_CLASS
            436 LOAD_CONST              41 (<code object Append at 0x100e3e0e0, file "./interp.py", line 259>)
            438 LOAD_CONST              42 ('Append')
            440 MAKE_FUNCTION            0
            442 LOAD_CONST              42 ('Append')
            444 LOAD_NAME               42 (Function)
            446 CALL_FUNCTION            3
            448 STORE_NAME              54 (Append)

276         450 LOAD_BUILD_CLASS
            452 LOAD_CONST              43 (<code object Items at 0x100e3e500, file "./interp.py", line 276>)
            454 LOAD_CONST              44 ('Items')
            456 MAKE_FUNCTION            0
            458 LOAD_CONST              44 ('Items')
            460 LOAD_NAME               42 (Function)
            462 CALL_FUNCTION            3
            464 STORE_NAME              55 (Items)

294         466 LOAD_BUILD_CLASS
            468 LOAD_CONST              45 (<code object PopLeft at 0x100e3e870, file "./interp.py", line 294>)
            470 LOAD_CONST              46 ('PopLeft')
            472 MAKE_FUNCTION            0
            474 LOAD_CONST              46 ('PopLeft')
            476 LOAD_NAME               42 (Function)
            478 CALL_FUNCTION            3
            480 STORE_NAME              56 (PopLeft)

310         482 LOAD_BUILD_CLASS
            484 LOAD_CONST              47 (<code object Value at 0x100e3edf0, file "./interp.py", line 310>)
            486 LOAD_CONST              48 ('Value')
            488 MAKE_FUNCTION            0
            490 LOAD_CONST              48 ('Value')
            492 LOAD_NAME               41 (Object)
            494 CALL_FUNCTION            3
            496 STORE_NAME              57 (Value)

338         498 LOAD_BUILD_CLASS
            500 LOAD_CONST              49 (<code object IsDigit at 0x100e3a0e0, file "./interp.py", line 338>)
            502 LOAD_CONST              50 ('IsDigit')
            504 MAKE_FUNCTION            0
            506 LOAD_CONST              50 ('IsDigit')
            508 LOAD_NAME               42 (Function)
            510 CALL_FUNCTION            3
            512 STORE_NAME              58 (IsDigit)

354         514 LOAD_BUILD_CLASS
            516 LOAD_CONST              51 (<code object IsAlpha at 0x100e3a3a0, file "./interp.py", line 354>)
            518 LOAD_CONST              52 ('IsAlpha')
            520 MAKE_FUNCTION            0
            522 LOAD_CONST              52 ('IsAlpha')
            524 LOAD_NAME               42 (Function)
            526 CALL_FUNCTION            3
            528 STORE_NAME              59 (IsAlpha)

370         530 LOAD_BUILD_CLASS
            532 LOAD_CONST              53 (<code object Join at 0x100e3a7c0, file "./interp.py", line 370>)
            534 LOAD_CONST              54 ('Join')
            536 MAKE_FUNCTION            0
            538 LOAD_CONST              54 ('Join')
            540 LOAD_NAME               42 (Function)
            542 CALL_FUNCTION            3
            544 STORE_NAME              60 (Join)

390         546 LOAD_BUILD_CLASS
            548 LOAD_CONST              55 (<code object List at 0x100e3ab30, file "./interp.py", line 390>)
            550 LOAD_CONST              56 ('List')
            552 MAKE_FUNCTION            0
            554 LOAD_CONST              56 ('List')
            556 LOAD_NAME               41 (Object)
            558 CALL_FUNCTION            3
            560 STORE_NAME              61 (List)

403         562 LOAD_BUILD_CLASS
            564 LOAD_CONST              57 (<code object Tuple at 0x100e3aea0, file "./interp.py", line 403>)
            566 LOAD_CONST              58 ('Tuple')
            568 MAKE_FUNCTION            0
            570 LOAD_CONST              58 ('Tuple')
            572 LOAD_NAME               41 (Object)
            574 CALL_FUNCTION            3
            576 STORE_NAME              62 (Tuple)

415         578 LOAD_BUILD_CLASS
            580 LOAD_CONST              59 (<code object Dict at 0x100e362f0, file "./interp.py", line 415>)
            582 LOAD_CONST              60 ('Dict')
            584 MAKE_FUNCTION            0
            586 LOAD_CONST              60 ('Dict')
            588 LOAD_NAME               41 (Object)
            590 CALL_FUNCTION            3
            592 STORE_NAME              63 (Dict)

434         594 LOAD_CONST              14 ('Object')
            596 LOAD_CONST              61 ('bool')
            598 LOAD_CONST              62 (('obj', 'return'))
            600 BUILD_CONST_KEY_MAP      2
            602 LOAD_CONST              63 (<code object is_truthy at 0x100e363a0, file "./interp.py", line 434>)
            604 LOAD_CONST              64 ('is_truthy')
            606 MAKE_FUNCTION            4 (annotations)
            608 STORE_NAME              64 (is_truthy)

441         610 LOAD_BUILD_CLASS
            612 LOAD_CONST              65 (<code object Interpreter at 0x100e2f190, file "./interp.py", line 441>)
            614 LOAD_CONST              66 ('Interpreter')
            616 MAKE_FUNCTION            0
            618 LOAD_CONST              66 ('Interpreter')
            620 CALL_FUNCTION            2
            622 STORE_NAME              65 (Interpreter)

864         624 LOAD_CONST              67 ('str')
            626 LOAD_CONST              68 ('None')
            628 LOAD_CONST              69 (('source', 'return'))
            630 BUILD_CONST_KEY_MAP      2
            632 LOAD_CONST              70 (<code object interpret at 0x100e2f240, file "./interp.py", line 864>)
            634 LOAD_CONST              71 ('interpret')
            636 MAKE_FUNCTION            4 (annotations)
            638 STORE_NAME              66 (interpret)

872         640 LOAD_CONST              68 ('None')
            642 LOAD_CONST              72 (('return',))
            644 BUILD_CONST_KEY_MAP      1
            646 LOAD_CONST              73 (<code object main at 0x100e2f3a0, file "./interp.py", line 872>)
            648 LOAD_CONST              74 ('main')
            650 MAKE_FUNCTION            4 (annotations)
            652 STORE_NAME              67 (main)

889         654 LOAD_NAME               68 (__name__)
            656 LOAD_CONST              75 ('__main__')
            658 COMPARE_OP               2 (==)
            660 EXTENDED_ARG             2
            662 POP_JUMP_IF_FALSE      670

890         664 LOAD_NAME               67 (main)
            666 CALL_FUNCTION            0
            668 POP_TOP
        >>  670 LOAD_CONST               2 (None)
            672 RETURN_VALUE

Disassembly of <code object Scope at 0x100e607c0, file "./interp.py", line 37>:
 37           0 LOAD_NAME                0 (__name__)
              2 STORE_NAME               1 (__module__)
              4 LOAD_CONST               0 ('Scope')
              6 STORE_NAME               2 (__qualname__)

 38           8 LOAD_CONST              11 ((None,))
             10 LOAD_CONST               2 ('None')
             12 LOAD_CONST               3 (('return',))
             14 BUILD_CONST_KEY_MAP      1
             16 LOAD_CONST               4 (<code object __init__ at 0x100e60660, file "./interp.py", line 38>)
             18 LOAD_CONST               5 ('Scope.__init__')
             20 MAKE_FUNCTION            5 (defaults, annotations)
             22 STORE_NAME               3 (__init__)

 48          24 LOAD_CONST               6 ('Any')
             26 LOAD_CONST               3 (('return',))
             28 BUILD_CONST_KEY_MAP      1
             30 LOAD_CONST               7 (<code object get at 0x100e605b0, file "./interp.py", line 48>)
             32 LOAD_CONST               8 ('Scope.get')
             34 MAKE_FUNCTION            4 (annotations)
             36 STORE_NAME               4 (get)

 51          38 LOAD_CONST               2 ('None')
             40 LOAD_CONST               3 (('return',))
             42 BUILD_CONST_KEY_MAP      1
             44 LOAD_CONST               9 (<code object set at 0x100e60710, file "./interp.py", line 51>)
             46 LOAD_CONST              10 ('Scope.set')
             48 MAKE_FUNCTION            4 (annotations)
             50 STORE_NAME               5 (set)
             52 LOAD_CONST               1 (None)
             54 RETURN_VALUE

Disassembly of <code object __init__ at 0x100e60660, file "./interp.py", line 38>:
 39           0 BUILD_MAP                0
              2 LOAD_FAST                0 (self)
              4 STORE_ATTR               0 (data)

 40           6 LOAD_FAST                1 (parent)
              8 LOAD_FAST                0 (self)
             10 STORE_ATTR               1 (parent)

 41          12 LOAD_FAST                0 (self)
             14 LOAD_METHOD              2 (set)
             16 LOAD_CONST               1 ('print')
             18 LOAD_GLOBAL              3 (Print)
             20 CALL_FUNCTION            0
             22 CALL_METHOD              2
             24 POP_TOP

 42          26 LOAD_FAST                0 (self)
             28 LOAD_METHOD              2 (set)
             30 LOAD_CONST               2 ('len')
             32 LOAD_GLOBAL              4 (Len)
             34 CALL_FUNCTION            0
             36 CALL_METHOD              2
             38 POP_TOP

 43          40 LOAD_FAST                0 (self)
             42 LOAD_METHOD              2 (set)
             44 LOAD_CONST               3 ('int')
             46 LOAD_GLOBAL              5 (Int)
             48 CALL_FUNCTION            0
             50 CALL_METHOD              2
             52 POP_TOP

 44          54 LOAD_FAST                0 (self)
             56 LOAD_METHOD              2 (set)
             58 LOAD_CONST               4 ('float')
             60 LOAD_GLOBAL              6 (Float)
             62 CALL_FUNCTION            0
             64 CALL_METHOD              2
             66 POP_TOP

 45          68 LOAD_FAST                0 (self)
             70 LOAD_METHOD              2 (set)
             72 LOAD_CONST               5 ('deque')
             74 LOAD_GLOBAL              7 (DequeConstructor)
             76 CALL_FUNCTION            0
             78 CALL_METHOD              2
             80 POP_TOP

 46          82 LOAD_FAST                0 (self)
             84 LOAD_METHOD              2 (set)
             86 LOAD_CONST               6 ('enumerate')
             88 LOAD_GLOBAL              8 (Enumerate)
             90 CALL_FUNCTION            0
             92 CALL_METHOD              2
             94 POP_TOP
             96 LOAD_CONST               0 (None)
             98 RETURN_VALUE

Disassembly of <code object get at 0x100e605b0, file "./interp.py", line 48>:
 49           0 LOAD_FAST                0 (self)
              2 LOAD_ATTR                0 (data)
              4 LOAD_METHOD              1 (get)
              6 LOAD_FAST                1 (name)
              8 LOAD_GLOBAL              2 (NOT_SET)
             10 CALL_METHOD              2
             12 RETURN_VALUE

Disassembly of <code object set at 0x100e60710, file "./interp.py", line 51>:
 52           0 LOAD_FAST                2 (value)
              2 LOAD_FAST                0 (self)
              4 LOAD_ATTR                0 (data)
              6 LOAD_FAST                1 (name)
              8 STORE_SUBSCR
             10 LOAD_CONST               0 (None)
             12 RETURN_VALUE

Disassembly of <code object InterpreterError at 0x100e60870, file "./interp.py", line 55>:
 55           0 LOAD_NAME                0 (__name__)
              2 STORE_NAME               1 (__module__)
              4 LOAD_CONST               0 ('InterpreterError')
              6 STORE_NAME               2 (__qualname__)

 56           8 LOAD_CONST               1 (None)
             10 RETURN_VALUE

Disassembly of <code object Object at 0x100e60b30, file "./interp.py", line 59>:
 59           0 LOAD_NAME                0 (__name__)
              2 STORE_NAME               1 (__module__)
              4 LOAD_CONST               0 ('Object')
              6 STORE_NAME               2 (__qualname__)

 60           8 LOAD_CONST               1 ('Every object will inherit this in this implementation.')
             10 STORE_NAME               3 (__doc__)

 62          12 LOAD_CONST               2 ('None')
             14 LOAD_CONST               3 (('return',))
             16 BUILD_CONST_KEY_MAP      1
             18 LOAD_CONST               4 (<code object __init__ at 0x100e60920, file "./interp.py", line 62>)
             20 LOAD_CONST               5 ('Object.__init__')
             22 MAKE_FUNCTION            4 (annotations)
             24 STORE_NAME               4 (__init__)

 66          26 LOAD_CONST               6 ('str')
             28 LOAD_CONST               3 (('return',))
             30 BUILD_CONST_KEY_MAP      1
             32 LOAD_CONST               7 (<code object as_string at 0x100e609d0, file "./interp.py", line 66>)
             34 LOAD_CONST               8 ('Object.as_string')
             36 MAKE_FUNCTION            4 (annotations)
             38 STORE_NAME               5 (as_string)

 69          40 LOAD_CONST               6 ('str')
             42 LOAD_CONST               3 (('return',))
             44 BUILD_CONST_KEY_MAP      1
             46 LOAD_CONST               9 (<code object repr at 0x100e60a80, file "./interp.py", line 69>)
             48 LOAD_CONST              10 ('Object.repr')
             50 MAKE_FUNCTION            4 (annotations)
             52 STORE_NAME               6 (repr)
             54 LOAD_CONST              11 (None)
             56 RETURN_VALUE

Disassembly of <code object __init__ at 0x100e60920, file "./interp.py", line 62>:
 63           0 BUILD_MAP                0
              2 LOAD_FAST                0 (self)
              4 STORE_ATTR               0 (attributes)

 64           6 BUILD_MAP                0
              8 LOAD_FAST                0 (self)
             10 STORE_ATTR               1 (methods)
             12 LOAD_CONST               0 (None)
             14 RETURN_VALUE

Disassembly of <code object as_string at 0x100e609d0, file "./interp.py", line 66>:
 67           0 LOAD_GLOBAL              0 (NotImplementedError)
              2 RAISE_VARARGS            1
              4 LOAD_CONST               0 (None)
              6 RETURN_VALUE

Disassembly of <code object repr at 0x100e60a80, file "./interp.py", line 69>:
 70           0 LOAD_FAST                0 (self)
              2 LOAD_METHOD              0 (as_string)
              4 CALL_METHOD              0
              6 RETURN_VALUE

Disassembly of <code object Module at 0x100e60df0, file "./interp.py", line 73>:
 73           0 LOAD_NAME                0 (__name__)
              2 STORE_NAME               1 (__module__)
              4 LOAD_CONST               0 ('Module')
              6 STORE_NAME               2 (__qualname__)

 74           8 LOAD_CONST               1 ('dict[str, Object]')
             10 LOAD_CONST               2 (('members',))
             12 BUILD_CONST_KEY_MAP      1
             14 LOAD_CLOSURE             0 (__class__)
             16 BUILD_TUPLE              1
             18 LOAD_CONST               3 (<code object __init__ at 0x100e60d40, file "./interp.py", line 74>)
             20 LOAD_CONST               4 ('Module.__init__')
             22 MAKE_FUNCTION           12 (annotations, closure)
             24 STORE_NAME               3 (__init__)
             26 LOAD_CLOSURE             0 (__class__)
             28 DUP_TOP
             30 STORE_NAME               4 (__classcell__)
             32 RETURN_VALUE

Disassembly of <code object __init__ at 0x100e60d40, file "./interp.py", line 74>:
 75           0 LOAD_GLOBAL              0 (super)
              2 CALL_FUNCTION            0
              4 LOAD_METHOD              1 (__init__)
              6 CALL_METHOD              0
              8 POP_TOP

 76          10 LOAD_FAST                0 (self)
             12 LOAD_ATTR                2 (attributes)
             14 LOAD_METHOD              3 (update)
             16 LOAD_FAST                1 (members)
             18 CALL_METHOD              1
             20 POP_TOP
             22 LOAD_CONST               0 (None)
             24 RETURN_VALUE

Disassembly of <code object Function at 0x100e57190, file "./interp.py", line 79>:
 79           0 LOAD_NAME                0 (__name__)
              2 STORE_NAME               1 (__module__)
              4 LOAD_CONST               0 ('Function')
              6 STORE_NAME               2 (__qualname__)

 80           8 LOAD_CONST               1 ('str')
             10 LOAD_CONST               2 (('return',))
             12 BUILD_CONST_KEY_MAP      1
             14 LOAD_CONST               3 (<code object as_string at 0x100e60ea0, file "./interp.py", line 80>)
             16 LOAD_CONST               4 ('Function.as_string')
             18 MAKE_FUNCTION            4 (annotations)
             20 STORE_NAME               3 (as_string)

 83          22 LOAD_CONST               5 ('int')
             24 LOAD_CONST               2 (('return',))
             26 BUILD_CONST_KEY_MAP      1
             28 LOAD_CONST               6 (<code object arg_count at 0x100e60f50, file "./interp.py", line 83>)
             30 LOAD_CONST               7 ('Function.arg_count')
             32 MAKE_FUNCTION            4 (annotations)
             34 STORE_NAME               4 (arg_count)

 86          36 LOAD_CONST               8 ('list[Object]')
             38 LOAD_CONST               9 ('Object')
             40 LOAD_CONST              10 (('args', 'return'))
             42 BUILD_CONST_KEY_MAP      2
             44 LOAD_CONST              11 (<code object ensure_args at 0x100e57030, file "./interp.py", line 86>)
             46 LOAD_CONST              12 ('Function.ensure_args')
             48 MAKE_FUNCTION            4 (annotations)
             50 STORE_NAME               5 (ensure_args)

 92          52 LOAD_CONST              13 ('Interpreter')
             54 LOAD_CONST               8 ('list[Object]')
             56 LOAD_CONST              14 ('None')
             58 LOAD_CONST              15 (('interpreter', 'args', 'return'))
             60 BUILD_CONST_KEY_MAP      3
             62 LOAD_CONST              16 (<code object call at 0x100e570e0, file "./interp.py", line 92>)
             64 LOAD_CONST              17 ('Function.call')
             66 MAKE_FUNCTION            4 (annotations)
             68 STORE_NAME               6 (call)
             70 LOAD_CONST              18 (None)
             72 RETURN_VALUE

Disassembly of <code object as_string at 0x100e60ea0, file "./interp.py", line 80>:
 81           0 LOAD_GLOBAL              0 (NotImplementedError)
              2 RAISE_VARARGS            1
              4 LOAD_CONST               0 (None)
              6 RETURN_VALUE

Disassembly of <code object arg_count at 0x100e60f50, file "./interp.py", line 83>:
 84           0 LOAD_GLOBAL              0 (NotImplementedError)
              2 RAISE_VARARGS            1
              4 LOAD_CONST               0 (None)
              6 RETURN_VALUE

Disassembly of <code object ensure_args at 0x100e57030, file "./interp.py", line 86>:
 87           0 LOAD_GLOBAL              0 (len)
              2 LOAD_FAST                1 (args)
              4 CALL_FUNCTION            1
              6 LOAD_FAST                0 (self)
              8 LOAD_METHOD              1 (arg_count)
             10 CALL_METHOD              0
             12 COMPARE_OP               3 (!=)
             14 POP_JUMP_IF_FALSE       54

 88          16 LOAD_GLOBAL              2 (InterpreterError)

 89          18 LOAD_FAST                0 (self)
             20 LOAD_METHOD              3 (repr)
             22 CALL_METHOD              0
             24 FORMAT_VALUE             0
             26 LOAD_CONST               1 (' takes ')
             28 LOAD_FAST                0 (self)
             30 LOAD_METHOD              1 (arg_count)
             32 CALL_METHOD              0
             34 FORMAT_VALUE             0
             36 LOAD_CONST               2 (' arguments, ')
             38 LOAD_GLOBAL              0 (len)
             40 LOAD_FAST                1 (args)
             42 CALL_FUNCTION            1
             44 FORMAT_VALUE             0
             46 LOAD_CONST               3 (' given')
             48 BUILD_STRING             6

 88          50 CALL_FUNCTION            1
             52 RAISE_VARARGS            1
        >>   54 LOAD_CONST               0 (None)
             56 RETURN_VALUE

Disassembly of <code object call at 0x100e570e0, file "./interp.py", line 92>:
 93           0 LOAD_GLOBAL              0 (NotImplementedError)
              2 RAISE_VARARGS            1
              4 LOAD_CONST               0 (None)
              6 RETURN_VALUE

Disassembly of <code object Print at 0x100e57500, file "./interp.py", line 96>:
 96           0 LOAD_NAME                0 (__name__)
              2 STORE_NAME               1 (__module__)
              4 LOAD_CONST               0 ('Print')
              6 STORE_NAME               2 (__qualname__)

 97           8 LOAD_CONST               1 ('str')
             10 LOAD_CONST               2 (('return',))
             12 BUILD_CONST_KEY_MAP      1
             14 LOAD_CONST               3 (<code object as_string at 0x100e57240, file "./interp.py", line 97>)
             16 LOAD_CONST               4 ('Print.as_string')
             18 MAKE_FUNCTION            4 (annotations)
             20 STORE_NAME               3 (as_string)

100          22 LOAD_CONST               5 ('int')
             24 LOAD_CONST               2 (('return',))
             26 BUILD_CONST_KEY_MAP      1
             28 LOAD_CONST               6 (<code object arg_count at 0x100e572f0, file "./interp.py", line 100>)
             30 LOAD_CONST               7 ('Print.arg_count')
             32 MAKE_FUNCTION            4 (annotations)
             34 STORE_NAME               4 (arg_count)

103          36 LOAD_CONST               8 ('Interpreter')
             38 LOAD_CONST               9 ('list[Object]')
             40 LOAD_CONST              10 ('None')
             42 LOAD_CONST              11 (('_', 'args', 'return'))
             44 BUILD_CONST_KEY_MAP      3
             46 LOAD_CONST              12 (<code object call at 0x100e57450, file "./interp.py", line 103>)
             48 LOAD_CONST              13 ('Print.call')
             50 MAKE_FUNCTION            4 (annotations)
             52 STORE_NAME               5 (call)
             54 LOAD_CONST              14 (None)
             56 RETURN_VALUE

Disassembly of <code object as_string at 0x100e57240, file "./interp.py", line 97>:
 98           0 LOAD_CONST               1 ("<function 'print'>")
              2 RETURN_VALUE

Disassembly of <code object arg_count at 0x100e572f0, file "./interp.py", line 100>:
101           0 LOAD_GLOBAL              0 (mock)
              2 LOAD_ATTR                1 (ANY)
              4 RETURN_VALUE

Disassembly of <code object call at 0x100e57450, file "./interp.py", line 103>:
104           0 LOAD_GLOBAL              0 (print)
              2 LOAD_CONST               1 (<code object <listcomp> at 0x100e573a0, file "./interp.py", line 104>)
              4 LOAD_CONST               2 ('Print.call.<locals>.<listcomp>')
              6 MAKE_FUNCTION            0
              8 LOAD_FAST                2 (args)
             10 GET_ITER
             12 CALL_FUNCTION            1
             14 CALL_FUNCTION_EX         0
             16 POP_TOP
             18 LOAD_CONST               0 (None)
             20 RETURN_VALUE

Disassembly of <code object <listcomp> at 0x100e573a0, file "./interp.py", line 104>:
104           0 BUILD_LIST               0
              2 LOAD_FAST                0 (.0)
        >>    4 FOR_ITER                12 (to 18)
              6 STORE_FAST               1 (arg)
              8 LOAD_FAST                1 (arg)
             10 LOAD_METHOD              0 (as_string)
             12 CALL_METHOD              0
             14 LIST_APPEND              2
             16 JUMP_ABSOLUTE            4
        >>   18 RETURN_VALUE

Disassembly of <code object Len at 0x100e57710, file "./interp.py", line 107>:
107           0 LOAD_NAME                0 (__name__)
              2 STORE_NAME               1 (__module__)
              4 LOAD_CONST               0 ('Len')
              6 STORE_NAME               2 (__qualname__)

108           8 LOAD_CONST               1 ('str')
             10 LOAD_CONST               2 (('return',))
             12 BUILD_CONST_KEY_MAP      1
             14 LOAD_CONST               3 (<code object as_string at 0x100e575b0, file "./interp.py", line 108>)
             16 LOAD_CONST               4 ('Len.as_string')
             18 MAKE_FUNCTION            4 (annotations)
             20 STORE_NAME               3 (as_string)

111          22 LOAD_CONST               5 ('int')
             24 LOAD_CONST               2 (('return',))
             26 BUILD_CONST_KEY_MAP      1
             28 LOAD_CONST               6 (<code object arg_count at 0x100e57660, file "./interp.py", line 111>)
             30 LOAD_CONST               7 ('Len.arg_count')
             32 MAKE_FUNCTION            4 (annotations)
             34 STORE_NAME               4 (arg_count)

114          36 LOAD_CONST               8 ('Interpreter')
             38 LOAD_CONST               9 ('list[Object]')
             40 LOAD_CONST              10 ('Object')
             42 LOAD_CONST              11 (('_', 'args', 'return'))
             44 BUILD_CONST_KEY_MAP      3
             46 LOAD_CLOSURE             0 (__class__)
             48 BUILD_TUPLE              1
             50 LOAD_CONST              12 (<code object call at 0x100e577c0, file "./interp.py", line 114>)
             52 LOAD_CONST              13 ('Len.call')
             54 MAKE_FUNCTION           12 (annotations, closure)
             56 STORE_NAME               5 (call)
             58 LOAD_CLOSURE             0 (__class__)
             60 DUP_TOP
             62 STORE_NAME               6 (__classcell__)
             64 RETURN_VALUE

Disassembly of <code object as_string at 0x100e575b0, file "./interp.py", line 108>:
109           0 LOAD_CONST               1 ("<function 'len'>")
              2 RETURN_VALUE

Disassembly of <code object arg_count at 0x100e57660, file "./interp.py", line 111>:
112           0 LOAD_CONST               1 (1)
              2 RETURN_VALUE

Disassembly of <code object call at 0x100e577c0, file "./interp.py", line 114>:
115           0 LOAD_GLOBAL              0 (super)
              2 CALL_FUNCTION            0
              4 LOAD_METHOD              1 (ensure_args)
              6 LOAD_FAST                2 (args)
              8 CALL_METHOD              1
             10 POP_TOP

117          12 LOAD_FAST                2 (args)
             14 LOAD_CONST               1 (0)
             16 BINARY_SUBSCR
             18 STORE_FAST               3 (item)

118          20 LOAD_GLOBAL              2 (isinstance)
             22 LOAD_FAST                3 (item)
             24 LOAD_GLOBAL              3 (List)
             26 LOAD_GLOBAL              4 (Tuple)
             28 LOAD_GLOBAL              5 (Deque)
             30 BUILD_TUPLE              3
             32 CALL_FUNCTION            2
             34 POP_JUMP_IF_FALSE       50

119          36 LOAD_GLOBAL              6 (Value)
             38 LOAD_GLOBAL              7 (len)
             40 LOAD_FAST                3 (item)
             42 LOAD_ATTR                8 (_data)
             44 CALL_FUNCTION            1
             46 CALL_FUNCTION            1
             48 RETURN_VALUE

121     >>   50 LOAD_GLOBAL              2 (isinstance)
             52 LOAD_FAST                3 (item)
             54 LOAD_GLOBAL              6 (Value)
             56 CALL_FUNCTION            2
             58 POP_JUMP_IF_FALSE       86
             60 LOAD_GLOBAL              2 (isinstance)
             62 LOAD_FAST                3 (item)
             64 LOAD_ATTR                9 (value)
             66 LOAD_GLOBAL             10 (str)
             68 CALL_FUNCTION            2
             70 POP_JUMP_IF_FALSE       86

122          72 LOAD_GLOBAL              6 (Value)
             74 LOAD_GLOBAL              7 (len)
             76 LOAD_FAST                3 (item)
             78 LOAD_ATTR                9 (value)
             80 CALL_FUNCTION            1
             82 CALL_FUNCTION            1
             84 RETURN_VALUE

124     >>   86 LOAD_GLOBAL             11 (InterpreterError)
             88 LOAD_GLOBAL             12 (type)
             90 LOAD_FAST                3 (item)
             92 CALL_FUNCTION            1
             94 LOAD_ATTR               13 (__name__)
             96 FORMAT_VALUE             0
             98 LOAD_CONST               2 (' has no len()')
            100 BUILD_STRING             2
            102 CALL_FUNCTION            1
            104 RAISE_VARARGS            1
            106 LOAD_CONST               0 (None)
            108 RETURN_VALUE

Disassembly of <code object Enumerate at 0x100e57be0, file "./interp.py", line 127>:
127           0 LOAD_NAME                0 (__name__)
              2 STORE_NAME               1 (__module__)
              4 LOAD_CONST               0 ('Enumerate')
              6 STORE_NAME               2 (__qualname__)

128           8 LOAD_CONST               1 ('str')
             10 LOAD_CONST               2 (('return',))
             12 BUILD_CONST_KEY_MAP      1
             14 LOAD_CONST               3 (<code object as_string at 0x100e57870, file "./interp.py", line 128>)
             16 LOAD_CONST               4 ('Enumerate.as_string')
             18 MAKE_FUNCTION            4 (annotations)
             20 STORE_NAME               3 (as_string)

131          22 LOAD_CONST               5 ('int')
             24 LOAD_CONST               2 (('return',))
             26 BUILD_CONST_KEY_MAP      1
             28 LOAD_CONST               6 (<code object arg_count at 0x100e57920, file "./interp.py", line 131>)
             30 LOAD_CONST               7 ('Enumerate.arg_count')
             32 MAKE_FUNCTION            4 (annotations)
             34 STORE_NAME               4 (arg_count)

134          36 LOAD_CONST               8 ('Interpreter')
             38 LOAD_CONST               9 ('list[Object]')
             40 LOAD_CONST              10 ('Object')
             42 LOAD_CONST              11 (('_', 'args', 'return'))
             44 BUILD_CONST_KEY_MAP      3
             46 LOAD_CLOSURE             0 (__class__)
             48 BUILD_TUPLE              1
             50 LOAD_CONST              12 (<code object call at 0x100e57b30, file "./interp.py", line 134>)
             52 LOAD_CONST              13 ('Enumerate.call')
             54 MAKE_FUNCTION           12 (annotations, closure)
             56 STORE_NAME               5 (call)
             58 LOAD_CLOSURE             0 (__class__)
             60 DUP_TOP
             62 STORE_NAME               6 (__classcell__)
             64 RETURN_VALUE

Disassembly of <code object as_string at 0x100e57870, file "./interp.py", line 128>:
129           0 LOAD_CONST               1 ("<function 'enumerate'>")
              2 RETURN_VALUE

Disassembly of <code object arg_count at 0x100e57920, file "./interp.py", line 131>:
132           0 LOAD_CONST               1 (1)
              2 RETURN_VALUE

Disassembly of <code object call at 0x100e57b30, file "./interp.py", line 134>:
135           0 LOAD_GLOBAL              0 (super)
              2 CALL_FUNCTION            0
              4 LOAD_METHOD              1 (ensure_args)
              6 LOAD_FAST                2 (args)
              8 CALL_METHOD              1
             10 POP_TOP

137          12 LOAD_CONST               1 (<code object <listcomp> at 0x100e57a80, file "./interp.py", line 137>)
             14 LOAD_CONST               2 ('Enumerate.call.<locals>.<listcomp>')
             16 MAKE_FUNCTION            0
             18 LOAD_GLOBAL              2 (enumerate)
             20 LOAD_FAST                2 (args)
             22 LOAD_CONST               3 (0)
             24 BINARY_SUBSCR
             26 CALL_FUNCTION            1
             28 GET_ITER
             30 CALL_FUNCTION            1
             32 STORE_FAST               3 (pairs)

138          34 LOAD_GLOBAL              3 (List)
             36 LOAD_FAST                3 (pairs)
             38 CALL_FUNCTION            1
             40 RETURN_VALUE

Disassembly of <code object <listcomp> at 0x100e57a80, file "./interp.py", line 137>:
137           0 BUILD_LIST               0
              2 LOAD_FAST                0 (.0)
        >>    4 FOR_ITER                24 (to 30)
              6 UNPACK_SEQUENCE          2
              8 STORE_FAST               1 (idx)
             10 STORE_FAST               2 (val)
             12 LOAD_GLOBAL              0 (Tuple)
             14 LOAD_GLOBAL              1 (Value)
             16 LOAD_FAST                1 (idx)
             18 CALL_FUNCTION            1
             20 LOAD_FAST                2 (val)
             22 BUILD_LIST               2
             24 CALL_FUNCTION            1
             26 LIST_APPEND              2
             28 JUMP_ABSOLUTE            4
        >>   30 RETURN_VALUE

Disassembly of <code object Int at 0x100e57ea0, file "./interp.py", line 141>:
141           0 LOAD_NAME                0 (__name__)
              2 STORE_NAME               1 (__module__)
              4 LOAD_CONST               0 ('Int')
              6 STORE_NAME               2 (__qualname__)

142           8 LOAD_CONST               1 ('str')
             10 LOAD_CONST               2 (('return',))
             12 BUILD_CONST_KEY_MAP      1
             14 LOAD_CONST               3 (<code object as_string at 0x100e57c90, file "./interp.py", line 142>)
             16 LOAD_CONST               4 ('Int.as_string')
             18 MAKE_FUNCTION            4 (annotations)
             20 STORE_NAME               3 (as_string)

145          22 LOAD_CONST               5 ('int')
             24 LOAD_CONST               2 (('return',))
             26 BUILD_CONST_KEY_MAP      1
             28 LOAD_CONST               6 (<code object arg_count at 0x100e57d40, file "./interp.py", line 145>)
             30 LOAD_CONST               7 ('Int.arg_count')
             32 MAKE_FUNCTION            4 (annotations)
             34 STORE_NAME               4 (arg_count)

148          36 LOAD_CONST               8 ('Interpreter')
             38 LOAD_CONST               9 ('list[Object]')
             40 LOAD_CONST              10 ('Object')
             42 LOAD_CONST              11 (('_', 'args', 'return'))
             44 BUILD_CONST_KEY_MAP      3
             46 LOAD_CLOSURE             0 (__class__)
             48 BUILD_TUPLE              1
             50 LOAD_CONST              12 (<code object call at 0x100e57df0, file "./interp.py", line 148>)
             52 LOAD_CONST              13 ('Int.call')
             54 MAKE_FUNCTION           12 (annotations, closure)
             56 STORE_NAME               5 (call)
             58 LOAD_CLOSURE             0 (__class__)
             60 DUP_TOP
             62 STORE_NAME               6 (__classcell__)
             64 RETURN_VALUE

Disassembly of <code object as_string at 0x100e57c90, file "./interp.py", line 142>:
143           0 LOAD_CONST               1 ("<function 'int'>")
              2 RETURN_VALUE

Disassembly of <code object arg_count at 0x100e57d40, file "./interp.py", line 145>:
146           0 LOAD_CONST               1 (1)
              2 RETURN_VALUE

Disassembly of <code object call at 0x100e57df0, file "./interp.py", line 148>:
149           0 LOAD_GLOBAL              0 (super)
              2 CALL_FUNCTION            0
              4 LOAD_METHOD              1 (ensure_args)
              6 LOAD_FAST                2 (args)
              8 CALL_METHOD              1
             10 POP_TOP

151          12 LOAD_FAST                2 (args)
             14 LOAD_CONST               1 (0)
             16 BINARY_SUBSCR
             18 STORE_FAST               3 (item)

152          20 LOAD_GLOBAL              2 (isinstance)
             22 LOAD_FAST                3 (item)
             24 LOAD_GLOBAL              3 (Value)
             26 CALL_FUNCTION            2
             28 POP_JUMP_IF_FALSE       62
             30 LOAD_GLOBAL              2 (isinstance)
             32 LOAD_FAST                3 (item)
             34 LOAD_ATTR                4 (value)
             36 LOAD_GLOBAL              5 (int)
             38 LOAD_GLOBAL              6 (str)
             40 LOAD_GLOBAL              7 (float)
             42 BUILD_TUPLE              3
             44 CALL_FUNCTION            2
             46 POP_JUMP_IF_FALSE       62

153          48 LOAD_GLOBAL              3 (Value)
             50 LOAD_GLOBAL              5 (int)
             52 LOAD_FAST                3 (item)
             54 LOAD_ATTR                4 (value)
             56 CALL_FUNCTION            1
             58 CALL_FUNCTION            1
             60 RETURN_VALUE

155     >>   62 LOAD_GLOBAL              8 (InterpreterError)
             64 LOAD_CONST               2 ('Invalid type for int(): ')
             66 LOAD_GLOBAL              9 (type)
             68 LOAD_FAST                3 (item)
             70 CALL_FUNCTION            1
             72 LOAD_ATTR               10 (__name__)
             74 FORMAT_VALUE             0
             76 BUILD_STRING             2
             78 CALL_FUNCTION            1
             80 RAISE_VARARGS            1
             82 LOAD_CONST               0 (None)
             84 RETURN_VALUE

Disassembly of <code object Float at 0x100e53190, file "./interp.py", line 158>:
158           0 LOAD_NAME                0 (__name__)
              2 STORE_NAME               1 (__module__)
              4 LOAD_CONST               0 ('Float')
              6 STORE_NAME               2 (__qualname__)

159           8 LOAD_CONST               1 ('str')
             10 LOAD_CONST               2 (('return',))
             12 BUILD_CONST_KEY_MAP      1
             14 LOAD_CONST               3 (<code object as_string at 0x100e57f50, file "./interp.py", line 159>)
             16 LOAD_CONST               4 ('Float.as_string')
             18 MAKE_FUNCTION            4 (annotations)
             20 STORE_NAME               3 (as_string)

162          22 LOAD_CONST               5 ('int')
             24 LOAD_CONST               2 (('return',))
             26 BUILD_CONST_KEY_MAP      1
             28 LOAD_CONST               6 (<code object arg_count at 0x100e53030, file "./interp.py", line 162>)
             30 LOAD_CONST               7 ('Float.arg_count')
             32 MAKE_FUNCTION            4 (annotations)
             34 STORE_NAME               4 (arg_count)

165          36 LOAD_CONST               8 ('Interpreter')
             38 LOAD_CONST               9 ('list[Object]')
             40 LOAD_CONST              10 ('Object')
             42 LOAD_CONST              11 (('_', 'args', 'return'))
             44 BUILD_CONST_KEY_MAP      3
             46 LOAD_CLOSURE             0 (__class__)
             48 BUILD_TUPLE              1
             50 LOAD_CONST              12 (<code object call at 0x100e530e0, file "./interp.py", line 165>)
             52 LOAD_CONST              13 ('Float.call')
             54 MAKE_FUNCTION           12 (annotations, closure)
             56 STORE_NAME               5 (call)
             58 LOAD_CLOSURE             0 (__class__)
             60 DUP_TOP
             62 STORE_NAME               6 (__classcell__)
             64 RETURN_VALUE

Disassembly of <code object as_string at 0x100e57f50, file "./interp.py", line 159>:
160           0 LOAD_CONST               1 ("<function 'float'>")
              2 RETURN_VALUE

Disassembly of <code object arg_count at 0x100e53030, file "./interp.py", line 162>:
163           0 LOAD_CONST               1 (1)
              2 RETURN_VALUE

Disassembly of <code object call at 0x100e530e0, file "./interp.py", line 165>:
166           0 LOAD_GLOBAL              0 (super)
              2 CALL_FUNCTION            0
              4 LOAD_METHOD              1 (ensure_args)
              6 LOAD_FAST                2 (args)
              8 CALL_METHOD              1
             10 POP_TOP

168          12 LOAD_FAST                2 (args)
             14 LOAD_CONST               1 (0)
             16 BINARY_SUBSCR
             18 STORE_FAST               3 (item)

169          20 LOAD_GLOBAL              2 (isinstance)
             22 LOAD_FAST                3 (item)
             24 LOAD_GLOBAL              3 (Value)
             26 CALL_FUNCTION            2
             28 POP_JUMP_IF_FALSE       62
             30 LOAD_GLOBAL              2 (isinstance)
             32 LOAD_FAST                3 (item)
             34 LOAD_ATTR                4 (value)
             36 LOAD_GLOBAL              5 (int)
             38 LOAD_GLOBAL              6 (str)
             40 LOAD_GLOBAL              7 (float)
             42 BUILD_TUPLE              3
             44 CALL_FUNCTION            2
             46 POP_JUMP_IF_FALSE       62

170          48 LOAD_GLOBAL              3 (Value)
             50 LOAD_GLOBAL              7 (float)
             52 LOAD_FAST                3 (item)
             54 LOAD_ATTR                4 (value)
             56 CALL_FUNCTION            1
             58 CALL_FUNCTION            1
             60 RETURN_VALUE

172     >>   62 LOAD_GLOBAL              8 (InterpreterError)
             64 LOAD_CONST               2 ('Invalid type for float(): ')
             66 LOAD_GLOBAL              9 (type)
             68 LOAD_FAST                3 (item)
             70 CALL_FUNCTION            1
             72 LOAD_ATTR               10 (__name__)
             74 FORMAT_VALUE             0
             76 BUILD_STRING             2
             78 CALL_FUNCTION            1
             80 RAISE_VARARGS            1
             82 LOAD_CONST               0 (None)
             84 RETURN_VALUE

Disassembly of <code object Break at 0x100e53240, file "./interp.py", line 175>:
175           0 LOAD_NAME                0 (__name__)
              2 STORE_NAME               1 (__module__)
              4 LOAD_CONST               0 ('Break')
              6 STORE_NAME               2 (__qualname__)

176           8 LOAD_CONST               1 ('This is thrown when a loop breaks.')
             10 STORE_NAME               3 (__doc__)
             12 LOAD_CONST               2 (None)
             14 RETURN_VALUE

Disassembly of <code object Continue at 0x100e532f0, file "./interp.py", line 179>:
179           0 LOAD_NAME                0 (__name__)
              2 STORE_NAME               1 (__module__)
              4 LOAD_CONST               0 ('Continue')
              6 STORE_NAME               2 (__qualname__)

180           8 LOAD_CONST               1 ('This is thrown when a loop continues.')
             10 STORE_NAME               3 (__doc__)
             12 LOAD_CONST               2 (None)
             14 RETURN_VALUE

Disassembly of <code object Return at 0x100e53450, file "./interp.py", line 183>:
183           0 LOAD_NAME                0 (__name__)
              2 STORE_NAME               1 (__module__)
              4 LOAD_CONST               0 ('Return')
              6 STORE_NAME               2 (__qualname__)

184           8 LOAD_CONST               1 ('This is thrown when something returns a value.')
             10 STORE_NAME               3 (__doc__)

186          12 LOAD_CONST               2 ('Object')
             14 LOAD_CONST               3 ('None')
             16 LOAD_CONST               4 (('value', 'return'))
             18 BUILD_CONST_KEY_MAP      2
             20 LOAD_CONST               5 (<code object __init__ at 0x100e533a0, file "./interp.py", line 186>)
             22 LOAD_CONST               6 ('Return.__init__')
             24 MAKE_FUNCTION            4 (annotations)
             26 STORE_NAME               4 (__init__)
             28 LOAD_CONST               7 (None)
             30 RETURN_VALUE

Disassembly of <code object __init__ at 0x100e533a0, file "./interp.py", line 186>:
187           0 LOAD_FAST                1 (value)
              2 LOAD_FAST                0 (self)
              4 STORE_ATTR               0 (value)
              6 LOAD_CONST               0 (None)
              8 RETURN_VALUE

Disassembly of <code object UserFunction at 0x100e537c0, file "./interp.py", line 190>:
190           0 LOAD_NAME                0 (__name__)
              2 STORE_NAME               1 (__module__)
              4 LOAD_CONST               0 ('UserFunction')
              6 STORE_NAME               2 (__qualname__)

191           8 LOAD_CONST               1 ('FunctionDef')
             10 LOAD_CONST               2 ('Scope')
             12 LOAD_CONST               2 ('Scope')
             14 LOAD_CONST               3 ('None')
             16 LOAD_CONST               4 (('definition', 'parent_scope', 'current_globals', 'return'))
             18 BUILD_CONST_KEY_MAP      4
             20 LOAD_CONST               5 (<code object __init__ at 0x100e53500, file "./interp.py", line 191>)
             22 LOAD_CONST               6 ('UserFunction.__init__')
             24 MAKE_FUNCTION            4 (annotations)
             26 STORE_NAME               3 (__init__)

201          28 LOAD_CONST               7 ('str')
             30 LOAD_CONST               8 (('return',))
             32 BUILD_CONST_KEY_MAP      1
             34 LOAD_CONST               9 (<code object as_string at 0x100e535b0, file "./interp.py", line 201>)
             36 LOAD_CONST              10 ('UserFunction.as_string')
             38 MAKE_FUNCTION            4 (annotations)
             40 STORE_NAME               4 (as_string)

204          42 LOAD_CONST              11 ('int')
             44 LOAD_CONST               8 (('return',))
             46 BUILD_CONST_KEY_MAP      1
             48 LOAD_CONST              12 (<code object arg_count at 0x100e53660, file "./interp.py", line 204>)
             50 LOAD_CONST              13 ('UserFunction.arg_count')
             52 MAKE_FUNCTION            4 (annotations)
             54 STORE_NAME               5 (arg_count)

207          56 LOAD_CONST              14 ('Interpreter')
             58 LOAD_CONST              15 ('list[Object]')
             60 LOAD_CONST              16 ('Object')
             62 LOAD_CONST              17 (('interpreter', 'args', 'return'))
             64 BUILD_CONST_KEY_MAP      3
             66 LOAD_CLOSURE             0 (__class__)
             68 BUILD_TUPLE              1
             70 LOAD_CONST              18 (<code object call at 0x100e53710, file "./interp.py", line 207>)
             72 LOAD_CONST              19 ('UserFunction.call')
             74 MAKE_FUNCTION           12 (annotations, closure)
             76 STORE_NAME               6 (call)
             78 LOAD_CLOSURE             0 (__class__)
             80 DUP_TOP
             82 STORE_NAME               7 (__classcell__)
             84 RETURN_VALUE

Disassembly of <code object __init__ at 0x100e53500, file "./interp.py", line 191>:
197           0 LOAD_FAST                1 (definition)
              2 LOAD_FAST                0 (self)
              4 STORE_ATTR               0 (definition)

198           6 LOAD_FAST                2 (parent_scope)
              8 LOAD_FAST                0 (self)
             10 STORE_ATTR               1 (parent_scope)

199          12 LOAD_FAST                3 (current_globals)
             14 LOAD_FAST                0 (self)
             16 STORE_ATTR               2 (current_globals)
             18 LOAD_CONST               0 (None)
             20 RETURN_VALUE

Disassembly of <code object as_string at 0x100e535b0, file "./interp.py", line 201>:
202           0 LOAD_CONST               1 ('<function ')
              2 LOAD_FAST                0 (self)
              4 LOAD_ATTR                0 (definition)
              6 LOAD_ATTR                1 (name)
              8 FORMAT_VALUE             2 (repr)
             10 LOAD_CONST               2 ('>')
             12 BUILD_STRING             3
             14 RETURN_VALUE

Disassembly of <code object arg_count at 0x100e53660, file "./interp.py", line 204>:
205           0 LOAD_GLOBAL              0 (len)
              2 LOAD_FAST                0 (self)
              4 LOAD_ATTR                1 (definition)
              6 LOAD_ATTR                2 (params)
              8 CALL_FUNCTION            1
             10 RETURN_VALUE

Disassembly of <code object call at 0x100e53710, file "./interp.py", line 207>:
208           0 LOAD_GLOBAL              0 (super)
              2 CALL_FUNCTION            0
              4 LOAD_METHOD              1 (ensure_args)
              6 LOAD_FAST                2 (args)
              8 CALL_METHOD              1
             10 POP_TOP

210          12 LOAD_FAST                1 (interpreter)
             14 LOAD_ATTR                2 (scope)
             16 STORE_FAST               3 (current_scope)

211          18 LOAD_FAST                1 (interpreter)
             20 LOAD_ATTR                3 (globals)
             22 STORE_FAST               4 (parent_globals)

213          24 LOAD_GLOBAL              4 (Scope)
             26 LOAD_FAST                0 (self)
             28 LOAD_ATTR                5 (parent_scope)
             30 LOAD_CONST               1 (('parent',))
             32 CALL_FUNCTION_KW         1
             34 STORE_FAST               5 (function_scope)

214          36 LOAD_FAST                0 (self)
             38 LOAD_ATTR                6 (current_globals)
             40 LOAD_FAST                1 (interpreter)
             42 STORE_ATTR               3 (globals)

215          44 LOAD_FAST                5 (function_scope)
             46 LOAD_FAST                1 (interpreter)
             48 STORE_ATTR               2 (scope)

217          50 LOAD_GLOBAL              7 (zip)
             52 LOAD_FAST                0 (self)
             54 LOAD_ATTR                8 (definition)
             56 LOAD_ATTR                9 (params)
             58 LOAD_FAST                2 (args)
             60 CALL_FUNCTION            2
             62 GET_ITER
        >>   64 FOR_ITER                20 (to 86)
             66 UNPACK_SEQUENCE          2
             68 STORE_FAST               6 (param)
             70 STORE_FAST               7 (arg)

218          72 LOAD_FAST                5 (function_scope)
             74 LOAD_METHOD             10 (set)
             76 LOAD_FAST                6 (param)
             78 LOAD_FAST                7 (arg)
             80 CALL_METHOD              2
             82 POP_TOP
             84 JUMP_ABSOLUTE           64

220     >>   86 SETUP_FINALLY          102 (to 190)
             88 SETUP_FINALLY           28 (to 118)

221          90 LOAD_FAST                0 (self)
             92 LOAD_ATTR                8 (definition)
             94 LOAD_ATTR               11 (body)
             96 GET_ITER
        >>   98 FOR_ITER                14 (to 114)
            100 STORE_FAST               8 (statement)

222         102 LOAD_FAST                1 (interpreter)
            104 LOAD_METHOD             12 (visit)
            106 LOAD_FAST                8 (statement)
            108 CALL_METHOD              1
            110 POP_TOP
            112 JUMP_ABSOLUTE           98
        >>  114 POP_BLOCK
            116 JUMP_FORWARD            56 (to 174)

224     >>  118 DUP_TOP
            120 LOAD_GLOBAL             13 (Return)
            122 JUMP_IF_NOT_EXC_MATCH   172
            124 POP_TOP
            126 STORE_FAST               9 (ret)
            128 POP_TOP
            130 SETUP_FINALLY           32 (to 164)

225         132 LOAD_FAST                9 (ret)
            134 LOAD_ATTR               14 (value)
            136 POP_BLOCK
            138 ROT_FOUR
            140 POP_EXCEPT
            142 LOAD_CONST               0 (None)
            144 STORE_FAST               9 (ret)
            146 DELETE_FAST              9 (ret)
            148 POP_BLOCK

228         150 LOAD_FAST                3 (current_scope)
            152 LOAD_FAST                1 (interpreter)
            154 STORE_ATTR               2 (scope)

229         156 LOAD_FAST                4 (parent_globals)
            158 LOAD_FAST                1 (interpreter)
            160 STORE_ATTR               3 (globals)

225         162 RETURN_VALUE
        >>  164 LOAD_CONST               0 (None)
            166 STORE_FAST               9 (ret)
            168 DELETE_FAST              9 (ret)
            170 RERAISE
        >>  172 RERAISE
        >>  174 POP_BLOCK

228         176 LOAD_FAST                3 (current_scope)
            178 LOAD_FAST                1 (interpreter)
            180 STORE_ATTR               2 (scope)

229         182 LOAD_FAST                4 (parent_globals)
            184 LOAD_FAST                1 (interpreter)
            186 STORE_ATTR               3 (globals)
            188 JUMP_FORWARD            14 (to 204)

228     >>  190 LOAD_FAST                3 (current_scope)
            192 LOAD_FAST                1 (interpreter)
            194 STORE_ATTR               2 (scope)

229         196 LOAD_FAST                4 (parent_globals)
            198 LOAD_FAST                1 (interpreter)
            200 STORE_ATTR               3 (globals)
            202 RERAISE

231     >>  204 LOAD_GLOBAL             15 (Value)
            206 LOAD_CONST               0 (None)
            208 CALL_FUNCTION            1
            210 RETURN_VALUE

Disassembly of <code object DequeConstructor at 0x100e53a80, file "./interp.py", line 234>:
234           0 LOAD_NAME                0 (__name__)
              2 STORE_NAME               1 (__module__)
              4 LOAD_CONST               0 ('DequeConstructor')
              6 STORE_NAME               2 (__qualname__)

235           8 LOAD_CONST               1 ('str')
             10 LOAD_CONST               2 (('return',))
             12 BUILD_CONST_KEY_MAP      1
             14 LOAD_CONST               3 (<code object as_string at 0x100e53870, file "./interp.py", line 235>)
             16 LOAD_CONST               4 ('DequeConstructor.as_string')
             18 MAKE_FUNCTION            4 (annotations)
             20 STORE_NAME               3 (as_string)

238          22 LOAD_CONST               5 ('int')
             24 LOAD_CONST               2 (('return',))
             26 BUILD_CONST_KEY_MAP      1
             28 LOAD_CONST               6 (<code object arg_count at 0x100e53920, file "./interp.py", line 238>)
             30 LOAD_CONST               7 ('DequeConstructor.arg_count')
             32 MAKE_FUNCTION            4 (annotations)
             34 STORE_NAME               4 (arg_count)

241          36 LOAD_CONST               8 ('Interpreter')
             38 LOAD_CONST               9 ('list[Object]')
             40 LOAD_CONST              10 ('None')
             42 LOAD_CONST              11 (('_', 'args', 'return'))
             44 BUILD_CONST_KEY_MAP      3
             46 LOAD_CLOSURE             0 (__class__)
             48 BUILD_TUPLE              1
             50 LOAD_CONST              12 (<code object call at 0x100e539d0, file "./interp.py", line 241>)
             52 LOAD_CONST              13 ('DequeConstructor.call')
             54 MAKE_FUNCTION           12 (annotations, closure)
             56 STORE_NAME               5 (call)
             58 LOAD_CLOSURE             0 (__class__)
             60 DUP_TOP
             62 STORE_NAME               6 (__classcell__)
             64 RETURN_VALUE

Disassembly of <code object as_string at 0x100e53870, file "./interp.py", line 235>:
236           0 LOAD_CONST               1 ("<function 'deque'>")
              2 RETURN_VALUE

Disassembly of <code object arg_count at 0x100e53920, file "./interp.py", line 238>:
239           0 LOAD_CONST               1 (0)
              2 RETURN_VALUE

Disassembly of <code object call at 0x100e539d0, file "./interp.py", line 241>:
242           0 LOAD_GLOBAL              0 (super)
              2 CALL_FUNCTION            0
              4 LOAD_METHOD              1 (ensure_args)
              6 LOAD_FAST                2 (args)
              8 CALL_METHOD              1
             10 POP_TOP

243          12 LOAD_GLOBAL              2 (Deque)
             14 CALL_FUNCTION            0
             16 RETURN_VALUE

Disassembly of <code object Deque at 0x100e53d40, file "./interp.py", line 246>:
246           0 LOAD_NAME                0 (__name__)
              2 STORE_NAME               1 (__module__)
              4 LOAD_CONST               0 ('Deque')
              6 STORE_NAME               2 (__qualname__)

247           8 LOAD_CONST               1 ('None')
             10 LOAD_CONST               2 (('return',))
             12 BUILD_CONST_KEY_MAP      1
             14 LOAD_CLOSURE             0 (__class__)
             16 BUILD_TUPLE              1
             18 LOAD_CONST               3 (<code object __init__ at 0x100e53b30, file "./interp.py", line 247>)
             20 LOAD_CONST               4 ('Deque.__init__')
             22 MAKE_FUNCTION           12 (annotations, closure)
             24 STORE_NAME               3 (__init__)

255          26 LOAD_CONST               5 ('str')
             28 LOAD_CONST               2 (('return',))
             30 BUILD_CONST_KEY_MAP      1
             32 LOAD_CONST               6 (<code object as_string at 0x100e53c90, file "./interp.py", line 255>)
             34 LOAD_CONST               7 ('Deque.as_string')
             36 MAKE_FUNCTION            4 (annotations)
             38 STORE_NAME               4 (as_string)
             40 LOAD_CLOSURE             0 (__class__)
             42 DUP_TOP
             44 STORE_NAME               5 (__classcell__)
             46 RETURN_VALUE

Disassembly of <code object __init__ at 0x100e53b30, file "./interp.py", line 247>:
248           0 LOAD_GLOBAL              0 (super)
              2 CALL_FUNCTION            0
              4 LOAD_METHOD              1 (__init__)
              6 CALL_METHOD              0
              8 POP_TOP

250          10 LOAD_GLOBAL              2 (deque)
             12 CALL_FUNCTION            0
             14 LOAD_FAST                0 (self)
             16 STORE_ATTR               3 (_data)

252          18 LOAD_GLOBAL              4 (Append)
             20 LOAD_FAST                0 (self)
             22 CALL_FUNCTION            1
             24 LOAD_FAST                0 (self)
             26 LOAD_ATTR                5 (methods)
             28 LOAD_CONST               1 ('append')
             30 STORE_SUBSCR

253          32 LOAD_GLOBAL              6 (PopLeft)
             34 LOAD_FAST                0 (self)
             36 CALL_FUNCTION            1
             38 LOAD_FAST                0 (self)
             40 LOAD_ATTR                5 (methods)
             42 LOAD_CONST               2 ('popleft')
             44 STORE_SUBSCR
             46 LOAD_CONST               0 (None)
             48 RETURN_VALUE

Disassembly of <code object as_string at 0x100e53c90, file "./interp.py", line 255>:
256           0 LOAD_CONST               1 ('<deque [')
              2 LOAD_CONST               2 (', ')
              4 LOAD_METHOD              0 (join)
              6 LOAD_CONST               3 (<code object <genexpr> at 0x100e53be0, file "./interp.py", line 256>)
              8 LOAD_CONST               4 ('Deque.as_string.<locals>.<genexpr>')
             10 MAKE_FUNCTION            0
             12 LOAD_FAST                0 (self)
             14 LOAD_ATTR                1 (_data)
             16 GET_ITER
             18 CALL_FUNCTION            1
             20 CALL_METHOD              1
             22 BINARY_ADD
             24 LOAD_CONST               5 (']>')
             26 BINARY_ADD
             28 RETURN_VALUE

Disassembly of <code object <genexpr> at 0x100e53be0, file "./interp.py", line 256>:
256           0 LOAD_FAST                0 (.0)
        >>    2 FOR_ITER                14 (to 18)
              4 STORE_FAST               1 (item)
              6 LOAD_FAST                1 (item)
              8 LOAD_METHOD              0 (repr)
             10 CALL_METHOD              0
             12 YIELD_VALUE
             14 POP_TOP
             16 JUMP_ABSOLUTE            2
        >>   18 LOAD_CONST               0 (None)
             20 RETURN_VALUE

Disassembly of <code object Append at 0x100e3e0e0, file "./interp.py", line 259>:
259           0 LOAD_NAME                0 (__name__)
              2 STORE_NAME               1 (__module__)
              4 LOAD_CONST               0 ('Append')
              6 STORE_NAME               2 (__qualname__)

260           8 LOAD_CONST               1 ('List | Deque')
             10 LOAD_CONST               2 ('None')
             12 LOAD_CONST               3 (('wrapper', 'return'))
             14 BUILD_CONST_KEY_MAP      2
             16 LOAD_CLOSURE             0 (__class__)
             18 BUILD_TUPLE              1
             20 LOAD_CONST               4 (<code object __init__ at 0x100e53df0, file "./interp.py", line 260>)
             22 LOAD_CONST               5 ('Append.__init__')
             24 MAKE_FUNCTION           12 (annotations, closure)
             26 STORE_NAME               3 (__init__)

264          28 LOAD_CONST               6 ('str')
             30 LOAD_CONST               7 (('return',))
             32 BUILD_CONST_KEY_MAP      1
             34 LOAD_CONST               8 (<code object as_string at 0x100e53ea0, file "./interp.py", line 264>)
             36 LOAD_CONST               9 ('Append.as_string')
             38 MAKE_FUNCTION            4 (annotations)
             40 STORE_NAME               4 (as_string)

267          42 LOAD_CONST              10 ('int')
             44 LOAD_CONST               7 (('return',))
             46 BUILD_CONST_KEY_MAP      1
             48 LOAD_CONST              11 (<code object arg_count at 0x100e53f50, file "./interp.py", line 267>)
             50 LOAD_CONST              12 ('Append.arg_count')
             52 MAKE_FUNCTION            4 (annotations)
             54 STORE_NAME               5 (arg_count)

270          56 LOAD_CONST              13 ('Interpreter')
             58 LOAD_CONST              14 ('list[Object]')
             60 LOAD_CONST               2 ('None')
             62 LOAD_CONST              15 (('_', 'args', 'return'))
             64 BUILD_CONST_KEY_MAP      3
             66 LOAD_CLOSURE             0 (__class__)
             68 BUILD_TUPLE              1
             70 LOAD_CONST              16 (<code object call at 0x100e3e030, file "./interp.py", line 270>)
             72 LOAD_CONST              17 ('Append.call')
             74 MAKE_FUNCTION           12 (annotations, closure)
             76 STORE_NAME               6 (call)
             78 LOAD_CLOSURE             0 (__class__)
             80 DUP_TOP
             82 STORE_NAME               7 (__classcell__)
             84 RETURN_VALUE

Disassembly of <code object __init__ at 0x100e53df0, file "./interp.py", line 260>:
261           0 LOAD_GLOBAL              0 (super)
              2 CALL_FUNCTION            0
              4 LOAD_METHOD              1 (__init__)
              6 CALL_METHOD              0
              8 POP_TOP

262          10 LOAD_FAST                1 (wrapper)
             12 LOAD_FAST                0 (self)
             14 STORE_ATTR               2 (wrapper)
             16 LOAD_CONST               0 (None)
             18 RETURN_VALUE

Disassembly of <code object as_string at 0x100e53ea0, file "./interp.py", line 264>:
265           0 LOAD_CONST               1 ("<method 'append' of ")
              2 LOAD_FAST                0 (self)
              4 LOAD_ATTR                0 (wrapper)
              6 LOAD_METHOD              1 (repr)
              8 CALL_METHOD              0
             10 FORMAT_VALUE             0
             12 LOAD_CONST               2 ('>')
             14 BUILD_STRING             3
             16 RETURN_VALUE

Disassembly of <code object arg_count at 0x100e53f50, file "./interp.py", line 267>:
268           0 LOAD_CONST               1 (1)
              2 RETURN_VALUE

Disassembly of <code object call at 0x100e3e030, file "./interp.py", line 270>:
271           0 LOAD_GLOBAL              0 (super)
              2 CALL_FUNCTION            0
              4 LOAD_METHOD              1 (ensure_args)
              6 LOAD_FAST                2 (args)
              8 CALL_METHOD              1
             10 POP_TOP

272          12 LOAD_FAST                2 (args)
             14 LOAD_CONST               1 (0)
             16 BINARY_SUBSCR
             18 STORE_FAST               3 (item)

273          20 LOAD_FAST                0 (self)
             22 LOAD_ATTR                2 (wrapper)
             24 LOAD_ATTR                3 (_data)
             26 LOAD_METHOD              4 (append)
             28 LOAD_FAST                3 (item)
             30 CALL_METHOD              1
             32 POP_TOP
             34 LOAD_CONST               0 (None)
             36 RETURN_VALUE

Disassembly of <code object Items at 0x100e3e500, file "./interp.py", line 276>:
276           0 LOAD_NAME                0 (__name__)
              2 STORE_NAME               1 (__module__)
              4 LOAD_CONST               0 ('Items')
              6 STORE_NAME               2 (__qualname__)

277           8 LOAD_CONST               1 ('Dict')
             10 LOAD_CONST               2 ('None')
             12 LOAD_CONST               3 (('wrapper', 'return'))
             14 BUILD_CONST_KEY_MAP      2
             16 LOAD_CLOSURE             0 (__class__)
             18 BUILD_TUPLE              1
             20 LOAD_CONST               4 (<code object __init__ at 0x100e3e190, file "./interp.py", line 277>)
             22 LOAD_CONST               5 ('Items.__init__')
             24 MAKE_FUNCTION           12 (annotations, closure)
             26 STORE_NAME               3 (__init__)

281          28 LOAD_CONST               6 ('str')
             30 LOAD_CONST               7 (('return',))
             32 BUILD_CONST_KEY_MAP      1
             34 LOAD_CONST               8 (<code object as_string at 0x100e3e240, file "./interp.py", line 281>)
             36 LOAD_CONST               9 ('Items.as_string')
             38 MAKE_FUNCTION            4 (annotations)
             40 STORE_NAME               4 (as_string)

284          42 LOAD_CONST              10 ('int')
             44 LOAD_CONST               7 (('return',))
             46 BUILD_CONST_KEY_MAP      1
             48 LOAD_CONST              11 (<code object arg_count at 0x100e3e2f0, file "./interp.py", line 284>)
             50 LOAD_CONST              12 ('Items.arg_count')
             52 MAKE_FUNCTION            4 (annotations)
             54 STORE_NAME               5 (arg_count)

287          56 LOAD_CONST              13 ('Interpreter')
             58 LOAD_CONST              14 ('list[Object]')
             60 LOAD_CONST              15 ('Any')
             62 LOAD_CONST              16 (('_', 'args', 'return'))
             64 BUILD_CONST_KEY_MAP      3
             66 LOAD_CLOSURE             0 (__class__)
             68 BUILD_TUPLE              1
             70 LOAD_CONST              17 (<code object call at 0x100e3e450, file "./interp.py", line 287>)
             72 LOAD_CONST              18 ('Items.call')
             74 MAKE_FUNCTION           12 (annotations, closure)
             76 STORE_NAME               6 (call)
             78 LOAD_CLOSURE             0 (__class__)
             80 DUP_TOP
             82 STORE_NAME               7 (__classcell__)
             84 RETURN_VALUE

Disassembly of <code object __init__ at 0x100e3e190, file "./interp.py", line 277>:
278           0 LOAD_GLOBAL              0 (super)
              2 CALL_FUNCTION            0
              4 LOAD_METHOD              1 (__init__)
              6 CALL_METHOD              0
              8 POP_TOP

279          10 LOAD_FAST                1 (wrapper)
             12 LOAD_FAST                0 (self)
             14 STORE_ATTR               2 (wrapper)
             16 LOAD_CONST               0 (None)
             18 RETURN_VALUE

Disassembly of <code object as_string at 0x100e3e240, file "./interp.py", line 281>:
282           0 LOAD_CONST               1 ("<method 'items' of ")
              2 LOAD_FAST                0 (self)
              4 LOAD_ATTR                0 (wrapper)
              6 LOAD_METHOD              1 (repr)
              8 CALL_METHOD              0
             10 FORMAT_VALUE             0
             12 LOAD_CONST               2 ('>')
             14 BUILD_STRING             3
             16 RETURN_VALUE

Disassembly of <code object arg_count at 0x100e3e2f0, file "./interp.py", line 284>:
285           0 LOAD_CONST               1 (0)
              2 RETURN_VALUE

Disassembly of <code object call at 0x100e3e450, file "./interp.py", line 287>:
288           0 LOAD_GLOBAL              0 (super)
              2 CALL_FUNCTION            0
              4 LOAD_METHOD              1 (ensure_args)
              6 LOAD_FAST                2 (args)
              8 CALL_METHOD              1
             10 POP_TOP

290          12 LOAD_CONST               1 (<code object <listcomp> at 0x100e3e3a0, file "./interp.py", line 290>)
             14 LOAD_CONST               2 ('Items.call.<locals>.<listcomp>')
             16 MAKE_FUNCTION            0
             18 LOAD_FAST                0 (self)
             20 LOAD_ATTR                2 (wrapper)
             22 LOAD_ATTR                3 (_dict)
             24 LOAD_METHOD              4 (items)
             26 CALL_METHOD              0
             28 GET_ITER
             30 CALL_FUNCTION            1
             32 STORE_FAST               3 (pairs)

291          34 LOAD_GLOBAL              5 (List)
             36 LOAD_FAST                3 (pairs)
             38 CALL_FUNCTION            1
             40 RETURN_VALUE

Disassembly of <code object <listcomp> at 0x100e3e3a0, file "./interp.py", line 290>:
290           0 BUILD_LIST               0
              2 LOAD_FAST                0 (.0)
        >>    4 FOR_ITER                12 (to 18)
              6 STORE_FAST               1 (key_value_pair)
              8 LOAD_GLOBAL              0 (Tuple)
             10 LOAD_FAST                1 (key_value_pair)
             12 CALL_FUNCTION            1
             14 LIST_APPEND              2
             16 JUMP_ABSOLUTE            4
        >>   18 RETURN_VALUE

Disassembly of <code object PopLeft at 0x100e3e870, file "./interp.py", line 294>:
294           0 LOAD_NAME                0 (__name__)
              2 STORE_NAME               1 (__module__)
              4 LOAD_CONST               0 ('PopLeft')
              6 STORE_NAME               2 (__qualname__)

295           8 LOAD_CONST               1 ('Deque')
             10 LOAD_CONST               2 ('None')
             12 LOAD_CONST               3 (('deque', 'return'))
             14 BUILD_CONST_KEY_MAP      2
             16 LOAD_CLOSURE             0 (__class__)
             18 BUILD_TUPLE              1
             20 LOAD_CONST               4 (<code object __init__ at 0x100e3e5b0, file "./interp.py", line 295>)
             22 LOAD_CONST               5 ('PopLeft.__init__')
             24 MAKE_FUNCTION           12 (annotations, closure)
             26 STORE_NAME               3 (__init__)

299          28 LOAD_CONST               6 ('str')
             30 LOAD_CONST               7 (('return',))
             32 BUILD_CONST_KEY_MAP      1
             34 LOAD_CONST               8 (<code object as_string at 0x100e3e660, file "./interp.py", line 299>)
             36 LOAD_CONST               9 ('PopLeft.as_string')
             38 MAKE_FUNCTION            4 (annotations)
             40 STORE_NAME               4 (as_string)

302          42 LOAD_CONST              10 ('int')
             44 LOAD_CONST               7 (('return',))
             46 BUILD_CONST_KEY_MAP      1
             48 LOAD_CONST              11 (<code object arg_count at 0x100e3e710, file "./interp.py", line 302>)
             50 LOAD_CONST              12 ('PopLeft.arg_count')
             52 MAKE_FUNCTION            4 (annotations)
             54 STORE_NAME               5 (arg_count)

305          56 LOAD_CONST              13 ('Interpreter')
             58 LOAD_CONST              14 ('list[Object]')
             60 LOAD_CONST               2 ('None')
             62 LOAD_CONST              15 (('_', 'args', 'return'))
             64 BUILD_CONST_KEY_MAP      3
             66 LOAD_CLOSURE             0 (__class__)
             68 BUILD_TUPLE              1
             70 LOAD_CONST              16 (<code object call at 0x100e3e7c0, file "./interp.py", line 305>)
             72 LOAD_CONST              17 ('PopLeft.call')
             74 MAKE_FUNCTION           12 (annotations, closure)
             76 STORE_NAME               6 (call)
             78 LOAD_CLOSURE             0 (__class__)
             80 DUP_TOP
             82 STORE_NAME               7 (__classcell__)
             84 RETURN_VALUE

Disassembly of <code object __init__ at 0x100e3e5b0, file "./interp.py", line 295>:
296           0 LOAD_GLOBAL              0 (super)
              2 CALL_FUNCTION            0
              4 LOAD_METHOD              1 (__init__)
              6 CALL_METHOD              0
              8 POP_TOP

297          10 LOAD_FAST                1 (deque)
             12 LOAD_FAST                0 (self)
             14 STORE_ATTR               2 (deque)
             16 LOAD_CONST               0 (None)
             18 RETURN_VALUE

Disassembly of <code object as_string at 0x100e3e660, file "./interp.py", line 299>:
300           0 LOAD_CONST               1 ("<method 'popleft' of ")
              2 LOAD_FAST                0 (self)
              4 LOAD_ATTR                0 (deque)
              6 LOAD_METHOD              1 (repr)
              8 CALL_METHOD              0
             10 FORMAT_VALUE             0
             12 LOAD_CONST               2 ('>')
             14 BUILD_STRING             3
             16 RETURN_VALUE

Disassembly of <code object arg_count at 0x100e3e710, file "./interp.py", line 302>:
303           0 LOAD_CONST               1 (0)
              2 RETURN_VALUE

Disassembly of <code object call at 0x100e3e7c0, file "./interp.py", line 305>:
306           0 LOAD_GLOBAL              0 (super)
              2 CALL_FUNCTION            0
              4 LOAD_METHOD              1 (ensure_args)
              6 LOAD_FAST                2 (args)
              8 CALL_METHOD              1
             10 POP_TOP

307          12 LOAD_FAST                0 (self)
             14 LOAD_ATTR                2 (deque)
             16 LOAD_ATTR                3 (_data)
             18 LOAD_METHOD              4 (popleft)
             20 CALL_METHOD              0
             22 RETURN_VALUE

Disassembly of <code object Value at 0x100e3edf0, file "./interp.py", line 310>:
310           0 LOAD_NAME                0 (__name__)
              2 STORE_NAME               1 (__module__)
              4 LOAD_CONST               0 ('Value')
              6 STORE_NAME               2 (__qualname__)

311           8 LOAD_CONST               1 ('Any')
             10 LOAD_CONST               2 ('None')
             12 LOAD_CONST               3 (('value', 'return'))
             14 BUILD_CONST_KEY_MAP      2
             16 LOAD_CLOSURE             0 (__class__)
             18 BUILD_TUPLE              1
             20 LOAD_CONST               4 (<code object __init__ at 0x100e3e920, file "./interp.py", line 311>)
             22 LOAD_CONST               5 ('Value.__init__')
             24 MAKE_FUNCTION           12 (annotations, closure)
             26 STORE_NAME               3 (__init__)

319          28 LOAD_CONST               6 ('Object')
             30 LOAD_CONST               7 ('int')
             32 LOAD_CONST               8 (('other', 'return'))
             34 BUILD_CONST_KEY_MAP      2
             36 LOAD_CONST               9 (<code object __eq__ at 0x100e3e9d0, file "./interp.py", line 319>)
             38 LOAD_CONST              10 ('Value.__eq__')
             40 MAKE_FUNCTION            4 (annotations)
             42 STORE_NAME               4 (__eq__)

325          44 LOAD_CONST               7 ('int')
             46 LOAD_CONST              11 (('return',))
             48 BUILD_CONST_KEY_MAP      1
             50 LOAD_CONST              12 (<code object __hash__ at 0x100e3ea80, file "./interp.py", line 325>)
             52 LOAD_CONST              13 ('Value.__hash__')
             54 MAKE_FUNCTION            4 (annotations)
             56 STORE_NAME               5 (__hash__)

328          58 LOAD_CONST              14 ('str')
             60 LOAD_CONST              11 (('return',))
             62 BUILD_CONST_KEY_MAP      1
             64 LOAD_CONST              15 (<code object __repr__ at 0x100e3eb30, file "./interp.py", line 328>)
             66 LOAD_CONST              16 ('Value.__repr__')
             68 MAKE_FUNCTION            4 (annotations)
             70 STORE_NAME               6 (__repr__)

331          72 LOAD_CONST               2 ('None')
             74 LOAD_CONST              11 (('return',))
             76 BUILD_CONST_KEY_MAP      1
             78 LOAD_CONST              17 (<code object as_string at 0x100e3ebe0, file "./interp.py", line 331>)
             80 LOAD_CONST              18 ('Value.as_string')
             82 MAKE_FUNCTION            4 (annotations)
             84 STORE_NAME               7 (as_string)

334          86 LOAD_CONST               2 ('None')
             88 LOAD_CONST              11 (('return',))
             90 BUILD_CONST_KEY_MAP      1
             92 LOAD_CONST              19 (<code object repr at 0x100e3ec90, file "./interp.py", line 334>)
             94 LOAD_CONST              20 ('Value.repr')
             96 MAKE_FUNCTION            4 (annotations)
             98 STORE_NAME               8 (repr)
            100 LOAD_CLOSURE             0 (__class__)
            102 DUP_TOP
            104 STORE_NAME               9 (__classcell__)
            106 RETURN_VALUE

Disassembly of <code object __init__ at 0x100e3e920, file "./interp.py", line 311>:
312           0 LOAD_GLOBAL              0 (super)
              2 CALL_FUNCTION            0
              4 LOAD_METHOD              1 (__init__)
              6 CALL_METHOD              0
              8 POP_TOP

313          10 LOAD_FAST                1 (value)
             12 LOAD_FAST                0 (self)
             14 STORE_ATTR               2 (value)

314          16 LOAD_GLOBAL              3 (isinstance)
             18 LOAD_FAST                1 (value)
             20 LOAD_GLOBAL              4 (str)
             22 CALL_FUNCTION            2
             24 POP_JUMP_IF_FALSE       68

315          26 LOAD_GLOBAL              5 (IsDigit)
             28 LOAD_FAST                0 (self)
             30 CALL_FUNCTION            1
             32 LOAD_FAST                0 (self)
             34 LOAD_ATTR                6 (methods)
             36 LOAD_CONST               1 ('isdigit')
             38 STORE_SUBSCR

316          40 LOAD_GLOBAL              7 (IsAlpha)
             42 LOAD_FAST                0 (self)
             44 CALL_FUNCTION            1
             46 LOAD_FAST                0 (self)
             48 LOAD_ATTR                6 (methods)
             50 LOAD_CONST               2 ('isalpha')
             52 STORE_SUBSCR

317          54 LOAD_GLOBAL              8 (Join)
             56 LOAD_FAST                0 (self)
             58 CALL_FUNCTION            1
             60 LOAD_FAST                0 (self)
             62 LOAD_ATTR                6 (methods)
             64 LOAD_CONST               3 ('join')
             66 STORE_SUBSCR
        >>   68 LOAD_CONST               0 (None)
             70 RETURN_VALUE

Disassembly of <code object __eq__ at 0x100e3e9d0, file "./interp.py", line 319>:
320           0 LOAD_GLOBAL              0 (isinstance)
              2 LOAD_FAST                1 (other)
              4 LOAD_GLOBAL              1 (Value)
              6 CALL_FUNCTION            2
              8 POP_JUMP_IF_TRUE        14

321          10 LOAD_CONST               1 (False)
             12 RETURN_VALUE

323     >>   14 LOAD_FAST                0 (self)
             16 LOAD_ATTR                2 (value)
             18 LOAD_FAST                1 (other)
             20 LOAD_ATTR                2 (value)
             22 COMPARE_OP               2 (==)
             24 RETURN_VALUE

Disassembly of <code object __hash__ at 0x100e3ea80, file "./interp.py", line 325>:
326           0 LOAD_GLOBAL              0 (hash)
              2 LOAD_FAST                0 (self)
              4 LOAD_ATTR                1 (value)
              6 CALL_FUNCTION            1
              8 RETURN_VALUE

Disassembly of <code object __repr__ at 0x100e3eb30, file "./interp.py", line 328>:
329           0 LOAD_CONST               1 ('Value(')
              2 LOAD_FAST                0 (self)
              4 LOAD_ATTR                0 (value)
              6 FORMAT_VALUE             2 (repr)
              8 LOAD_CONST               2 (')')
             10 BUILD_STRING             3
             12 RETURN_VALUE

Disassembly of <code object as_string at 0x100e3ebe0, file "./interp.py", line 331>:
332           0 LOAD_GLOBAL              0 (str)
              2 LOAD_FAST                0 (self)
              4 LOAD_ATTR                1 (value)
              6 CALL_FUNCTION            1
              8 RETURN_VALUE

Disassembly of <code object repr at 0x100e3ec90, file "./interp.py", line 334>:
335           0 LOAD_GLOBAL              0 (repr)
              2 LOAD_FAST                0 (self)
              4 LOAD_ATTR                1 (value)
              6 CALL_FUNCTION            1
              8 RETURN_VALUE

Disassembly of <code object IsDigit at 0x100e3a0e0, file "./interp.py", line 338>:
338           0 LOAD_NAME                0 (__name__)
              2 STORE_NAME               1 (__module__)
              4 LOAD_CONST               0 ('IsDigit')
              6 STORE_NAME               2 (__qualname__)

339           8 LOAD_CONST               1 ('Value')
             10 LOAD_CONST               2 ('None')
             12 LOAD_CONST               3 (('wrapper', 'return'))
             14 BUILD_CONST_KEY_MAP      2
             16 LOAD_CLOSURE             0 (__class__)
             18 BUILD_TUPLE              1
             20 LOAD_CONST               4 (<code object __init__ at 0x100e3ed40, file "./interp.py", line 339>)
             22 LOAD_CONST               5 ('IsDigit.__init__')
             24 MAKE_FUNCTION           12 (annotations, closure)
             26 STORE_NAME               3 (__init__)

343          28 LOAD_CONST               6 ('str')
             30 LOAD_CONST               7 (('return',))
             32 BUILD_CONST_KEY_MAP      1
             34 LOAD_CONST               8 (<code object as_string at 0x100e3eea0, file "./interp.py", line 343>)
             36 LOAD_CONST               9 ('IsDigit.as_string')
             38 MAKE_FUNCTION            4 (annotations)
             40 STORE_NAME               4 (as_string)

346          42 LOAD_CONST              10 ('int')
             44 LOAD_CONST               7 (('return',))
             46 BUILD_CONST_KEY_MAP      1
             48 LOAD_CONST              11 (<code object arg_count at 0x100e3ef50, file "./interp.py", line 346>)
             50 LOAD_CONST              12 ('IsDigit.arg_count')
             52 MAKE_FUNCTION            4 (annotations)
             54 STORE_NAME               5 (arg_count)

349          56 LOAD_CONST              13 ('Interpreter')
             58 LOAD_CONST              14 ('list[Object]')
             60 LOAD_CONST               1 ('Value')
             62 LOAD_CONST              15 (('_', 'args', 'return'))
             64 BUILD_CONST_KEY_MAP      3
             66 LOAD_CLOSURE             0 (__class__)
             68 BUILD_TUPLE              1
             70 LOAD_CONST              16 (<code object call at 0x100e3a030, file "./interp.py", line 349>)
             72 LOAD_CONST              17 ('IsDigit.call')
             74 MAKE_FUNCTION           12 (annotations, closure)
             76 STORE_NAME               6 (call)
             78 LOAD_CLOSURE             0 (__class__)
             80 DUP_TOP
             82 STORE_NAME               7 (__classcell__)
             84 RETURN_VALUE

Disassembly of <code object __init__ at 0x100e3ed40, file "./interp.py", line 339>:
340           0 LOAD_GLOBAL              0 (super)
              2 CALL_FUNCTION            0
              4 LOAD_METHOD              1 (__init__)
              6 CALL_METHOD              0
              8 POP_TOP

341          10 LOAD_FAST                1 (wrapper)
             12 LOAD_FAST                0 (self)
             14 STORE_ATTR               2 (wrapper)
             16 LOAD_CONST               0 (None)
             18 RETURN_VALUE

Disassembly of <code object as_string at 0x100e3eea0, file "./interp.py", line 343>:
344           0 LOAD_CONST               1 ("<method 'isdigit' of ")
              2 LOAD_FAST                0 (self)
              4 LOAD_ATTR                0 (wrapper)
              6 LOAD_METHOD              1 (repr)
              8 CALL_METHOD              0
             10 FORMAT_VALUE             0
             12 LOAD_CONST               2 ('>')
             14 BUILD_STRING             3
             16 RETURN_VALUE

Disassembly of <code object arg_count at 0x100e3ef50, file "./interp.py", line 346>:
347           0 LOAD_CONST               1 (0)
              2 RETURN_VALUE

Disassembly of <code object call at 0x100e3a030, file "./interp.py", line 349>:
350           0 LOAD_GLOBAL              0 (super)
              2 CALL_FUNCTION            0
              4 LOAD_METHOD              1 (ensure_args)
              6 LOAD_FAST                2 (args)
              8 CALL_METHOD              1
             10 POP_TOP

351          12 LOAD_GLOBAL              2 (Value)
             14 LOAD_FAST                0 (self)
             16 LOAD_ATTR                3 (wrapper)
             18 LOAD_ATTR                4 (value)
             20 LOAD_METHOD              5 (isdigit)
             22 CALL_METHOD              0
             24 CALL_FUNCTION            1
             26 RETURN_VALUE

Disassembly of <code object IsAlpha at 0x100e3a3a0, file "./interp.py", line 354>:
354           0 LOAD_NAME                0 (__name__)
              2 STORE_NAME               1 (__module__)
              4 LOAD_CONST               0 ('IsAlpha')
              6 STORE_NAME               2 (__qualname__)

355           8 LOAD_CONST               1 ('Value')
             10 LOAD_CONST               2 ('None')
             12 LOAD_CONST               3 (('wrapper', 'return'))
             14 BUILD_CONST_KEY_MAP      2
             16 LOAD_CLOSURE             0 (__class__)
             18 BUILD_TUPLE              1
             20 LOAD_CONST               4 (<code object __init__ at 0x100b985b0, file "./interp.py", line 355>)
             22 LOAD_CONST               5 ('IsAlpha.__init__')
             24 MAKE_FUNCTION           12 (annotations, closure)
             26 STORE_NAME               3 (__init__)

359          28 LOAD_CONST               6 ('str')
             30 LOAD_CONST               7 (('return',))
             32 BUILD_CONST_KEY_MAP      1
             34 LOAD_CONST               8 (<code object as_string at 0x100e3a190, file "./interp.py", line 359>)
             36 LOAD_CONST               9 ('IsAlpha.as_string')
             38 MAKE_FUNCTION            4 (annotations)
             40 STORE_NAME               4 (as_string)

362          42 LOAD_CONST              10 ('int')
             44 LOAD_CONST               7 (('return',))
             46 BUILD_CONST_KEY_MAP      1
             48 LOAD_CONST              11 (<code object arg_count at 0x100e3a240, file "./interp.py", line 362>)
             50 LOAD_CONST              12 ('IsAlpha.arg_count')
             52 MAKE_FUNCTION            4 (annotations)
             54 STORE_NAME               5 (arg_count)

365          56 LOAD_CONST              13 ('Interpreter')
             58 LOAD_CONST              14 ('list[Object]')
             60 LOAD_CONST               1 ('Value')
             62 LOAD_CONST              15 (('_', 'args', 'return'))
             64 BUILD_CONST_KEY_MAP      3
             66 LOAD_CLOSURE             0 (__class__)
             68 BUILD_TUPLE              1
             70 LOAD_CONST              16 (<code object call at 0x100e3a2f0, file "./interp.py", line 365>)
             72 LOAD_CONST              17 ('IsAlpha.call')
             74 MAKE_FUNCTION           12 (annotations, closure)
             76 STORE_NAME               6 (call)
             78 LOAD_CLOSURE             0 (__class__)
             80 DUP_TOP
             82 STORE_NAME               7 (__classcell__)
             84 RETURN_VALUE

Disassembly of <code object __init__ at 0x100b985b0, file "./interp.py", line 355>:
356           0 LOAD_GLOBAL              0 (super)
              2 CALL_FUNCTION            0
              4 LOAD_METHOD              1 (__init__)
              6 CALL_METHOD              0
              8 POP_TOP

357          10 LOAD_FAST                1 (wrapper)
             12 LOAD_FAST                0 (self)
             14 STORE_ATTR               2 (wrapper)
             16 LOAD_CONST               0 (None)
             18 RETURN_VALUE

Disassembly of <code object as_string at 0x100e3a190, file "./interp.py", line 359>:
360           0 LOAD_CONST               1 ("<method 'isalpha' of ")
              2 LOAD_FAST                0 (self)
              4 LOAD_ATTR                0 (wrapper)
              6 LOAD_METHOD              1 (repr)
              8 CALL_METHOD              0
             10 FORMAT_VALUE             0
             12 LOAD_CONST               2 ('>')
             14 BUILD_STRING             3
             16 RETURN_VALUE

Disassembly of <code object arg_count at 0x100e3a240, file "./interp.py", line 362>:
363           0 LOAD_CONST               1 (0)
              2 RETURN_VALUE

Disassembly of <code object call at 0x100e3a2f0, file "./interp.py", line 365>:
366           0 LOAD_GLOBAL              0 (super)
              2 CALL_FUNCTION            0
              4 LOAD_METHOD              1 (ensure_args)
              6 LOAD_FAST                2 (args)
              8 CALL_METHOD              1
             10 POP_TOP

367          12 LOAD_GLOBAL              2 (Value)
             14 LOAD_FAST                0 (self)
             16 LOAD_ATTR                3 (wrapper)
             18 LOAD_ATTR                4 (value)
             20 LOAD_METHOD              5 (isalpha)
             22 CALL_METHOD              0
             24 CALL_FUNCTION            1
             26 RETURN_VALUE

Disassembly of <code object Join at 0x100e3a7c0, file "./interp.py", line 370>:
370           0 LOAD_NAME                0 (__name__)
              2 STORE_NAME               1 (__module__)
              4 LOAD_CONST               0 ('Join')
              6 STORE_NAME               2 (__qualname__)

371           8 LOAD_CONST               1 ('Value')
             10 LOAD_CONST               2 ('None')
             12 LOAD_CONST               3 (('wrapper', 'return'))
             14 BUILD_CONST_KEY_MAP      2
             16 LOAD_CLOSURE             0 (__class__)
             18 BUILD_TUPLE              1
             20 LOAD_CONST               4 (<code object __init__ at 0x100e3a450, file "./interp.py", line 371>)
             22 LOAD_CONST               5 ('Join.__init__')
             24 MAKE_FUNCTION           12 (annotations, closure)
             26 STORE_NAME               3 (__init__)

375          28 LOAD_CONST               6 ('str')
             30 LOAD_CONST               7 (('return',))
             32 BUILD_CONST_KEY_MAP      1
             34 LOAD_CONST               8 (<code object as_string at 0x100e3a500, file "./interp.py", line 375>)
             36 LOAD_CONST               9 ('Join.as_string')
             38 MAKE_FUNCTION            4 (annotations)
             40 STORE_NAME               4 (as_string)

378          42 LOAD_CONST              10 ('int')
             44 LOAD_CONST               7 (('return',))
             46 BUILD_CONST_KEY_MAP      1
             48 LOAD_CONST              11 (<code object arg_count at 0x100e3a5b0, file "./interp.py", line 378>)
             50 LOAD_CONST              12 ('Join.arg_count')
             52 MAKE_FUNCTION            4 (annotations)
             54 STORE_NAME               5 (arg_count)

381          56 LOAD_CONST              13 ('Interpreter')
             58 LOAD_CONST              14 ('list[Object]')
             60 LOAD_CONST               1 ('Value')
             62 LOAD_CONST              15 (('_', 'args', 'return'))
             64 BUILD_CONST_KEY_MAP      3
             66 LOAD_CLOSURE             0 (__class__)
             68 BUILD_TUPLE              1
             70 LOAD_CONST              16 (<code object call at 0x100e3a710, file "./interp.py", line 381>)
             72 LOAD_CONST              17 ('Join.call')
             74 MAKE_FUNCTION           12 (annotations, closure)
             76 STORE_NAME               6 (call)
             78 LOAD_CLOSURE             0 (__class__)
             80 DUP_TOP
             82 STORE_NAME               7 (__classcell__)
             84 RETURN_VALUE

Disassembly of <code object __init__ at 0x100e3a450, file "./interp.py", line 371>:
372           0 LOAD_GLOBAL              0 (super)
              2 CALL_FUNCTION            0
              4 LOAD_METHOD              1 (__init__)
              6 CALL_METHOD              0
              8 POP_TOP

373          10 LOAD_FAST                1 (wrapper)
             12 LOAD_FAST                0 (self)
             14 STORE_ATTR               2 (wrapper)
             16 LOAD_CONST               0 (None)
             18 RETURN_VALUE

Disassembly of <code object as_string at 0x100e3a500, file "./interp.py", line 375>:
376           0 LOAD_CONST               1 ("<method 'join' of ")
              2 LOAD_FAST                0 (self)
              4 LOAD_ATTR                0 (wrapper)
              6 LOAD_METHOD              1 (repr)
              8 CALL_METHOD              0
             10 FORMAT_VALUE             0
             12 LOAD_CONST               2 ('>')
             14 BUILD_STRING             3
             16 RETURN_VALUE

Disassembly of <code object arg_count at 0x100e3a5b0, file "./interp.py", line 378>:
379           0 LOAD_CONST               1 (1)
              2 RETURN_VALUE

Disassembly of <code object call at 0x100e3a710, file "./interp.py", line 381>:
382           0 LOAD_GLOBAL              0 (super)
              2 CALL_FUNCTION            0
              4 LOAD_METHOD              1 (ensure_args)
              6 LOAD_FAST                2 (args)
              8 CALL_METHOD              1
             10 POP_TOP

383          12 LOAD_FAST                2 (args)
             14 LOAD_CONST               1 (0)
             16 BINARY_SUBSCR
             18 STORE_FAST               3 (items)

384          20 LOAD_GLOBAL              2 (isinstance)
             22 LOAD_FAST                3 (items)
             24 LOAD_GLOBAL              3 (List)
             26 LOAD_GLOBAL              4 (Tuple)
             28 LOAD_GLOBAL              5 (Deque)
             30 BUILD_TUPLE              3
             32 CALL_FUNCTION            2
             34 POP_JUMP_IF_TRUE        56

385          36 LOAD_GLOBAL              6 (InterpreterError)
             38 LOAD_GLOBAL              7 (type)
             40 LOAD_FAST                3 (items)
             42 CALL_FUNCTION            1
             44 LOAD_ATTR                8 (__name__)
             46 FORMAT_VALUE             0
             48 LOAD_CONST               2 (' object is not iterable')
             50 BUILD_STRING             2
             52 CALL_FUNCTION            1
             54 RAISE_VARARGS            1

387     >>   56 LOAD_GLOBAL              9 (Value)
             58 LOAD_FAST                0 (self)
             60 LOAD_ATTR               10 (wrapper)
             62 LOAD_ATTR               11 (value)
             64 LOAD_METHOD             12 (join)
             66 LOAD_CONST               3 (<code object <genexpr> at 0x100e3a660, file "./interp.py", line 387>)
             68 LOAD_CONST               4 ('Join.call.<locals>.<genexpr>')
             70 MAKE_FUNCTION            0
             72 LOAD_FAST                3 (items)
             74 LOAD_ATTR               13 (_data)
             76 GET_ITER
             78 CALL_FUNCTION            1
             80 CALL_METHOD              1
             82 CALL_FUNCTION            1
             84 RETURN_VALUE

Disassembly of <code object <genexpr> at 0x100e3a660, file "./interp.py", line 387>:
387           0 LOAD_FAST                0 (.0)
        >>    2 FOR_ITER                14 (to 18)
              4 STORE_FAST               1 (item)
              6 LOAD_FAST                1 (item)
              8 LOAD_METHOD              0 (as_string)
             10 CALL_METHOD              0
             12 YIELD_VALUE
             14 POP_TOP
             16 JUMP_ABSOLUTE            2
        >>   18 LOAD_CONST               0 (None)
             20 RETURN_VALUE

Disassembly of <code object List at 0x100e3ab30, file "./interp.py", line 390>:
390           0 LOAD_NAME                0 (__name__)
              2 STORE_NAME               1 (__module__)
              4 LOAD_CONST               0 ('List')
              6 STORE_NAME               2 (__qualname__)

391           8 LOAD_CONST               1 ('Iterable[Object]')
             10 LOAD_CONST               2 ('None')
             12 LOAD_CONST               3 (('elements', 'return'))
             14 BUILD_CONST_KEY_MAP      2
             16 LOAD_CLOSURE             0 (__class__)
             18 BUILD_TUPLE              1
             20 LOAD_CONST               4 (<code object __init__ at 0x100e3a870, file "./interp.py", line 391>)
             22 LOAD_CONST               5 ('List.__init__')
             24 MAKE_FUNCTION           12 (annotations, closure)
             26 STORE_NAME               3 (__init__)

396          28 LOAD_CONST               6 ('str')
             30 LOAD_CONST               7 (('return',))
             32 BUILD_CONST_KEY_MAP      1
             34 LOAD_CONST               8 (<code object as_string at 0x100e3a9d0, file "./interp.py", line 396>)
             36 LOAD_CONST               9 ('List.as_string')
             38 MAKE_FUNCTION            4 (annotations)
             40 STORE_NAME               4 (as_string)

399          42 LOAD_CONST               1 ('Iterable[Object]')
             44 LOAD_CONST               7 (('return',))
             46 BUILD_CONST_KEY_MAP      1
             48 LOAD_CONST              10 (<code object __iter__ at 0x100e3aa80, file "./interp.py", line 399>)
             50 LOAD_CONST              11 ('List.__iter__')
             52 MAKE_FUNCTION            4 (annotations)
             54 STORE_NAME               5 (__iter__)
             56 LOAD_CLOSURE             0 (__class__)
             58 DUP_TOP
             60 STORE_NAME               6 (__classcell__)
             62 RETURN_VALUE

Disassembly of <code object __init__ at 0x100e3a870, file "./interp.py", line 391>:
392           0 LOAD_GLOBAL              0 (super)
              2 CALL_FUNCTION            0
              4 LOAD_METHOD              1 (__init__)
              6 CALL_METHOD              0
              8 POP_TOP

393          10 LOAD_FAST                1 (elements)
             12 LOAD_FAST                0 (self)
             14 STORE_ATTR               2 (_data)

394          16 LOAD_GLOBAL              3 (Append)
             18 LOAD_FAST                0 (self)
             20 CALL_FUNCTION            1
             22 LOAD_FAST                0 (self)
             24 LOAD_ATTR                4 (methods)
             26 LOAD_CONST               1 ('append')
             28 STORE_SUBSCR
             30 LOAD_CONST               0 (None)
             32 RETURN_VALUE

Disassembly of <code object as_string at 0x100e3a9d0, file "./interp.py", line 396>:
397           0 LOAD_CONST               1 ('[')
              2 LOAD_CONST               2 (', ')
              4 LOAD_METHOD              0 (join)
              6 LOAD_CONST               3 (<code object <genexpr> at 0x100e3a920, file "./interp.py", line 397>)
              8 LOAD_CONST               4 ('List.as_string.<locals>.<genexpr>')
             10 MAKE_FUNCTION            0
             12 LOAD_FAST                0 (self)
             14 LOAD_ATTR                1 (_data)
             16 GET_ITER
             18 CALL_FUNCTION            1
             20 CALL_METHOD              1
             22 BINARY_ADD
             24 LOAD_CONST               5 (']')
             26 BINARY_ADD
             28 RETURN_VALUE

Disassembly of <code object <genexpr> at 0x100e3a920, file "./interp.py", line 397>:
397           0 LOAD_FAST                0 (.0)
        >>    2 FOR_ITER                14 (to 18)
              4 STORE_FAST               1 (item)
              6 LOAD_FAST                1 (item)
              8 LOAD_METHOD              0 (repr)
             10 CALL_METHOD              0
             12 YIELD_VALUE
             14 POP_TOP
             16 JUMP_ABSOLUTE            2
        >>   18 LOAD_CONST               0 (None)
             20 RETURN_VALUE

Disassembly of <code object __iter__ at 0x100e3aa80, file "./interp.py", line 399>:
400           0 LOAD_GLOBAL              0 (iter)
              2 LOAD_FAST                0 (self)
              4 LOAD_ATTR                1 (_data)
              6 CALL_FUNCTION            1
              8 RETURN_VALUE

Disassembly of <code object Tuple at 0x100e3aea0, file "./interp.py", line 403>:
403           0 LOAD_NAME                0 (__name__)
              2 STORE_NAME               1 (__module__)
              4 LOAD_CONST               0 ('Tuple')
              6 STORE_NAME               2 (__qualname__)

404           8 LOAD_CONST               1 ('Iterable[Object]')
             10 LOAD_CONST               2 ('None')
             12 LOAD_CONST               3 (('elements', 'return'))
             14 BUILD_CONST_KEY_MAP      2
             16 LOAD_CLOSURE             0 (__class__)
             18 BUILD_TUPLE              1
             20 LOAD_CONST               4 (<code object __init__ at 0x100e3abe0, file "./interp.py", line 404>)
             22 LOAD_CONST               5 ('Tuple.__init__')
             24 MAKE_FUNCTION           12 (annotations, closure)
             26 STORE_NAME               3 (__init__)

408          28 LOAD_CONST               6 ('str')
             30 LOAD_CONST               7 (('return',))
             32 BUILD_CONST_KEY_MAP      1
             34 LOAD_CONST               8 (<code object as_string at 0x100e3ad40, file "./interp.py", line 408>)
             36 LOAD_CONST               9 ('Tuple.as_string')
             38 MAKE_FUNCTION            4 (annotations)
             40 STORE_NAME               4 (as_string)

411          42 LOAD_CONST               1 ('Iterable[Object]')
             44 LOAD_CONST               7 (('return',))
             46 BUILD_CONST_KEY_MAP      1
             48 LOAD_CONST              10 (<code object __iter__ at 0x100e3adf0, file "./interp.py", line 411>)
             50 LOAD_CONST              11 ('Tuple.__iter__')
             52 MAKE_FUNCTION            4 (annotations)
             54 STORE_NAME               5 (__iter__)
             56 LOAD_CLOSURE             0 (__class__)
             58 DUP_TOP
             60 STORE_NAME               6 (__classcell__)
             62 RETURN_VALUE

Disassembly of <code object __init__ at 0x100e3abe0, file "./interp.py", line 404>:
405           0 LOAD_GLOBAL              0 (super)
              2 CALL_FUNCTION            0
              4 LOAD_METHOD              1 (__init__)
              6 CALL_METHOD              0
              8 POP_TOP

406          10 LOAD_FAST                1 (elements)
             12 LOAD_FAST                0 (self)
             14 STORE_ATTR               2 (_data)
             16 LOAD_CONST               0 (None)
             18 RETURN_VALUE

Disassembly of <code object as_string at 0x100e3ad40, file "./interp.py", line 408>:
409           0 LOAD_CONST               1 ('(')
              2 LOAD_CONST               2 (', ')
              4 LOAD_METHOD              0 (join)
              6 LOAD_CONST               3 (<code object <genexpr> at 0x100e3ac90, file "./interp.py", line 409>)
              8 LOAD_CONST               4 ('Tuple.as_string.<locals>.<genexpr>')
             10 MAKE_FUNCTION            0
             12 LOAD_FAST                0 (self)
             14 LOAD_ATTR                1 (_data)
             16 GET_ITER
             18 CALL_FUNCTION            1
             20 CALL_METHOD              1
             22 BINARY_ADD
             24 LOAD_CONST               5 (')')
             26 BINARY_ADD
             28 RETURN_VALUE

Disassembly of <code object <genexpr> at 0x100e3ac90, file "./interp.py", line 409>:
409           0 LOAD_FAST                0 (.0)
        >>    2 FOR_ITER                14 (to 18)
              4 STORE_FAST               1 (item)
              6 LOAD_FAST                1 (item)
              8 LOAD_METHOD              0 (repr)
             10 CALL_METHOD              0
             12 YIELD_VALUE
             14 POP_TOP
             16 JUMP_ABSOLUTE            2
        >>   18 LOAD_CONST               0 (None)
             20 RETURN_VALUE

Disassembly of <code object __iter__ at 0x100e3adf0, file "./interp.py", line 411>:
412           0 LOAD_GLOBAL              0 (iter)
              2 LOAD_FAST                0 (self)
              4 LOAD_ATTR                1 (_data)
              6 CALL_FUNCTION            1
              8 RETURN_VALUE

Disassembly of <code object Dict at 0x100e362f0, file "./interp.py", line 415>:
415           0 LOAD_NAME                0 (__name__)
              2 STORE_NAME               1 (__module__)
              4 LOAD_CONST               0 ('Dict')
              6 STORE_NAME               2 (__qualname__)

416           8 LOAD_CONST               1 ('list[Object]')
             10 LOAD_CONST               1 ('list[Object]')
             12 LOAD_CONST               2 ('None')
             14 LOAD_CONST               3 (('keys', 'values', 'return'))
             16 BUILD_CONST_KEY_MAP      3
             18 LOAD_CLOSURE             0 (__class__)
             20 BUILD_TUPLE              1
             22 LOAD_CONST               4 (<code object __init__ at 0x100e36030, file "./interp.py", line 416>)
             24 LOAD_CONST               5 ('Dict.__init__')
             26 MAKE_FUNCTION           12 (annotations, closure)
             28 STORE_NAME               3 (__init__)

421          30 LOAD_CONST               6 ('str')
             32 LOAD_CONST               7 (('return',))
             34 BUILD_CONST_KEY_MAP      1
             36 LOAD_CONST               8 (<code object as_string at 0x100e36190, file "./interp.py", line 421>)
             38 LOAD_CONST               9 ('Dict.as_string')
             40 MAKE_FUNCTION            4 (annotations)
             42 STORE_NAME               4 (as_string)

430          44 LOAD_CONST              10 ('Iterable[Object]')
             46 LOAD_CONST               7 (('return',))
             48 BUILD_CONST_KEY_MAP      1
             50 LOAD_CONST              11 (<code object __iter__ at 0x100e36240, file "./interp.py", line 430>)
             52 LOAD_CONST              12 ('Dict.__iter__')
             54 MAKE_FUNCTION            4 (annotations)
             56 STORE_NAME               5 (__iter__)
             58 LOAD_CLOSURE             0 (__class__)
             60 DUP_TOP
             62 STORE_NAME               6 (__classcell__)
             64 RETURN_VALUE

Disassembly of <code object __init__ at 0x100e36030, file "./interp.py", line 416>:
417           0 LOAD_GLOBAL              0 (super)
              2 CALL_FUNCTION            0
              4 LOAD_METHOD              1 (__init__)
              6 CALL_METHOD              0
              8 POP_TOP

418          10 LOAD_CONST               1 (<code object <dictcomp> at 0x100e3af50, file "./interp.py", line 418>)
             12 LOAD_CONST               2 ('Dict.__init__.<locals>.<dictcomp>')
             14 MAKE_FUNCTION            0
             16 LOAD_GLOBAL              2 (zip)
             18 LOAD_FAST                1 (keys)
             20 LOAD_FAST                2 (values)
             22 CALL_FUNCTION            2
             24 GET_ITER
             26 CALL_FUNCTION            1
             28 LOAD_FAST                0 (self)
             30 STORE_ATTR               3 (_dict)

419          32 LOAD_GLOBAL              4 (Items)
             34 LOAD_FAST                0 (self)
             36 CALL_FUNCTION            1
             38 LOAD_FAST                0 (self)
             40 LOAD_ATTR                5 (methods)
             42 LOAD_CONST               3 ('items')
             44 STORE_SUBSCR
             46 LOAD_CONST               0 (None)
             48 RETURN_VALUE

Disassembly of <code object <dictcomp> at 0x100e3af50, file "./interp.py", line 418>:
418           0 BUILD_MAP                0
              2 LOAD_FAST                0 (.0)
        >>    4 FOR_ITER                14 (to 20)
              6 UNPACK_SEQUENCE          2
              8 STORE_FAST               1 (key)
             10 STORE_FAST               2 (value)
             12 LOAD_FAST                1 (key)
             14 LOAD_FAST                2 (value)
             16 MAP_ADD                  2
             18 JUMP_ABSOLUTE            4
        >>   20 RETURN_VALUE

Disassembly of <code object as_string at 0x100e36190, file "./interp.py", line 421>:
423           0 LOAD_CONST               1 ('{')

424           2 LOAD_CONST               2 (', ')
              4 LOAD_METHOD              0 (join)
              6 LOAD_CONST               3 (<code object <genexpr> at 0x100e360e0, file "./interp.py", line 424>)
              8 LOAD_CONST               4 ('Dict.as_string.<locals>.<genexpr>')
             10 MAKE_FUNCTION            0

425          12 LOAD_FAST                0 (self)
             14 LOAD_ATTR                1 (_dict)
             16 LOAD_METHOD              2 (items)
             18 CALL_METHOD              0

424          20 GET_ITER
             22 CALL_FUNCTION            1
             24 CALL_METHOD              1

423          26 BINARY_ADD

427          28 LOAD_CONST               5 ('}')

423          30 BINARY_ADD

422          32 RETURN_VALUE

Disassembly of <code object <genexpr> at 0x100e360e0, file "./interp.py", line 424>:
424           0 LOAD_FAST                0 (.0)
        >>    2 FOR_ITER                32 (to 36)

425           4 UNPACK_SEQUENCE          2
              6 STORE_FAST               1 (key)
              8 STORE_FAST               2 (value)
             10 LOAD_FAST                1 (key)
             12 LOAD_METHOD              0 (repr)
             14 CALL_METHOD              0
             16 FORMAT_VALUE             0
             18 LOAD_CONST               0 (': ')
             20 LOAD_FAST                2 (value)
             22 LOAD_METHOD              0 (repr)
             24 CALL_METHOD              0
             26 FORMAT_VALUE             0
             28 BUILD_STRING             3
             30 YIELD_VALUE
             32 POP_TOP
             34 JUMP_ABSOLUTE            2
        >>   36 LOAD_CONST               1 (None)
             38 RETURN_VALUE

Disassembly of <code object __iter__ at 0x100e36240, file "./interp.py", line 430>:
431           0 LOAD_GLOBAL              0 (iter)
              2 LOAD_GLOBAL              1 (list)
              4 LOAD_FAST                0 (self)
              6 LOAD_ATTR                2 (_dict)
              8 CALL_FUNCTION            1
             10 CALL_FUNCTION            1
             12 RETURN_VALUE

Disassembly of <code object is_truthy at 0x100e363a0, file "./interp.py", line 434>:
435           0 LOAD_GLOBAL              0 (isinstance)
              2 LOAD_FAST                0 (obj)
              4 LOAD_GLOBAL              1 (Value)
              6 CALL_FUNCTION            2
              8 POP_JUMP_IF_FALSE       20

436          10 LOAD_GLOBAL              2 (bool)
             12 LOAD_FAST                0 (obj)
             14 LOAD_ATTR                3 (value)
             16 CALL_FUNCTION            1
             18 RETURN_VALUE

438     >>   20 LOAD_CONST               1 (True)
             22 RETURN_VALUE

Disassembly of <code object Interpreter at 0x100e2f190, file "./interp.py", line 441>:
441           0 LOAD_NAME                0 (__name__)
              2 STORE_NAME               1 (__module__)
              4 LOAD_CONST               0 ('Interpreter')
              6 STORE_NAME               2 (__qualname__)

442           8 LOAD_CONST               1 ('None')
             10 LOAD_CONST               2 (('return',))
             12 BUILD_CONST_KEY_MAP      1
             14 LOAD_CONST               3 (<code object __init__ at 0x100e36450, file "./interp.py", line 442>)
             16 LOAD_CONST               4 ('Interpreter.__init__')
             18 MAKE_FUNCTION            4 (annotations)
             20 STORE_NAME               3 (__init__)

446          22 LOAD_CONST               5 ('Node')
             24 LOAD_CONST               6 ('Object | None')
             26 LOAD_CONST               7 (('node', 'return'))
             28 BUILD_CONST_KEY_MAP      2
             30 LOAD_CONST               8 (<code object visit at 0x100e36500, file "./interp.py", line 446>)
             32 LOAD_CONST               9 ('Interpreter.visit')
             34 MAKE_FUNCTION            4 (annotations)
             36 STORE_NAME               4 (visit)

451          38 LOAD_CONST              10 ('Module')
             40 LOAD_CONST               1 ('None')
             42 LOAD_CONST               7 (('node', 'return'))
             44 BUILD_CONST_KEY_MAP      2
             46 LOAD_CONST              11 (<code object visit_Module at 0x100e365b0, file "./interp.py", line 451>)
             48 LOAD_CONST              12 ('Interpreter.visit_Module')
             50 MAKE_FUNCTION            4 (annotations)
             52 STORE_NAME               5 (visit_Module)

455          54 LOAD_CONST              13 ('Import')
             56 LOAD_CONST               1 ('None')
             58 LOAD_CONST               7 (('node', 'return'))
             60 BUILD_CONST_KEY_MAP      2
             62 LOAD_CONST              14 (<code object visit_Import at 0x100e36660, file "./interp.py", line 455>)
             64 LOAD_CONST              15 ('Interpreter.visit_Import')
             66 MAKE_FUNCTION            4 (annotations)
             68 STORE_NAME               6 (visit_Import)

482          70 LOAD_CONST              16 ('ImportFrom')
             72 LOAD_CONST               1 ('None')
             74 LOAD_CONST               7 (('node', 'return'))
             76 BUILD_CONST_KEY_MAP      2
             78 LOAD_CONST              17 (<code object visit_ImportFrom at 0x100e36710, file "./interp.py", line 482>)
             80 LOAD_CONST              18 ('Interpreter.visit_ImportFrom')
             82 MAKE_FUNCTION            4 (annotations)
             84 STORE_NAME               7 (visit_ImportFrom)

515          86 LOAD_CONST              19 ('FunctionDef')
             88 LOAD_CONST               1 ('None')
             90 LOAD_CONST               7 (('node', 'return'))
             92 BUILD_CONST_KEY_MAP      2
             94 LOAD_CONST              20 (<code object visit_FunctionDef at 0x100e36870, file "./interp.py", line 515>)
             96 LOAD_CONST              21 ('Interpreter.visit_FunctionDef')
             98 MAKE_FUNCTION            4 (annotations)
            100 STORE_NAME               8 (visit_FunctionDef)

532         102 LOAD_CONST               5 ('Node')
            104 LOAD_CONST              22 ('Object')
            106 LOAD_CONST               1 ('None')
            108 LOAD_CONST              23 (('target', 'value', 'return'))
            110 BUILD_CONST_KEY_MAP      3
            112 LOAD_CONST              24 (<code object assign at 0x100e367c0, file "./interp.py", line 532>)
            114 LOAD_CONST              25 ('Interpreter.assign')
            116 MAKE_FUNCTION            4 (annotations)
            118 STORE_NAME               9 (assign)

567         120 LOAD_CONST              26 ('Assign')
            122 LOAD_CONST               1 ('None')
            124 LOAD_CONST               7 (('node', 'return'))
            126 BUILD_CONST_KEY_MAP      2
            128 LOAD_CONST              27 (<code object visit_Assign at 0x100e36920, file "./interp.py", line 567>)
            130 LOAD_CONST              28 ('Interpreter.visit_Assign')
            132 MAKE_FUNCTION            4 (annotations)
            134 STORE_NAME              10 (visit_Assign)

574         136 LOAD_CONST              29 ('AugAssign')
            138 LOAD_CONST               1 ('None')
            140 LOAD_CONST               7 (('node', 'return'))
            142 BUILD_CONST_KEY_MAP      2
            144 LOAD_CONST              30 (<code object visit_AugAssign at 0x100e36b30, file "./interp.py", line 574>)
            146 LOAD_CONST              31 ('Interpreter.visit_AugAssign')
            148 MAKE_FUNCTION            4 (annotations)
            150 STORE_NAME              11 (visit_AugAssign)

591         152 LOAD_CONST              32 ('If')
            154 LOAD_CONST               1 ('None')
            156 LOAD_CONST               7 (('node', 'return'))
            158 BUILD_CONST_KEY_MAP      2
            160 LOAD_CONST              33 (<code object visit_If at 0x100e369d0, file "./interp.py", line 591>)
            162 LOAD_CONST              34 ('Interpreter.visit_If')
            164 MAKE_FUNCTION            4 (annotations)
            166 STORE_NAME              12 (visit_If)

599         168 LOAD_CONST              35 ('nodes.For')
            170 LOAD_CONST               1 ('None')
            172 LOAD_CONST               7 (('node', 'return'))
            174 BUILD_CONST_KEY_MAP      2
            176 LOAD_CONST              36 (<code object visit_For at 0x100e36d40, file "./interp.py", line 599>)
            178 LOAD_CONST              37 ('Interpreter.visit_For')
            180 MAKE_FUNCTION            4 (annotations)
            182 STORE_NAME              13 (visit_For)

622         184 LOAD_CONST              38 ('While')
            186 LOAD_CONST               1 ('None')
            188 LOAD_CONST               7 (('node', 'return'))
            190 BUILD_CONST_KEY_MAP      2
            192 LOAD_CONST              39 (<code object visit_While at 0x100e36df0, file "./interp.py", line 622>)
            194 LOAD_CONST              40 ('Interpreter.visit_While')
            196 MAKE_FUNCTION            4 (annotations)
            198 STORE_NAME              14 (visit_While)

634         200 LOAD_CONST              41 ('nodes.Break')
            202 LOAD_CONST              42 ('Break')
            204 LOAD_CONST               7 (('node', 'return'))
            206 BUILD_CONST_KEY_MAP      2
            208 LOAD_CONST              43 (<code object visit_Break at 0x100e36ea0, file "./interp.py", line 634>)
            210 LOAD_CONST              44 ('Interpreter.visit_Break')
            212 MAKE_FUNCTION            4 (annotations)
            214 STORE_NAME              15 (visit_Break)

637         216 LOAD_CONST              45 ('nodes.Continue')
            218 LOAD_CONST              46 ('Continue')
            220 LOAD_CONST               7 (('node', 'return'))
            222 BUILD_CONST_KEY_MAP      2
            224 LOAD_CONST              47 (<code object visit_Continue at 0x100e36f50, file "./interp.py", line 637>)
            226 LOAD_CONST              48 ('Interpreter.visit_Continue')
            228 MAKE_FUNCTION            4 (annotations)
            230 STORE_NAME              16 (visit_Continue)

640         232 LOAD_CONST              49 ('nodes.Return')
            234 LOAD_CONST              50 ('Return')
            236 LOAD_CONST               7 (('node', 'return'))
            238 BUILD_CONST_KEY_MAP      2
            240 LOAD_CONST              51 (<code object visit_Return at 0x100e33030, file "./interp.py", line 640>)
            242 LOAD_CONST              52 ('Interpreter.visit_Return')
            244 MAKE_FUNCTION            4 (annotations)
            246 STORE_NAME              17 (visit_Return)

643         248 LOAD_CONST              53 ('nodes.Pass')
            250 LOAD_CONST               1 ('None')
            252 LOAD_CONST               7 (('node', 'return'))
            254 BUILD_CONST_KEY_MAP      2
            256 LOAD_CONST              54 (<code object visit_Pass at 0x100e330e0, file "./interp.py", line 643>)
            258 LOAD_CONST              55 ('Interpreter.visit_Pass')
            260 MAKE_FUNCTION            4 (annotations)
            262 STORE_NAME              18 (visit_Pass)

646         264 LOAD_CONST              56 ('ExprStmt')
            266 LOAD_CONST               1 ('None')
            268 LOAD_CONST               7 (('node', 'return'))
            270 BUILD_CONST_KEY_MAP      2
            272 LOAD_CONST              57 (<code object visit_ExprStmt at 0x100e33190, file "./interp.py", line 646>)
            274 LOAD_CONST              58 ('Interpreter.visit_ExprStmt')
            276 MAKE_FUNCTION            4 (annotations)
            278 STORE_NAME              19 (visit_ExprStmt)

649         280 LOAD_CONST              59 ('Compare')
            282 LOAD_CONST              60 ('Value')
            284 LOAD_CONST               7 (('node', 'return'))
            286 BUILD_CONST_KEY_MAP      2
            288 LOAD_CONST              61 (<code object visit_Compare at 0x100e335b0, file "./interp.py", line 649>)
            290 LOAD_CONST              62 ('Interpreter.visit_Compare')
            292 MAKE_FUNCTION            4 (annotations)
            294 STORE_NAME              20 (visit_Compare)

709         296 LOAD_CONST              63 ('BinOp')
            298 LOAD_CONST              22 ('Object')
            300 LOAD_CONST               7 (('node', 'return'))
            302 BUILD_CONST_KEY_MAP      2
            304 LOAD_CONST              64 (<code object visit_BinOp at 0x100e33660, file "./interp.py", line 709>)
            306 LOAD_CONST              65 ('Interpreter.visit_BinOp')
            308 MAKE_FUNCTION            4 (annotations)
            310 STORE_NAME              21 (visit_BinOp)

730         312 LOAD_CONST              66 ('BoolOp')
            314 LOAD_CONST              22 ('Object')
            316 LOAD_CONST               7 (('node', 'return'))
            318 BUILD_CONST_KEY_MAP      2
            320 LOAD_CONST              67 (<code object visit_BoolOp at 0x100e33710, file "./interp.py", line 730>)
            322 LOAD_CONST              68 ('Interpreter.visit_BoolOp')
            324 MAKE_FUNCTION            4 (annotations)
            326 STORE_NAME              22 (visit_BoolOp)

747         328 LOAD_CONST              69 ('UnaryOp')
            330 LOAD_CONST              60 ('Value')
            332 LOAD_CONST               7 (('node', 'return'))
            334 BUILD_CONST_KEY_MAP      2
            336 LOAD_CONST              70 (<code object visit_UnaryOp at 0x100e33870, file "./interp.py", line 747>)
            338 LOAD_CONST              71 ('Interpreter.visit_UnaryOp')
            340 MAKE_FUNCTION            4 (annotations)
            342 STORE_NAME              23 (visit_UnaryOp)

761         344 LOAD_CONST              72 ('Call')
            346 LOAD_CONST              22 ('Object')
            348 LOAD_CONST               7 (('node', 'return'))
            350 BUILD_CONST_KEY_MAP      2
            352 LOAD_CONST              73 (<code object visit_Call at 0x100e33920, file "./interp.py", line 761>)
            354 LOAD_CONST              74 ('Interpreter.visit_Call')
            356 MAKE_FUNCTION            4 (annotations)
            358 STORE_NAME              24 (visit_Call)

771         360 LOAD_CONST              75 ('Subscript')
            362 LOAD_CONST              22 ('Object')
            364 LOAD_CONST               7 (('node', 'return'))
            366 BUILD_CONST_KEY_MAP      2
            368 LOAD_CONST              76 (<code object visit_Subscript at 0x100e339d0, file "./interp.py", line 771>)
            370 LOAD_CONST              77 ('Interpreter.visit_Subscript')
            372 MAKE_FUNCTION            4 (annotations)
            374 STORE_NAME              25 (visit_Subscript)

815         376 LOAD_CONST              78 ('Attribute')
            378 LOAD_CONST              22 ('Object')
            380 LOAD_CONST               7 (('node', 'return'))
            382 BUILD_CONST_KEY_MAP      2
            384 LOAD_CONST              79 (<code object visit_Attribute at 0x100e33a80, file "./interp.py", line 815>)
            386 LOAD_CONST              80 ('Interpreter.visit_Attribute')
            388 MAKE_FUNCTION            4 (annotations)
            390 STORE_NAME              26 (visit_Attribute)

830         392 LOAD_CONST              81 ('Name')
            394 LOAD_CONST              60 ('Value')
            396 LOAD_CONST               7 (('node', 'return'))
            398 BUILD_CONST_KEY_MAP      2
            400 LOAD_CONST              82 (<code object visit_Name at 0x100e33b30, file "./interp.py", line 830>)
            402 LOAD_CONST              83 ('Interpreter.visit_Name')
            404 MAKE_FUNCTION            4 (annotations)
            406 STORE_NAME              27 (visit_Name)

847         408 LOAD_CONST              84 ('nodes.List')
            410 LOAD_CONST              85 ('List')
            412 LOAD_CONST               7 (('node', 'return'))
            414 BUILD_CONST_KEY_MAP      2
            416 LOAD_CONST              86 (<code object visit_List at 0x100e33c90, file "./interp.py", line 847>)
            418 LOAD_CONST              87 ('Interpreter.visit_List')
            420 MAKE_FUNCTION            4 (annotations)
            422 STORE_NAME              28 (visit_List)

851         424 LOAD_CONST              88 ('nodes.Tuple')
            426 LOAD_CONST              89 ('Tuple')
            428 LOAD_CONST               7 (('node', 'return'))
            430 BUILD_CONST_KEY_MAP      2
            432 LOAD_CONST              90 (<code object visit_Tuple at 0x100e33df0, file "./interp.py", line 851>)
            434 LOAD_CONST              91 ('Interpreter.visit_Tuple')
            436 MAKE_FUNCTION            4 (annotations)
            438 STORE_NAME              29 (visit_Tuple)

855         440 LOAD_CONST              92 ('nodes.Dict')
            442 LOAD_CONST              93 ('Dict')
            444 LOAD_CONST               7 (('node', 'return'))
            446 BUILD_CONST_KEY_MAP      2
            448 LOAD_CONST              94 (<code object visit_Dict at 0x100e2f030, file "./interp.py", line 855>)
            450 LOAD_CONST              95 ('Interpreter.visit_Dict')
            452 MAKE_FUNCTION            4 (annotations)
            454 STORE_NAME              30 (visit_Dict)

860         456 LOAD_CONST              96 ('Constant')
            458 LOAD_CONST              60 ('Value')
            460 LOAD_CONST               7 (('node', 'return'))
            462 BUILD_CONST_KEY_MAP      2
            464 LOAD_CONST              97 (<code object visit_Constant at 0x100e2f0e0, file "./interp.py", line 860>)
            466 LOAD_CONST              98 ('Interpreter.visit_Constant')
            468 MAKE_FUNCTION            4 (annotations)
            470 STORE_NAME              31 (visit_Constant)
            472 LOAD_CONST              99 (None)
            474 RETURN_VALUE

Disassembly of <code object __init__ at 0x100e36450, file "./interp.py", line 442>:
443           0 LOAD_GLOBAL              0 (Scope)
              2 CALL_FUNCTION            0
              4 LOAD_FAST                0 (self)
              6 STORE_ATTR               1 (globals)

444           8 LOAD_FAST                0 (self)
             10 LOAD_ATTR                1 (globals)
             12 LOAD_FAST                0 (self)
             14 STORE_ATTR               2 (scope)
             16 LOAD_CONST               0 (None)
             18 RETURN_VALUE

Disassembly of <code object visit at 0x100e36500, file "./interp.py", line 446>:
447           0 LOAD_GLOBAL              0 (type)
              2 LOAD_FAST                1 (node)
              4 CALL_FUNCTION            1
              6 LOAD_ATTR                1 (__name__)
              8 STORE_FAST               2 (node_type)

448          10 LOAD_GLOBAL              2 (getattr)
             12 LOAD_FAST                0 (self)
             14 LOAD_CONST               1 ('visit_')
             16 LOAD_FAST                2 (node_type)
             18 FORMAT_VALUE             0
             20 BUILD_STRING             2
             22 CALL_FUNCTION            2
             24 STORE_FAST               3 (visitor_method)

449          26 LOAD_FAST                3 (visitor_method)
             28 LOAD_FAST                1 (node)
             30 CALL_FUNCTION            1
             32 RETURN_VALUE

Disassembly of <code object visit_Module at 0x100e365b0, file "./interp.py", line 451>:
452           0 LOAD_FAST                1 (node)
              2 LOAD_ATTR                0 (body)
              4 GET_ITER
        >>    6 FOR_ITER                14 (to 22)
              8 STORE_FAST               2 (stmt)

453          10 LOAD_FAST                0 (self)
             12 LOAD_METHOD              1 (visit)
             14 LOAD_FAST                2 (stmt)
             16 CALL_METHOD              1
             18 POP_TOP
             20 JUMP_ABSOLUTE            6
        >>   22 LOAD_CONST               0 (None)
             24 RETURN_VALUE

Disassembly of <code object visit_Import at 0x100e36660, file "./interp.py", line 455>:
456           0 LOAD_FAST                1 (node)
              2 LOAD_ATTR                0 (names)
              4 GET_ITER
        >>    6 FOR_ITER               170 (to 178)
              8 STORE_FAST               2 (alias)

457          10 LOAD_FAST                2 (alias)
             12 LOAD_ATTR                1 (name)
             14 STORE_FAST               3 (name)

458          16 LOAD_FAST                2 (alias)
             18 LOAD_ATTR                2 (asname)
             20 POP_JUMP_IF_FALSE       28

459          22 LOAD_FAST                2 (alias)
             24 LOAD_ATTR                2 (asname)
             26 STORE_FAST               3 (name)

461     >>   28 LOAD_CONST               1 ('')
             30 STORE_FAST               4 (contents)

462          32 LOAD_GLOBAL              3 (open)
             34 LOAD_FAST                2 (alias)
             36 LOAD_ATTR                1 (name)
             38 FORMAT_VALUE             0
             40 LOAD_CONST               2 ('.py')
             42 BUILD_STRING             2
             44 LOAD_CONST               3 ('r')
             46 CALL_FUNCTION            2
             48 SETUP_WITH              24 (to 74)
             50 STORE_FAST               5 (f)

463          52 LOAD_FAST                5 (f)
             54 LOAD_METHOD              4 (read)
             56 CALL_METHOD              0
             58 STORE_FAST               4 (contents)
             60 POP_BLOCK
             62 LOAD_CONST               0 (None)
             64 DUP_TOP
             66 DUP_TOP
             68 CALL_FUNCTION            3
             70 POP_TOP
             72 JUMP_FORWARD            16 (to 90)
        >>   74 WITH_EXCEPT_START
             76 POP_JUMP_IF_TRUE        80
             78 RERAISE
        >>   80 POP_TOP
             82 POP_TOP
             84 POP_TOP
             86 POP_EXCEPT
             88 POP_TOP

464     >>   90 LOAD_GLOBAL              5 (parse)
             92 LOAD_FAST                4 (contents)
             94 CALL_FUNCTION            1
             96 STORE_FAST               6 (module)

466          98 LOAD_FAST                0 (self)
            100 LOAD_ATTR                6 (scope)
            102 STORE_FAST               7 (parent_scope)

467         104 LOAD_FAST                0 (self)
            106 LOAD_ATTR                7 (globals)
            108 STORE_FAST               8 (parent_globals)

469         110 LOAD_GLOBAL              8 (Scope)
            112 CALL_FUNCTION            0
            114 STORE_FAST               9 (module_scope)

470         116 LOAD_FAST                9 (module_scope)
            118 LOAD_FAST                0 (self)
            120 STORE_ATTR               6 (scope)

471         122 LOAD_FAST                9 (module_scope)
            124 LOAD_FAST                0 (self)
            126 STORE_ATTR               7 (globals)

473         128 LOAD_FAST                0 (self)
            130 LOAD_METHOD              9 (visit)
            132 LOAD_FAST                6 (module)
            134 CALL_METHOD              1
            136 POP_TOP

475         138 LOAD_FAST                7 (parent_scope)
            140 LOAD_FAST                0 (self)
            142 STORE_ATTR               6 (scope)

476         144 LOAD_FAST                8 (parent_globals)
            146 LOAD_FAST                0 (self)
            148 STORE_ATTR               7 (globals)

478         150 LOAD_GLOBAL             10 (Module)
            152 LOAD_FAST                9 (module_scope)
            154 LOAD_ATTR               11 (data)
            156 LOAD_CONST               4 (('members',))
            158 CALL_FUNCTION_KW         1
            160 STORE_FAST              10 (module_obj)

480         162 LOAD_FAST                0 (self)
            164 LOAD_ATTR                6 (scope)
            166 LOAD_METHOD             12 (set)
            168 LOAD_FAST                3 (name)
            170 LOAD_FAST               10 (module_obj)
            172 CALL_METHOD              2
            174 POP_TOP
            176 JUMP_ABSOLUTE            6
        >>  178 LOAD_CONST               0 (None)
            180 RETURN_VALUE

Disassembly of <code object visit_ImportFrom at 0x100e36710, file "./interp.py", line 482>:
483           0 LOAD_FAST                1 (node)
              2 LOAD_ATTR                0 (module)
              4 STORE_FAST               2 (module_name)

485           6 LOAD_CONST               1 ('')
              8 STORE_FAST               3 (contents)

486          10 LOAD_GLOBAL              1 (open)
             12 LOAD_FAST                2 (module_name)
             14 FORMAT_VALUE             0
             16 LOAD_CONST               2 ('.py')
             18 BUILD_STRING             2
             20 LOAD_CONST               3 ('r')
             22 CALL_FUNCTION            2
             24 SETUP_WITH              24 (to 50)
             26 STORE_FAST               4 (f)

487          28 LOAD_FAST                4 (f)
             30 LOAD_METHOD              2 (read)
             32 CALL_METHOD              0
             34 STORE_FAST               3 (contents)
             36 POP_BLOCK
             38 LOAD_CONST               0 (None)
             40 DUP_TOP
             42 DUP_TOP
             44 CALL_FUNCTION            3
             46 POP_TOP
             48 JUMP_FORWARD            16 (to 66)
        >>   50 WITH_EXCEPT_START
             52 POP_JUMP_IF_TRUE        56
             54 RERAISE
        >>   56 POP_TOP
             58 POP_TOP
             60 POP_TOP
             62 POP_EXCEPT
             64 POP_TOP

488     >>   66 LOAD_GLOBAL              3 (parse)
             68 LOAD_FAST                3 (contents)
             70 CALL_FUNCTION            1
             72 STORE_FAST               5 (module)

490          74 LOAD_FAST                0 (self)
             76 LOAD_ATTR                4 (scope)
             78 STORE_FAST               6 (parent_scope)

491          80 LOAD_FAST                0 (self)
             82 LOAD_ATTR                5 (globals)
             84 STORE_FAST               7 (parent_globals)

493          86 LOAD_GLOBAL              6 (Scope)
             88 CALL_FUNCTION            0
             90 STORE_FAST               8 (module_scope)

494          92 LOAD_FAST                8 (module_scope)
             94 LOAD_FAST                0 (self)
             96 STORE_ATTR               4 (scope)

495          98 LOAD_FAST                8 (module_scope)
            100 LOAD_FAST                0 (self)
            102 STORE_ATTR               5 (globals)

497         104 LOAD_FAST                0 (self)
            106 LOAD_METHOD              7 (visit)
            108 LOAD_FAST                5 (module)
            110 CALL_METHOD              1
            112 POP_TOP

499         114 LOAD_FAST                6 (parent_scope)
            116 LOAD_FAST                0 (self)
            118 STORE_ATTR               4 (scope)

500         120 LOAD_FAST                7 (parent_globals)
            122 LOAD_FAST                0 (self)
            124 STORE_ATTR               5 (globals)

502         126 LOAD_FAST                1 (node)
            128 LOAD_ATTR                8 (names)
            130 GET_ITER
        >>  132 FOR_ITER                96 (to 230)
            134 STORE_FAST               9 (alias)

503         136 LOAD_FAST                9 (alias)
            138 LOAD_ATTR                9 (name)
            140 STORE_FAST              10 (name)

504         142 LOAD_FAST               10 (name)
            144 LOAD_CONST               4 ('*')
            146 COMPARE_OP               2 (==)
            148 POP_JUMP_IF_FALSE      190

505         150 LOAD_FAST                8 (module_scope)
            152 LOAD_ATTR               10 (data)
            154 LOAD_METHOD             11 (items)
            156 CALL_METHOD              0
            158 GET_ITER
        >>  160 FOR_ITER                22 (to 184)
            162 UNPACK_SEQUENCE          2
            164 STORE_FAST              11 (member)
            166 STORE_FAST              12 (value)

506         168 LOAD_FAST                0 (self)
            170 LOAD_ATTR                4 (scope)
            172 LOAD_METHOD             12 (set)
            174 LOAD_FAST               11 (member)
            176 LOAD_FAST               12 (value)
            178 CALL_METHOD              2
            180 POP_TOP
            182 JUMP_ABSOLUTE          160

507     >>  184 POP_TOP
            186 LOAD_CONST               0 (None)
            188 RETURN_VALUE

509     >>  190 LOAD_FAST                9 (alias)
            192 LOAD_ATTR               13 (asname)
            194 POP_JUMP_IF_FALSE      202

510         196 LOAD_FAST                9 (alias)
            198 LOAD_ATTR               13 (asname)
            200 STORE_FAST              10 (name)

512     >>  202 LOAD_FAST                8 (module_scope)
            204 LOAD_METHOD             14 (get)
            206 LOAD_FAST                9 (alias)
            208 LOAD_ATTR                9 (name)
            210 CALL_METHOD              1
            212 STORE_FAST              11 (member)

513         214 LOAD_FAST                0 (self)
            216 LOAD_ATTR                4 (scope)
            218 LOAD_METHOD             12 (set)
            220 LOAD_FAST               10 (name)
            222 LOAD_FAST               11 (member)
            224 CALL_METHOD              2
            226 POP_TOP
            228 JUMP_ABSOLUTE          132
        >>  230 LOAD_CONST               0 (None)
            232 RETURN_VALUE

Disassembly of <code object visit_FunctionDef at 0x100e36870, file "./interp.py", line 515>:
516           0 LOAD_FAST                0 (self)
              2 LOAD_ATTR                0 (scope)
              4 STORE_FAST               2 (parent_scope)

517           6 LOAD_GLOBAL              1 (UserFunction)
              8 LOAD_FAST                1 (node)
             10 LOAD_FAST                2 (parent_scope)
             12 LOAD_FAST                0 (self)
             14 LOAD_ATTR                2 (globals)
             16 CALL_FUNCTION            3
             18 STORE_FAST               3 (function)

519          20 LOAD_GLOBAL              3 (reversed)
             22 LOAD_FAST                1 (node)
             24 LOAD_ATTR                4 (decorators)
             26 CALL_FUNCTION            1
             28 STORE_FAST               4 (decorators)

521          30 LOAD_FAST                4 (decorators)
             32 GET_ITER
        >>   34 FOR_ITER                62 (to 98)
             36 STORE_FAST               5 (decorator_node)

522          38 LOAD_FAST                0 (self)
             40 LOAD_METHOD              5 (visit)
             42 LOAD_FAST                5 (decorator_node)
             44 LOAD_ATTR                6 (value)
             46 CALL_METHOD              1
             48 STORE_FAST               6 (decorator)

524          50 LOAD_GLOBAL              7 (isinstance)
             52 LOAD_FAST                6 (decorator)
             54 LOAD_GLOBAL              8 (Function)
             56 CALL_FUNCTION            2
             58 POP_JUMP_IF_TRUE        82

525          60 LOAD_FAST                6 (decorator)
             62 LOAD_ATTR                9 (__class__)
             64 LOAD_ATTR               10 (__name__)
             66 STORE_FAST               7 (object_type)

526          68 LOAD_GLOBAL             11 (InterpreterError)
             70 LOAD_FAST                7 (object_type)
             72 FORMAT_VALUE             2 (repr)
             74 LOAD_CONST               1 (' object is not callable')
             76 BUILD_STRING             2
             78 CALL_FUNCTION            1
             80 RAISE_VARARGS            1

528     >>   82 LOAD_FAST                6 (decorator)
             84 LOAD_METHOD             12 (call)
             86 LOAD_FAST                0 (self)
             88 LOAD_FAST                3 (function)
             90 BUILD_LIST               1
             92 CALL_METHOD              2
             94 STORE_FAST               3 (function)
             96 JUMP_ABSOLUTE           34

530     >>   98 LOAD_FAST                0 (self)
            100 LOAD_ATTR                0 (scope)
            102 LOAD_METHOD             13 (set)
            104 LOAD_FAST                1 (node)
            106 LOAD_ATTR               14 (name)
            108 LOAD_FAST                3 (function)
            110 CALL_METHOD              2
            112 POP_TOP
            114 LOAD_CONST               0 (None)
            116 RETURN_VALUE

Disassembly of <code object assign at 0x100e367c0, file "./interp.py", line 532>:
533           0 LOAD_GLOBAL              0 (isinstance)
              2 LOAD_FAST                1 (target)
              4 LOAD_GLOBAL              1 (Name)
              6 CALL_FUNCTION            2
              8 POP_JUMP_IF_FALSE       28

534          10 LOAD_FAST                0 (self)
             12 LOAD_ATTR                2 (scope)
             14 LOAD_METHOD              3 (set)
             16 LOAD_FAST                1 (target)
             18 LOAD_ATTR                4 (id)
             20 LOAD_FAST                2 (value)
             22 CALL_METHOD              2
             24 POP_TOP
             26 JUMP_FORWARD           254 (to 282)

536     >>   28 LOAD_GLOBAL              0 (isinstance)
             30 LOAD_FAST                1 (target)
             32 LOAD_GLOBAL              5 (nodes)
             34 LOAD_ATTR                6 (List)
             36 LOAD_GLOBAL              5 (nodes)
             38 LOAD_ATTR                7 (Tuple)
             40 BUILD_TUPLE              2
             42 CALL_FUNCTION            2
             44 POP_JUMP_IF_FALSE      100
             46 LOAD_GLOBAL              0 (isinstance)

537          48 LOAD_FAST                2 (value)
             50 LOAD_GLOBAL              6 (List)
             52 LOAD_GLOBAL              7 (Tuple)
             54 LOAD_GLOBAL              8 (Deque)
             56 LOAD_GLOBAL              9 (Dict)
             58 BUILD_TUPLE              4

536          60 CALL_FUNCTION            2
             62 POP_JUMP_IF_FALSE      100

539          64 LOAD_GLOBAL             10 (zip)
             66 LOAD_FAST                1 (target)
             68 LOAD_ATTR               11 (elements)
             70 LOAD_FAST                2 (value)
             72 CALL_FUNCTION            2
             74 GET_ITER
        >>   76 FOR_ITER                20 (to 98)
             78 UNPACK_SEQUENCE          2
             80 STORE_FAST               3 (element)
             82 STORE_FAST               2 (value)

540          84 LOAD_FAST                0 (self)
             86 LOAD_METHOD             12 (assign)
             88 LOAD_FAST                3 (element)
             90 LOAD_FAST                2 (value)
             92 CALL_METHOD              2
             94 POP_TOP
             96 JUMP_ABSOLUTE           76
        >>   98 JUMP_FORWARD           182 (to 282)

542     >>  100 LOAD_GLOBAL              0 (isinstance)
            102 LOAD_FAST                1 (target)
            104 LOAD_GLOBAL             13 (Subscript)
            106 CALL_FUNCTION            2
            108 EXTENDED_ARG             1
            110 POP_JUMP_IF_FALSE      272

543         112 LOAD_FAST                0 (self)
            114 LOAD_METHOD             14 (visit)
            116 LOAD_FAST                1 (target)
            118 LOAD_ATTR               15 (value)
            120 CALL_METHOD              1
            122 STORE_FAST               4 (obj)

545         124 LOAD_GLOBAL              0 (isinstance)
            126 LOAD_FAST                4 (obj)
            128 LOAD_GLOBAL              6 (List)
            130 LOAD_GLOBAL              8 (Deque)
            132 BUILD_TUPLE              2
            134 CALL_FUNCTION            2
            136 POP_JUMP_IF_FALSE      216

546         138 LOAD_FAST                0 (self)
            140 LOAD_METHOD             14 (visit)
            142 LOAD_FAST                1 (target)
            144 LOAD_ATTR               16 (key)
            146 CALL_METHOD              1
            148 STORE_FAST               5 (key)

547         150 LOAD_GLOBAL              0 (isinstance)
            152 LOAD_FAST                5 (key)
            154 LOAD_GLOBAL             17 (Value)
            156 CALL_FUNCTION            2
            158 POP_JUMP_IF_FALSE      172
            160 LOAD_GLOBAL              0 (isinstance)
            162 LOAD_FAST                5 (key)
            164 LOAD_ATTR               15 (value)
            166 LOAD_GLOBAL             18 (int)
            168 CALL_FUNCTION            2
            170 POP_JUMP_IF_TRUE       202

548     >>  172 LOAD_GLOBAL             19 (InterpreterError)

549         174 LOAD_CONST               1 ('Expected integer index for ')
            176 LOAD_GLOBAL             20 (type)
            178 LOAD_FAST                4 (obj)
            180 CALL_FUNCTION            1
            182 LOAD_ATTR               21 (__name__)
            184 FORMAT_VALUE             0
            186 LOAD_CONST               2 (', got ')

550         188 LOAD_FAST                5 (key)
            190 LOAD_METHOD             22 (repr)
            192 CALL_METHOD              0

549         194 FORMAT_VALUE             0
            196 BUILD_STRING             4

548         198 CALL_FUNCTION            1
            200 RAISE_VARARGS            1

553     >>  202 LOAD_FAST                2 (value)
            204 LOAD_FAST                4 (obj)
            206 LOAD_ATTR               23 (_data)
            208 LOAD_FAST                5 (key)
            210 LOAD_ATTR               15 (value)
            212 STORE_SUBSCR
            214 JUMP_FORWARD            54 (to 270)

555     >>  216 LOAD_GLOBAL              0 (isinstance)
            218 LOAD_FAST                4 (obj)
            220 LOAD_GLOBAL              9 (Dict)
            222 CALL_FUNCTION            2
            224 POP_JUMP_IF_FALSE      250

556         226 LOAD_FAST                0 (self)
            228 LOAD_METHOD             14 (visit)
            230 LOAD_FAST                1 (target)
            232 LOAD_ATTR               16 (key)
            234 CALL_METHOD              1
            236 STORE_FAST               5 (key)

557         238 LOAD_FAST                2 (value)
            240 LOAD_FAST                4 (obj)
            242 LOAD_ATTR               24 (_dict)
            244 LOAD_FAST                5 (key)
            246 STORE_SUBSCR
            248 JUMP_FORWARD            20 (to 270)

560     >>  250 LOAD_GLOBAL             19 (InterpreterError)

561         252 LOAD_CONST               3 ('Index not implemented for ')
            254 LOAD_GLOBAL             20 (type)
            256 LOAD_FAST                4 (obj)
            258 CALL_FUNCTION            1
            260 LOAD_ATTR               21 (__name__)
            262 FORMAT_VALUE             0
            264 BUILD_STRING             2

560         266 CALL_FUNCTION            1
            268 RAISE_VARARGS            1
        >>  270 JUMP_FORWARD            10 (to 282)

565     >>  272 LOAD_GLOBAL             25 (NotImplementedError)
            274 LOAD_FAST                1 (target)
            276 LOAD_FAST                2 (value)
            278 CALL_FUNCTION            2
            280 RAISE_VARARGS            1
        >>  282 LOAD_CONST               0 (None)
            284 RETURN_VALUE

Disassembly of <code object visit_Assign at 0x100e36920, file "./interp.py", line 567>:
568           0 LOAD_FAST                0 (self)
              2 LOAD_METHOD              0 (visit)
              4 LOAD_FAST                1 (node)
              6 LOAD_ATTR                1 (value)
              8 CALL_METHOD              1
             10 STORE_FAST               2 (value)

569          12 LOAD_GLOBAL              2 (len)
             14 LOAD_FAST                1 (node)
             16 LOAD_ATTR                3 (targets)
             18 CALL_FUNCTION            1
             20 LOAD_CONST               1 (1)
             22 COMPARE_OP               2 (==)
             24 POP_JUMP_IF_TRUE        30
             26 LOAD_ASSERTION_ERROR
             28 RAISE_VARARGS            1

570     >>   30 LOAD_FAST                1 (node)
             32 LOAD_ATTR                3 (targets)
             34 LOAD_CONST               2 (0)
             36 BINARY_SUBSCR
             38 STORE_FAST               3 (target)

572          40 LOAD_FAST                0 (self)
             42 LOAD_METHOD              4 (assign)
             44 LOAD_FAST                3 (target)
             46 LOAD_FAST                2 (value)
             48 CALL_METHOD              2
             50 POP_TOP
             52 LOAD_CONST               0 (None)
             54 RETURN_VALUE

Disassembly of <code object visit_AugAssign at 0x100e36b30, file "./interp.py", line 574>:
575           0 LOAD_FAST                0 (self)
              2 LOAD_METHOD              0 (visit)
              4 LOAD_FAST                1 (node)
              6 LOAD_ATTR                1 (value)
              8 CALL_METHOD              1
             10 STORE_FAST               2 (increment)

576          12 LOAD_GLOBAL              2 (isinstance)
             14 LOAD_FAST                2 (increment)
             16 LOAD_GLOBAL              3 (Value)
             18 CALL_FUNCTION            2
             20 POP_JUMP_IF_TRUE        26
             22 LOAD_ASSERTION_ERROR
             24 RAISE_VARARGS            1

578     >>   26 LOAD_FAST                1 (node)
             28 LOAD_ATTR                4 (target)
             30 STORE_FAST               3 (target)

579          32 LOAD_GLOBAL              2 (isinstance)
             34 LOAD_FAST                3 (target)
             36 LOAD_GLOBAL              5 (Name)
             38 CALL_FUNCTION            2
             40 POP_JUMP_IF_FALSE      120

580          42 LOAD_FAST                0 (self)
             44 LOAD_METHOD              0 (visit)
             46 LOAD_FAST                3 (target)
             48 CALL_METHOD              1
             50 STORE_FAST               4 (current_value)

581          52 LOAD_GLOBAL              2 (isinstance)
             54 LOAD_FAST                4 (current_value)
             56 LOAD_GLOBAL              3 (Value)
             58 CALL_FUNCTION            2
             60 POP_JUMP_IF_TRUE        66
             62 LOAD_ASSERTION_ERROR
             64 RAISE_VARARGS            1

582     >>   66 LOAD_FAST                1 (node)
             68 LOAD_ATTR                6 (op)
             70 LOAD_CONST               1 ('+=')
             72 COMPARE_OP               2 (==)
             74 POP_JUMP_IF_FALSE       94

583          76 LOAD_GLOBAL              3 (Value)
             78 LOAD_FAST                4 (current_value)
             80 LOAD_ATTR                1 (value)
             82 LOAD_FAST                2 (increment)
             84 LOAD_ATTR                1 (value)
             86 BINARY_ADD
             88 CALL_FUNCTION            1
             90 STORE_FAST               5 (new_value)
             92 JUMP_FORWARD             8 (to 102)

585     >>   94 LOAD_GLOBAL              7 (NotImplementedError)
             96 LOAD_FAST                1 (node)
             98 CALL_FUNCTION            1
            100 RAISE_VARARGS            1

587     >>  102 LOAD_FAST                0 (self)
            104 LOAD_ATTR                8 (scope)
            106 LOAD_METHOD              9 (set)
            108 LOAD_FAST                3 (target)
            110 LOAD_ATTR               10 (id)
            112 LOAD_FAST                5 (new_value)
            114 CALL_METHOD              2
            116 POP_TOP
            118 JUMP_FORWARD             8 (to 128)

589     >>  120 LOAD_GLOBAL              7 (NotImplementedError)
            122 LOAD_FAST                3 (target)
            124 CALL_FUNCTION            1
            126 RAISE_VARARGS            1
        >>  128 LOAD_CONST               0 (None)
            130 RETURN_VALUE

Disassembly of <code object visit_If at 0x100e369d0, file "./interp.py", line 591>:
592           0 LOAD_GLOBAL              0 (is_truthy)
              2 LOAD_FAST                0 (self)
              4 LOAD_METHOD              1 (visit)
              6 LOAD_FAST                1 (node)
              8 LOAD_ATTR                2 (condition)
             10 CALL_METHOD              1
             12 CALL_FUNCTION            1
             14 POP_JUMP_IF_FALSE       40

593          16 LOAD_FAST                1 (node)
             18 LOAD_ATTR                3 (body)
             20 GET_ITER
        >>   22 FOR_ITER                14 (to 38)
             24 STORE_FAST               2 (stmt)

594          26 LOAD_FAST                0 (self)
             28 LOAD_METHOD              1 (visit)
             30 LOAD_FAST                2 (stmt)
             32 CALL_METHOD              1
             34 POP_TOP
             36 JUMP_ABSOLUTE           22
        >>   38 JUMP_FORWARD            22 (to 62)

596     >>   40 LOAD_FAST                1 (node)
             42 LOAD_ATTR                4 (orelse)
             44 GET_ITER
        >>   46 FOR_ITER                14 (to 62)
             48 STORE_FAST               2 (stmt)

597          50 LOAD_FAST                0 (self)
             52 LOAD_METHOD              1 (visit)
             54 LOAD_FAST                2 (stmt)
             56 CALL_METHOD              1
             58 POP_TOP
             60 JUMP_ABSOLUTE           46
        >>   62 LOAD_CONST               0 (None)
             64 RETURN_VALUE

Disassembly of <code object visit_For at 0x100e36d40, file "./interp.py", line 599>:
600           0 LOAD_GLOBAL              0 (isinstance)
              2 LOAD_FAST                1 (node)
              4 LOAD_ATTR                1 (iterable)
              6 LOAD_GLOBAL              2 (nodes)
              8 LOAD_ATTR                3 (List)
             10 LOAD_GLOBAL              2 (nodes)
             12 LOAD_ATTR                4 (Tuple)
             14 BUILD_TUPLE              2
             16 CALL_FUNCTION            2
             18 POP_JUMP_IF_FALSE       44

601          20 LOAD_CLOSURE             0 (self)
             22 BUILD_TUPLE              1
             24 LOAD_CONST               1 (<code object <listcomp> at 0x100e36be0, file "./interp.py", line 601>)
             26 LOAD_CONST               2 ('Interpreter.visit_For.<locals>.<listcomp>')
             28 MAKE_FUNCTION            8 (closure)
             30 LOAD_FAST                1 (node)
             32 LOAD_ATTR                1 (iterable)
             34 LOAD_ATTR                5 (elements)
             36 GET_ITER
             38 CALL_FUNCTION            1
             40 STORE_FAST               2 (elements)
             42 JUMP_FORWARD            90 (to 134)

602     >>   44 LOAD_GLOBAL              0 (isinstance)
             46 LOAD_FAST                1 (node)
             48 LOAD_ATTR                1 (iterable)
             50 LOAD_GLOBAL              2 (nodes)
             52 LOAD_ATTR                6 (Dict)
             54 CALL_FUNCTION            2
             56 POP_JUMP_IF_FALSE       82

603          58 LOAD_CLOSURE             0 (self)
             60 BUILD_TUPLE              1
             62 LOAD_CONST               3 (<code object <listcomp> at 0x100e36c90, file "./interp.py", line 603>)
             64 LOAD_CONST               2 ('Interpreter.visit_For.<locals>.<listcomp>')
             66 MAKE_FUNCTION            8 (closure)
             68 LOAD_FAST                1 (node)
             70 LOAD_ATTR                1 (iterable)
             72 LOAD_ATTR                7 (keys)
             74 GET_ITER
             76 CALL_FUNCTION            1
             78 STORE_FAST               2 (elements)
             80 JUMP_FORWARD            52 (to 134)

605     >>   82 LOAD_DEREF               0 (self)
             84 LOAD_METHOD              8 (visit)
             86 LOAD_FAST                1 (node)
             88 LOAD_ATTR                1 (iterable)
             90 CALL_METHOD              1
             92 STORE_FAST               2 (elements)

606          94 LOAD_GLOBAL              0 (isinstance)
             96 LOAD_FAST                2 (elements)
             98 LOAD_GLOBAL              3 (List)
            100 LOAD_GLOBAL              4 (Tuple)
            102 LOAD_GLOBAL              9 (Deque)
            104 LOAD_GLOBAL              6 (Dict)
            106 BUILD_TUPLE              4
            108 CALL_FUNCTION            2
            110 POP_JUMP_IF_TRUE       134

607         112 LOAD_GLOBAL             10 (InterpreterError)

608         114 LOAD_CONST               4 ('Object of type ')
            116 LOAD_GLOBAL             11 (type)
            118 LOAD_FAST                2 (elements)
            120 CALL_FUNCTION            1
            122 LOAD_ATTR               12 (__name__)
            124 FORMAT_VALUE             0
            126 LOAD_CONST               5 (' is not iterable')
            128 BUILD_STRING             3

607         130 CALL_FUNCTION            1
            132 RAISE_VARARGS            1

611     >>  134 LOAD_FAST                2 (elements)
            136 GET_ITER
        >>  138 FOR_ITER                92 (to 232)
            140 STORE_FAST               3 (element)

612         142 LOAD_DEREF               0 (self)
            144 LOAD_METHOD             13 (assign)
            146 LOAD_FAST                1 (node)
            148 LOAD_ATTR               14 (target)
            150 LOAD_FAST                3 (element)
            152 CALL_METHOD              2
            154 POP_TOP

614         156 LOAD_FAST                1 (node)
            158 LOAD_ATTR               15 (body)
            160 GET_ITER
        >>  162 FOR_ITER                66 (to 230)
            164 STORE_FAST               4 (stmt)

615         166 SETUP_FINALLY           14 (to 182)

616         168 LOAD_DEREF               0 (self)
            170 LOAD_METHOD              8 (visit)
            172 LOAD_FAST                4 (stmt)
            174 CALL_METHOD              1
            176 POP_TOP
            178 POP_BLOCK
            180 JUMP_ABSOLUTE          162

617     >>  182 DUP_TOP
            184 LOAD_GLOBAL             16 (Break)
            186 JUMP_IF_NOT_EXC_MATCH   204
            188 POP_TOP
            190 POP_TOP
            192 POP_TOP

618         194 POP_EXCEPT
            196 POP_TOP
            198 POP_TOP
            200 LOAD_CONST               0 (None)
            202 RETURN_VALUE

619     >>  204 DUP_TOP
            206 LOAD_GLOBAL             17 (Continue)
            208 JUMP_IF_NOT_EXC_MATCH   226
            210 POP_TOP
            212 POP_TOP
            214 POP_TOP

620         216 POP_EXCEPT
            218 POP_TOP
            220 JUMP_ABSOLUTE          138
            222 POP_EXCEPT
            224 JUMP_ABSOLUTE          162
        >>  226 RERAISE
            228 JUMP_ABSOLUTE          162
        >>  230 JUMP_ABSOLUTE          138
        >>  232 LOAD_CONST               0 (None)
            234 RETURN_VALUE

Disassembly of <code object <listcomp> at 0x100e36be0, file "./interp.py", line 601>:
601           0 BUILD_LIST               0
              2 LOAD_FAST                0 (.0)
        >>    4 FOR_ITER                14 (to 20)
              6 STORE_FAST               1 (element)
              8 LOAD_DEREF               0 (self)
             10 LOAD_METHOD              0 (visit)
             12 LOAD_FAST                1 (element)
             14 CALL_METHOD              1
             16 LIST_APPEND              2
             18 JUMP_ABSOLUTE            4
        >>   20 RETURN_VALUE

Disassembly of <code object <listcomp> at 0x100e36c90, file "./interp.py", line 603>:
603           0 BUILD_LIST               0
              2 LOAD_FAST                0 (.0)
        >>    4 FOR_ITER                14 (to 20)
              6 STORE_FAST               1 (element)
              8 LOAD_DEREF               0 (self)
             10 LOAD_METHOD              0 (visit)
             12 LOAD_FAST                1 (element)
             14 CALL_METHOD              1
             16 LIST_APPEND              2
             18 JUMP_ABSOLUTE            4
        >>   20 RETURN_VALUE

Disassembly of <code object visit_While at 0x100e36df0, file "./interp.py", line 622>:
623     >>    0 LOAD_GLOBAL              0 (is_truthy)
              2 LOAD_FAST                0 (self)
              4 LOAD_METHOD              1 (visit)
              6 LOAD_FAST                1 (node)
              8 LOAD_ATTR                2 (condition)
             10 CALL_METHOD              1
             12 CALL_FUNCTION            1
             14 POP_JUMP_IF_FALSE       90

624          16 LOAD_FAST                1 (node)
             18 LOAD_ATTR                3 (body)
             20 GET_ITER
        >>   22 FOR_ITER                64 (to 88)
             24 STORE_FAST               2 (stmt)

625          26 SETUP_FINALLY           14 (to 42)

626          28 LOAD_FAST                0 (self)
             30 LOAD_METHOD              1 (visit)
             32 LOAD_FAST                2 (stmt)
             34 CALL_METHOD              1
             36 POP_TOP
             38 POP_BLOCK
             40 JUMP_ABSOLUTE           22

627     >>   42 DUP_TOP
             44 LOAD_GLOBAL              4 (Break)
             46 JUMP_IF_NOT_EXC_MATCH    62
             48 POP_TOP
             50 POP_TOP
             52 POP_TOP

628          54 POP_EXCEPT
             56 POP_TOP
             58 LOAD_CONST               0 (None)
             60 RETURN_VALUE

629     >>   62 DUP_TOP
             64 LOAD_GLOBAL              5 (Continue)
             66 JUMP_IF_NOT_EXC_MATCH    84
             68 POP_TOP
             70 POP_TOP
             72 POP_TOP

630          74 POP_EXCEPT
             76 POP_TOP
             78 JUMP_ABSOLUTE            0
             80 POP_EXCEPT
             82 JUMP_ABSOLUTE           22
        >>   84 RERAISE
             86 JUMP_ABSOLUTE           22
        >>   88 JUMP_ABSOLUTE            0
        >>   90 LOAD_CONST               0 (None)
             92 RETURN_VALUE

Disassembly of <code object visit_Break at 0x100e36ea0, file "./interp.py", line 634>:
635           0 LOAD_GLOBAL              0 (Break)
              2 RAISE_VARARGS            1
              4 LOAD_CONST               0 (None)
              6 RETURN_VALUE

Disassembly of <code object visit_Continue at 0x100e36f50, file "./interp.py", line 637>:
638           0 LOAD_GLOBAL              0 (Continue)
              2 RAISE_VARARGS            1
              4 LOAD_CONST               0 (None)
              6 RETURN_VALUE

Disassembly of <code object visit_Return at 0x100e33030, file "./interp.py", line 640>:
641           0 LOAD_GLOBAL              0 (Return)
              2 LOAD_FAST                0 (self)
              4 LOAD_METHOD              1 (visit)
              6 LOAD_FAST                1 (node)
              8 LOAD_ATTR                2 (value)
             10 CALL_METHOD              1
             12 CALL_FUNCTION            1
             14 RAISE_VARARGS            1
             16 LOAD_CONST               0 (None)
             18 RETURN_VALUE

Disassembly of <code object visit_Pass at 0x100e330e0, file "./interp.py", line 643>:
644           0 LOAD_CONST               0 (None)
              2 RETURN_VALUE

Disassembly of <code object visit_ExprStmt at 0x100e33190, file "./interp.py", line 646>:
647           0 LOAD_FAST                0 (self)
              2 LOAD_METHOD              0 (visit)
              4 LOAD_FAST                1 (node)
              6 LOAD_ATTR                1 (value)
              8 CALL_METHOD              1
             10 POP_TOP
             12 LOAD_CONST               0 (None)
             14 RETURN_VALUE

Disassembly of <code object visit_Compare at 0x100e335b0, file "./interp.py", line 649>:
650           0 LOAD_FAST                0 (self)
              2 LOAD_METHOD              0 (visit)
              4 LOAD_FAST                1 (node)
              6 LOAD_ATTR                1 (left)
              8 CALL_METHOD              1
             10 STORE_FAST               2 (lhs)

651          12 LOAD_FAST                0 (self)
             14 LOAD_METHOD              0 (visit)
             16 LOAD_FAST                1 (node)
             18 LOAD_ATTR                2 (right)
             20 CALL_METHOD              1
             22 STORE_FAST               3 (rhs)

652          24 LOAD_GLOBAL              3 (isinstance)
             26 LOAD_FAST                2 (lhs)
             28 LOAD_GLOBAL              4 (Value)
             30 CALL_FUNCTION            2
             32 POP_JUMP_IF_FALSE       42

653          34 LOAD_FAST                2 (lhs)
             36 LOAD_ATTR                5 (value)
             38 STORE_DEREF              0 (left)
             40 JUMP_FORWARD            78 (to 120)

654     >>   42 LOAD_GLOBAL              3 (isinstance)
             44 LOAD_FAST                2 (lhs)
             46 LOAD_GLOBAL              6 (List)
             48 LOAD_GLOBAL              7 (Tuple)
             50 LOAD_GLOBAL              8 (Deque)
             52 BUILD_TUPLE              3
             54 CALL_FUNCTION            2
             56 POP_JUMP_IF_FALSE       66

655          58 LOAD_FAST                2 (lhs)
             60 LOAD_ATTR                9 (_data)
             62 STORE_DEREF              0 (left)
             64 JUMP_FORWARD            54 (to 120)

656     >>   66 LOAD_GLOBAL              3 (isinstance)
             68 LOAD_FAST                2 (lhs)
             70 LOAD_GLOBAL             10 (Dict)
             72 CALL_FUNCTION            2
             74 POP_JUMP_IF_FALSE       84

657          76 LOAD_FAST                2 (lhs)
             78 LOAD_ATTR               11 (_dict)
             80 STORE_DEREF              0 (left)
             82 JUMP_FORWARD            36 (to 120)

659     >>   84 LOAD_GLOBAL             12 (InterpreterError)
             86 LOAD_CONST               1 ('Cannot do ')
             88 LOAD_FAST                2 (lhs)
             90 LOAD_METHOD             13 (repr)
             92 CALL_METHOD              0
             94 FORMAT_VALUE             0
             96 LOAD_CONST               2 (' ')
             98 LOAD_FAST                1 (node)
            100 LOAD_ATTR               14 (op)
            102 FORMAT_VALUE             2 (repr)
            104 LOAD_CONST               2 (' ')
            106 LOAD_FAST                3 (rhs)
            108 LOAD_METHOD             13 (repr)
            110 CALL_METHOD              0
            112 FORMAT_VALUE             0
            114 BUILD_STRING             6
            116 CALL_FUNCTION            1
            118 RAISE_VARARGS            1

661     >>  120 LOAD_GLOBAL              3 (isinstance)
            122 LOAD_FAST                3 (rhs)
            124 LOAD_GLOBAL              4 (Value)
            126 CALL_FUNCTION            2
            128 POP_JUMP_IF_FALSE      138

662         130 LOAD_FAST                3 (rhs)
            132 LOAD_ATTR                5 (value)
            134 STORE_FAST               4 (right)
            136 JUMP_FORWARD            78 (to 216)

663     >>  138 LOAD_GLOBAL              3 (isinstance)
            140 LOAD_FAST                3 (rhs)
            142 LOAD_GLOBAL              6 (List)
            144 LOAD_GLOBAL              7 (Tuple)
            146 LOAD_GLOBAL              8 (Deque)
            148 BUILD_TUPLE              3
            150 CALL_FUNCTION            2
            152 POP_JUMP_IF_FALSE      162

664         154 LOAD_FAST                3 (rhs)
            156 LOAD_ATTR                9 (_data)
            158 STORE_FAST               4 (right)
            160 JUMP_FORWARD            54 (to 216)

665     >>  162 LOAD_GLOBAL              3 (isinstance)
            164 LOAD_FAST                3 (rhs)
            166 LOAD_GLOBAL             10 (Dict)
            168 CALL_FUNCTION            2
            170 POP_JUMP_IF_FALSE      180

666         172 LOAD_FAST                3 (rhs)
            174 LOAD_ATTR               11 (_dict)
            176 STORE_FAST               4 (right)
            178 JUMP_FORWARD            36 (to 216)

668     >>  180 LOAD_GLOBAL             12 (InterpreterError)
            182 LOAD_CONST               1 ('Cannot do ')
            184 LOAD_FAST                2 (lhs)
            186 LOAD_METHOD             13 (repr)
            188 CALL_METHOD              0
            190 FORMAT_VALUE             0
            192 LOAD_CONST               2 (' ')
            194 LOAD_FAST                1 (node)
            196 LOAD_ATTR               14 (op)
            198 FORMAT_VALUE             2 (repr)
            200 LOAD_CONST               2 (' ')
            202 LOAD_FAST                3 (rhs)
            204 LOAD_METHOD             13 (repr)
            206 CALL_METHOD              0
            208 FORMAT_VALUE             0
            210 BUILD_STRING             6
            212 CALL_FUNCTION            1
            214 RAISE_VARARGS            1

670     >>  216 LOAD_FAST                1 (node)
            218 LOAD_ATTR               14 (op)
            220 LOAD_CONST               3 ('==')
            222 COMPARE_OP               2 (==)
            224 POP_JUMP_IF_FALSE      238

671         226 LOAD_GLOBAL              4 (Value)
            228 LOAD_DEREF               0 (left)
            230 LOAD_FAST                4 (right)
            232 COMPARE_OP               2 (==)
            234 CALL_FUNCTION            1
            236 RETURN_VALUE

672     >>  238 LOAD_FAST                1 (node)
            240 LOAD_ATTR               14 (op)
            242 LOAD_CONST               4 ('!=')
            244 COMPARE_OP               2 (==)
            246 EXTENDED_ARG             1
            248 POP_JUMP_IF_FALSE      262

673         250 LOAD_GLOBAL              4 (Value)
            252 LOAD_DEREF               0 (left)
            254 LOAD_FAST                4 (right)
            256 COMPARE_OP               3 (!=)
            258 CALL_FUNCTION            1
            260 RETURN_VALUE

674     >>  262 LOAD_FAST                1 (node)
            264 LOAD_ATTR               14 (op)
            266 LOAD_CONST               5 ('<')
            268 COMPARE_OP               2 (==)
            270 EXTENDED_ARG             1
            272 POP_JUMP_IF_FALSE      286

675         274 LOAD_GLOBAL              4 (Value)
            276 LOAD_DEREF               0 (left)
            278 LOAD_FAST                4 (right)
            280 COMPARE_OP               0 (<)
            282 CALL_FUNCTION            1
            284 RETURN_VALUE

676     >>  286 LOAD_FAST                1 (node)
            288 LOAD_ATTR               14 (op)
            290 LOAD_CONST               6 ('>')
            292 COMPARE_OP               2 (==)
            294 EXTENDED_ARG             1
            296 POP_JUMP_IF_FALSE      310

677         298 LOAD_GLOBAL              4 (Value)
            300 LOAD_DEREF               0 (left)
            302 LOAD_FAST                4 (right)
            304 COMPARE_OP               4 (>)
            306 CALL_FUNCTION            1
            308 RETURN_VALUE

678     >>  310 LOAD_FAST                1 (node)
            312 LOAD_ATTR               14 (op)
            314 LOAD_CONST               7 ('<=')
            316 COMPARE_OP               2 (==)
            318 EXTENDED_ARG             1
            320 POP_JUMP_IF_FALSE      334

679         322 LOAD_GLOBAL              4 (Value)
            324 LOAD_DEREF               0 (left)
            326 LOAD_FAST                4 (right)
            328 COMPARE_OP               1 (<=)
            330 CALL_FUNCTION            1
            332 RETURN_VALUE

680     >>  334 LOAD_FAST                1 (node)
            336 LOAD_ATTR               14 (op)
            338 LOAD_CONST               8 ('>=')
            340 COMPARE_OP               2 (==)
            342 EXTENDED_ARG             1
            344 POP_JUMP_IF_FALSE      358

681         346 LOAD_GLOBAL              4 (Value)
            348 LOAD_DEREF               0 (left)
            350 LOAD_FAST                4 (right)
            352 COMPARE_OP               5 (>=)
            354 CALL_FUNCTION            1
            356 RETURN_VALUE

682     >>  358 LOAD_FAST                1 (node)
            360 LOAD_ATTR               14 (op)
            362 LOAD_CONST               9 ('in')
            364 COMPARE_OP               2 (==)
            366 EXTENDED_ARG             1
            368 POP_JUMP_IF_FALSE      440

683         370 LOAD_GLOBAL              3 (isinstance)
            372 LOAD_FAST                4 (right)
            374 LOAD_GLOBAL             15 (str)
            376 CALL_FUNCTION            2
            378 EXTENDED_ARG             1
            380 POP_JUMP_IF_FALSE      394

684         382 LOAD_GLOBAL              4 (Value)
            384 LOAD_DEREF               0 (left)
            386 LOAD_FAST                4 (right)
            388 CONTAINS_OP              0
            390 CALL_FUNCTION            1
            392 RETURN_VALUE

685     >>  394 LOAD_GLOBAL              3 (isinstance)
            396 LOAD_FAST                4 (right)
            398 LOAD_GLOBAL             16 (list)
            400 LOAD_GLOBAL             17 (tuple)
            402 LOAD_GLOBAL             18 (deque)
            404 LOAD_GLOBAL             19 (dict)
            406 BUILD_TUPLE              4
            408 CALL_FUNCTION            2
            410 EXTENDED_ARG             1
            412 POP_JUMP_IF_FALSE      440

686         414 LOAD_GLOBAL              4 (Value)

687         416 LOAD_GLOBAL             20 (any)
            418 LOAD_CLOSURE             0 (left)
            420 BUILD_TUPLE              1
            422 LOAD_CONST              10 (<code object <genexpr> at 0x100e33240, file "./interp.py", line 687>)
            424 LOAD_CONST              11 ('Interpreter.visit_Compare.<locals>.<genexpr>')
            426 MAKE_FUNCTION            8 (closure)

689         428 LOAD_FAST                4 (right)

687         430 GET_ITER
            432 CALL_FUNCTION            1
            434 CALL_FUNCTION            1

686         436 CALL_FUNCTION            1
            438 RETURN_VALUE

692     >>  440 LOAD_FAST                1 (node)
            442 LOAD_ATTR               14 (op)
            444 LOAD_CONST              12 ('not in')
            446 COMPARE_OP               2 (==)
            448 EXTENDED_ARG             2
            450 POP_JUMP_IF_FALSE      522

693         452 LOAD_GLOBAL              3 (isinstance)
            454 LOAD_FAST                4 (right)
            456 LOAD_GLOBAL             15 (str)
            458 CALL_FUNCTION            2
            460 EXTENDED_ARG             1
            462 POP_JUMP_IF_FALSE      476

694         464 LOAD_GLOBAL              4 (Value)
            466 LOAD_DEREF               0 (left)
            468 LOAD_FAST                4 (right)
            470 CONTAINS_OP              1
            472 CALL_FUNCTION            1
            474 RETURN_VALUE

695     >>  476 LOAD_GLOBAL              3 (isinstance)
            478 LOAD_FAST                4 (right)
            480 LOAD_GLOBAL             16 (list)
            482 LOAD_GLOBAL             17 (tuple)
            484 LOAD_GLOBAL             18 (deque)
            486 BUILD_TUPLE              3
            488 CALL_FUNCTION            2
            490 EXTENDED_ARG             2
            492 POP_JUMP_IF_FALSE      522

696         494 LOAD_GLOBAL              4 (Value)

697         496 LOAD_GLOBAL             20 (any)
            498 LOAD_CLOSURE             0 (left)
            500 BUILD_TUPLE              1
            502 LOAD_CONST              13 (<code object <genexpr> at 0x100e332f0, file "./interp.py", line 697>)
            504 LOAD_CONST              11 ('Interpreter.visit_Compare.<locals>.<genexpr>')
            506 MAKE_FUNCTION            8 (closure)

699         508 LOAD_FAST                4 (right)

697         510 GET_ITER
            512 CALL_FUNCTION            1
            514 CALL_FUNCTION            1
            516 UNARY_NOT

696         518 CALL_FUNCTION            1
            520 RETURN_VALUE

702     >>  522 LOAD_FAST                1 (node)
            524 LOAD_ATTR               14 (op)
            526 LOAD_CONST              14 ('is')
            528 COMPARE_OP               2 (==)
            530 EXTENDED_ARG             2
            532 POP_JUMP_IF_FALSE      546

703         534 LOAD_GLOBAL              4 (Value)
            536 LOAD_DEREF               0 (left)
            538 LOAD_FAST                4 (right)
            540 IS_OP                    0
            542 CALL_FUNCTION            1
            544 RETURN_VALUE

704     >>  546 LOAD_FAST                1 (node)
            548 LOAD_ATTR               14 (op)
            550 LOAD_CONST              15 ('is not')
            552 COMPARE_OP               2 (==)
            554 EXTENDED_ARG             2
            556 POP_JUMP_IF_FALSE      570

705         558 LOAD_GLOBAL              4 (Value)
            560 LOAD_DEREF               0 (left)
            562 LOAD_FAST                4 (right)
            564 IS_OP                    1
            566 CALL_FUNCTION            1
            568 RETURN_VALUE

707     >>  570 LOAD_GLOBAL             21 (NotImplementedError)
            572 LOAD_FAST                1 (node)
            574 CALL_FUNCTION            1
            576 RAISE_VARARGS            1
            578 LOAD_CONST               0 (None)
            580 RETURN_VALUE

Disassembly of <code object <genexpr> at 0x100e33240, file "./interp.py", line 687>:
687           0 LOAD_FAST                0 (.0)
        >>    2 FOR_ITER                26 (to 30)

689           4 STORE_FAST               1 (element)

688           6 LOAD_GLOBAL              0 (isinstance)
              8 LOAD_FAST                1 (element)
             10 LOAD_GLOBAL              1 (Value)
             12 CALL_FUNCTION            2
             14 JUMP_IF_FALSE_OR_POP    24
             16 LOAD_FAST                1 (element)
             18 LOAD_ATTR                2 (value)
             20 LOAD_DEREF               0 (left)
             22 COMPARE_OP               2 (==)
        >>   24 YIELD_VALUE
             26 POP_TOP
             28 JUMP_ABSOLUTE            2
        >>   30 LOAD_CONST               0 (None)
             32 RETURN_VALUE

Disassembly of <code object <genexpr> at 0x100e332f0, file "./interp.py", line 697>:
697           0 LOAD_FAST                0 (.0)
        >>    2 FOR_ITER                26 (to 30)

699           4 STORE_FAST               1 (element)

698           6 LOAD_GLOBAL              0 (isinstance)
              8 LOAD_FAST                1 (element)
             10 LOAD_GLOBAL              1 (Value)
             12 CALL_FUNCTION            2
             14 JUMP_IF_FALSE_OR_POP    24
             16 LOAD_FAST                1 (element)
             18 LOAD_ATTR                2 (value)
             20 LOAD_DEREF               0 (left)
             22 COMPARE_OP               2 (==)
        >>   24 YIELD_VALUE
             26 POP_TOP
             28 JUMP_ABSOLUTE            2
        >>   30 LOAD_CONST               0 (None)
             32 RETURN_VALUE

Disassembly of <code object visit_BinOp at 0x100e33660, file "./interp.py", line 709>:
710           0 LOAD_FAST                0 (self)
              2 LOAD_METHOD              0 (visit)
              4 LOAD_FAST                1 (node)
              6 LOAD_ATTR                1 (left)
              8 CALL_METHOD              1
             10 STORE_FAST               2 (left)

711          12 LOAD_FAST                0 (self)
             14 LOAD_METHOD              0 (visit)
             16 LOAD_FAST                1 (node)
             18 LOAD_ATTR                2 (right)
             20 CALL_METHOD              1
             22 STORE_FAST               3 (right)

713          24 LOAD_GLOBAL              3 (isinstance)
             26 LOAD_FAST                2 (left)
             28 LOAD_GLOBAL              4 (Value)
             30 CALL_FUNCTION            2
             32 POP_JUMP_IF_FALSE       44
             34 LOAD_GLOBAL              3 (isinstance)
             36 LOAD_FAST                3 (right)
             38 LOAD_GLOBAL              4 (Value)
             40 CALL_FUNCTION            2
             42 POP_JUMP_IF_TRUE        84

714     >>   44 LOAD_GLOBAL              5 (InterpreterError)

715          46 LOAD_CONST               1 ('Cannot perform ')
             48 LOAD_FAST                1 (node)
             50 LOAD_ATTR                6 (op)
             52 FORMAT_VALUE             0
             54 LOAD_CONST               2 (' on a ')
             56 LOAD_GLOBAL              7 (type)
             58 LOAD_FAST                2 (left)
             60 CALL_FUNCTION            1
             62 LOAD_ATTR                8 (__name__)
             64 FORMAT_VALUE             0
             66 LOAD_CONST               3 (' and a ')

716          68 LOAD_GLOBAL              7 (type)
             70 LOAD_FAST                3 (right)
             72 CALL_FUNCTION            1
             74 LOAD_ATTR                8 (__name__)

715          76 FORMAT_VALUE             0
             78 BUILD_STRING             6

714          80 CALL_FUNCTION            1
             82 RAISE_VARARGS            1

719     >>   84 LOAD_FAST                1 (node)
             86 LOAD_ATTR                6 (op)
             88 LOAD_CONST               4 ('+')
             90 COMPARE_OP               2 (==)
             92 POP_JUMP_IF_FALSE      110

720          94 LOAD_GLOBAL              4 (Value)
             96 LOAD_FAST                2 (left)
             98 LOAD_ATTR                9 (value)
            100 LOAD_FAST                3 (right)
            102 LOAD_ATTR                9 (value)
            104 BINARY_ADD
            106 CALL_FUNCTION            1
            108 RETURN_VALUE

721     >>  110 LOAD_FAST                1 (node)
            112 LOAD_ATTR                6 (op)
            114 LOAD_CONST               5 ('-')
            116 COMPARE_OP               2 (==)
            118 POP_JUMP_IF_FALSE      136

722         120 LOAD_GLOBAL              4 (Value)
            122 LOAD_FAST                2 (left)
            124 LOAD_ATTR                9 (value)
            126 LOAD_FAST                3 (right)
            128 LOAD_ATTR                9 (value)
            130 BINARY_SUBTRACT
            132 CALL_FUNCTION            1
            134 RETURN_VALUE

723     >>  136 LOAD_FAST                1 (node)
            138 LOAD_ATTR                6 (op)
            140 LOAD_CONST               6 ('*')
            142 COMPARE_OP               2 (==)
            144 POP_JUMP_IF_FALSE      162

724         146 LOAD_GLOBAL              4 (Value)
            148 LOAD_FAST                2 (left)
            150 LOAD_ATTR                9 (value)
            152 LOAD_FAST                3 (right)
            154 LOAD_ATTR                9 (value)
            156 BINARY_MULTIPLY
            158 CALL_FUNCTION            1
            160 RETURN_VALUE

725     >>  162 LOAD_FAST                1 (node)
            164 LOAD_ATTR                6 (op)
            166 LOAD_CONST               7 ('//')
            168 COMPARE_OP               2 (==)
            170 POP_JUMP_IF_FALSE      188

726         172 LOAD_GLOBAL              4 (Value)
            174 LOAD_FAST                2 (left)
            176 LOAD_ATTR                9 (value)
            178 LOAD_FAST                3 (right)
            180 LOAD_ATTR                9 (value)
            182 BINARY_TRUE_DIVIDE
            184 CALL_FUNCTION            1
            186 RETURN_VALUE

728     >>  188 LOAD_GLOBAL             10 (NotImplementedError)
            190 LOAD_FAST                1 (node)
            192 CALL_FUNCTION            1
            194 RAISE_VARARGS            1
            196 LOAD_CONST               0 (None)
            198 RETURN_VALUE

Disassembly of <code object visit_BoolOp at 0x100e33710, file "./interp.py", line 730>:
731           0 LOAD_FAST                0 (self)
              2 LOAD_METHOD              0 (visit)
              4 LOAD_FAST                1 (node)
              6 LOAD_ATTR                1 (left)
              8 CALL_METHOD              1
             10 STORE_FAST               2 (left)

732          12 LOAD_FAST                0 (self)
             14 LOAD_METHOD              0 (visit)
             16 LOAD_FAST                1 (node)
             18 LOAD_ATTR                2 (right)
             20 CALL_METHOD              1
             22 STORE_FAST               3 (right)

734          24 LOAD_GLOBAL              3 (isinstance)
             26 LOAD_FAST                2 (left)
             28 LOAD_GLOBAL              4 (Value)
             30 CALL_FUNCTION            2
             32 POP_JUMP_IF_FALSE       44
             34 LOAD_GLOBAL              3 (isinstance)
             36 LOAD_FAST                3 (right)
             38 LOAD_GLOBAL              4 (Value)
             40 CALL_FUNCTION            2
             42 POP_JUMP_IF_TRUE        84

735     >>   44 LOAD_GLOBAL              5 (InterpreterError)

736          46 LOAD_CONST               1 ('Cannot perform ')
             48 LOAD_FAST                1 (node)
             50 LOAD_ATTR                6 (op)
             52 FORMAT_VALUE             2 (repr)
             54 LOAD_CONST               2 (' on a ')
             56 LOAD_GLOBAL              7 (type)
             58 LOAD_FAST                2 (left)
             60 CALL_FUNCTION            1
             62 LOAD_ATTR                8 (__name__)
             64 FORMAT_VALUE             2 (repr)
             66 LOAD_CONST               3 (' and a ')

737          68 LOAD_GLOBAL              7 (type)
             70 LOAD_FAST                3 (right)
             72 CALL_FUNCTION            1
             74 LOAD_ATTR                8 (__name__)

736          76 FORMAT_VALUE             2 (repr)
             78 BUILD_STRING             6

735          80 CALL_FUNCTION            1
             82 RAISE_VARARGS            1

740     >>   84 LOAD_FAST                1 (node)
             86 LOAD_ATTR                6 (op)
             88 LOAD_CONST               4 ('and')
             90 COMPARE_OP               2 (==)
             92 POP_JUMP_IF_FALSE      110

741          94 LOAD_GLOBAL              4 (Value)
             96 LOAD_FAST                2 (left)
             98 LOAD_ATTR                9 (value)
            100 JUMP_IF_FALSE_OR_POP   106
            102 LOAD_FAST                3 (right)
            104 LOAD_ATTR                9 (value)
        >>  106 CALL_FUNCTION            1
            108 RETURN_VALUE

742     >>  110 LOAD_FAST                1 (node)
            112 LOAD_ATTR                6 (op)
            114 LOAD_CONST               5 ('or')
            116 COMPARE_OP               2 (==)
            118 POP_JUMP_IF_FALSE      136

743         120 LOAD_GLOBAL              4 (Value)
            122 LOAD_FAST                2 (left)
            124 LOAD_ATTR                9 (value)
            126 JUMP_IF_TRUE_OR_POP    132
            128 LOAD_FAST                3 (right)
            130 LOAD_ATTR                9 (value)
        >>  132 CALL_FUNCTION            1
            134 RETURN_VALUE

745     >>  136 LOAD_GLOBAL             10 (AssertionError)
            138 LOAD_CONST               6 ("node.op must be 'and' or 'or', found ")
            140 LOAD_FAST                1 (node)
            142 LOAD_ATTR                6 (op)
            144 FORMAT_VALUE             2 (repr)
            146 BUILD_STRING             2
            148 CALL_FUNCTION            1
            150 RAISE_VARARGS            1
            152 LOAD_CONST               0 (None)
            154 RETURN_VALUE

Disassembly of <code object visit_UnaryOp at 0x100e33870, file "./interp.py", line 747>:
748           0 LOAD_FAST                0 (self)
              2 LOAD_METHOD              0 (visit)
              4 LOAD_FAST                1 (node)
              6 LOAD_ATTR                1 (value)
              8 CALL_METHOD              1
             10 STORE_FAST               2 (value)

749          12 LOAD_GLOBAL              2 (isinstance)
             14 LOAD_FAST                2 (value)
             16 LOAD_GLOBAL              3 (Value)
             18 CALL_FUNCTION            2
             20 POP_JUMP_IF_TRUE        42

750          22 LOAD_GLOBAL              4 (InterpreterError)
             24 LOAD_CONST               1 ('Cannot negate a ')
             26 LOAD_GLOBAL              5 (type)
             28 LOAD_FAST                2 (value)
             30 CALL_FUNCTION            1
             32 LOAD_ATTR                6 (__name__)
             34 FORMAT_VALUE             2 (repr)
             36 BUILD_STRING             2
             38 CALL_FUNCTION            1
             40 RAISE_VARARGS            1

752     >>   42 LOAD_FAST                1 (node)
             44 LOAD_ATTR                7 (op)
             46 LOAD_CONST               2 ('not')
             48 COMPARE_OP               2 (==)
             50 POP_JUMP_IF_FALSE       64

753          52 LOAD_GLOBAL              3 (Value)
             54 LOAD_FAST                2 (value)
             56 LOAD_ATTR                1 (value)
             58 UNARY_NOT
             60 CALL_FUNCTION            1
             62 RETURN_VALUE

754     >>   64 LOAD_FAST                1 (node)
             66 LOAD_ATTR                7 (op)
             68 LOAD_CONST               3 ('+')
             70 COMPARE_OP               2 (==)
             72 POP_JUMP_IF_FALSE       78

755          74 LOAD_FAST                2 (value)
             76 RETURN_VALUE

756     >>   78 LOAD_FAST                1 (node)
             80 LOAD_ATTR                7 (op)
             82 LOAD_CONST               4 ('-')
             84 COMPARE_OP               2 (==)
             86 POP_JUMP_IF_FALSE      100

757          88 LOAD_GLOBAL              3 (Value)
             90 LOAD_FAST                2 (value)
             92 LOAD_ATTR                1 (value)
             94 UNARY_NEGATIVE
             96 CALL_FUNCTION            1
             98 RETURN_VALUE

759     >>  100 LOAD_GLOBAL              8 (AssertionError)
            102 LOAD_CONST               5 ("node.op must be '+', '-', or 'not', found ")
            104 LOAD_FAST                1 (node)
            106 FORMAT_VALUE             2 (repr)
            108 BUILD_STRING             2
            110 CALL_FUNCTION            1
            112 RAISE_VARARGS            1
            114 LOAD_CONST               0 (None)
            116 RETURN_VALUE

Disassembly of <code object visit_Call at 0x100e33920, file "./interp.py", line 761>:
762           0 LOAD_DEREF               0 (self)
              2 LOAD_METHOD              0 (visit)
              4 LOAD_FAST                1 (node)
              6 LOAD_ATTR                1 (function)
              8 CALL_METHOD              1
             10 STORE_FAST               2 (function)

763          12 LOAD_GLOBAL              2 (isinstance)
             14 LOAD_FAST                2 (function)
             16 LOAD_GLOBAL              3 (Function)
             18 CALL_FUNCTION            2
             20 POP_JUMP_IF_TRUE        44

764          22 LOAD_FAST                2 (function)
             24 LOAD_ATTR                4 (__class__)
             26 LOAD_ATTR                5 (__name__)
             28 STORE_FAST               3 (object_type)

765          30 LOAD_GLOBAL              6 (InterpreterError)
             32 LOAD_FAST                3 (object_type)
             34 FORMAT_VALUE             2 (repr)
             36 LOAD_CONST               1 (' object is not callable')
             38 BUILD_STRING             2
             40 CALL_FUNCTION            1
             42 RAISE_VARARGS            1

767     >>   44 LOAD_CLOSURE             0 (self)
             46 BUILD_TUPLE              1
             48 LOAD_CONST               2 (<code object <listcomp> at 0x100e337c0, file "./interp.py", line 767>)
             50 LOAD_CONST               3 ('Interpreter.visit_Call.<locals>.<listcomp>')
             52 MAKE_FUNCTION            8 (closure)
             54 LOAD_FAST                1 (node)
             56 LOAD_ATTR                7 (args)
             58 GET_ITER
             60 CALL_FUNCTION            1
             62 STORE_FAST               4 (arguments)

769          64 LOAD_FAST                2 (function)
             66 LOAD_METHOD              8 (call)
             68 LOAD_DEREF               0 (self)
             70 LOAD_FAST                4 (arguments)
             72 CALL_METHOD              2
             74 RETURN_VALUE

Disassembly of <code object <listcomp> at 0x100e337c0, file "./interp.py", line 767>:
767           0 BUILD_LIST               0
              2 LOAD_FAST                0 (.0)
        >>    4 FOR_ITER                14 (to 20)
              6 STORE_FAST               1 (arg)
              8 LOAD_DEREF               0 (self)
             10 LOAD_METHOD              0 (visit)
             12 LOAD_FAST                1 (arg)
             14 CALL_METHOD              1
             16 LIST_APPEND              2
             18 JUMP_ABSOLUTE            4
        >>   20 RETURN_VALUE

Disassembly of <code object visit_Subscript at 0x100e339d0, file "./interp.py", line 771>:
772           0 LOAD_FAST                0 (self)
              2 LOAD_METHOD              0 (visit)
              4 LOAD_FAST                1 (node)
              6 LOAD_ATTR                1 (value)
              8 CALL_METHOD              1
             10 STORE_FAST               2 (obj)

773          12 LOAD_FAST                2 (obj)
             14 LOAD_CONST               0 (None)
             16 IS_OP                    1
             18 POP_JUMP_IF_TRUE        24
             20 LOAD_ASSERTION_ERROR
             22 RAISE_VARARGS            1

775     >>   24 LOAD_GLOBAL              2 (isinstance)
             26 LOAD_FAST                1 (node)
             28 LOAD_ATTR                3 (key)
             30 LOAD_GLOBAL              4 (Slice)
             32 CALL_FUNCTION            2
             34 POP_JUMP_IF_FALSE      208

776          36 LOAD_GLOBAL              2 (isinstance)
             38 LOAD_FAST                2 (obj)
             40 LOAD_GLOBAL              5 (Value)
             42 CALL_FUNCTION            2
             44 POP_JUMP_IF_FALSE      200
             46 LOAD_GLOBAL              2 (isinstance)
             48 LOAD_FAST                2 (obj)
             50 LOAD_ATTR                1 (value)
             52 LOAD_GLOBAL              6 (str)
             54 CALL_FUNCTION            2
             56 POP_JUMP_IF_FALSE      200

777          58 LOAD_FAST                0 (self)
             60 LOAD_METHOD              0 (visit)
             62 LOAD_FAST                1 (node)
             64 LOAD_ATTR                3 (key)
             66 LOAD_ATTR                7 (start)
             68 CALL_METHOD              1
             70 STORE_FAST               3 (start)

778          72 LOAD_FAST                0 (self)
             74 LOAD_METHOD              0 (visit)
             76 LOAD_FAST                1 (node)
             78 LOAD_ATTR                3 (key)
             80 LOAD_ATTR                8 (end)
             82 CALL_METHOD              1
             84 STORE_FAST               4 (end)

780          86 LOAD_GLOBAL              2 (isinstance)
             88 LOAD_FAST                3 (start)
             90 LOAD_GLOBAL              5 (Value)
             92 CALL_FUNCTION            2

779          94 POP_JUMP_IF_FALSE      150

781          96 LOAD_GLOBAL              2 (isinstance)
             98 LOAD_FAST                4 (end)
            100 LOAD_GLOBAL              5 (Value)
            102 CALL_FUNCTION            2

779         104 POP_JUMP_IF_FALSE      150

782         106 LOAD_FAST                3 (start)
            108 LOAD_ATTR                1 (value)
            110 LOAD_CONST               0 (None)
            112 IS_OP                    0

779         114 POP_JUMP_IF_TRUE       128

782         116 LOAD_GLOBAL              2 (isinstance)
            118 LOAD_FAST                3 (start)
            120 LOAD_ATTR                1 (value)
            122 LOAD_GLOBAL              9 (int)
            124 CALL_FUNCTION            2

779         126 POP_JUMP_IF_FALSE      150

783     >>  128 LOAD_FAST                4 (end)
            130 LOAD_ATTR                1 (value)
            132 LOAD_CONST               0 (None)
            134 IS_OP                    0

779         136 POP_JUMP_IF_TRUE       178

783         138 LOAD_GLOBAL              2 (isinstance)
            140 LOAD_FAST                4 (end)
            142 LOAD_ATTR                1 (value)
            144 LOAD_GLOBAL              9 (int)
            146 CALL_FUNCTION            2

779         148 POP_JUMP_IF_TRUE       178

785     >>  150 LOAD_GLOBAL             10 (InterpreterError)

786         152 LOAD_CONST               1 ("Slice indices should be integers or 'None', got ")
            154 LOAD_FAST                3 (start)
            156 LOAD_METHOD             11 (repr)
            158 CALL_METHOD              0
            160 FORMAT_VALUE             0
            162 LOAD_CONST               2 (', ')
            164 LOAD_FAST                4 (end)
            166 LOAD_METHOD             11 (repr)
            168 CALL_METHOD              0
            170 FORMAT_VALUE             0
            172 BUILD_STRING             4

785         174 CALL_FUNCTION            1
            176 RAISE_VARARGS            1

788     >>  178 LOAD_GLOBAL              5 (Value)
            180 LOAD_FAST                2 (obj)
            182 LOAD_ATTR                1 (value)
            184 LOAD_FAST                3 (start)
            186 LOAD_ATTR                1 (value)
            188 LOAD_FAST                4 (end)
            190 LOAD_ATTR                1 (value)
            192 BUILD_SLICE              2
            194 BINARY_SUBSCR
            196 CALL_FUNCTION            1
            198 RETURN_VALUE

789     >>  200 LOAD_GLOBAL             12 (NotImplementedError)
            202 LOAD_FAST                1 (node)
            204 CALL_FUNCTION            1
            206 RAISE_VARARGS            1

791     >>  208 LOAD_FAST                0 (self)
            210 LOAD_METHOD              0 (visit)
            212 LOAD_FAST                1 (node)
            214 LOAD_ATTR                3 (key)
            216 CALL_METHOD              1
            218 STORE_FAST               5 (key)

792         220 LOAD_GLOBAL              2 (isinstance)
            222 LOAD_FAST                2 (obj)
            224 LOAD_GLOBAL             13 (List)
            226 LOAD_GLOBAL             14 (Tuple)
            228 LOAD_GLOBAL             15 (Deque)
            230 BUILD_TUPLE              3
            232 CALL_FUNCTION            2
            234 EXTENDED_ARG             1
            236 POP_JUMP_IF_FALSE      304

793         238 LOAD_GLOBAL              2 (isinstance)
            240 LOAD_FAST                5 (key)
            242 LOAD_GLOBAL              5 (Value)
            244 CALL_FUNCTION            2
            246 EXTENDED_ARG             1
            248 POP_JUMP_IF_FALSE      264
            250 LOAD_GLOBAL              2 (isinstance)
            252 LOAD_FAST                5 (key)
            254 LOAD_ATTR                1 (value)
            256 LOAD_GLOBAL              9 (int)
            258 CALL_FUNCTION            2
            260 EXTENDED_ARG             1
            262 POP_JUMP_IF_TRUE       292

794     >>  264 LOAD_GLOBAL             10 (InterpreterError)

795         266 LOAD_GLOBAL             16 (type)
            268 LOAD_FAST                2 (obj)
            270 CALL_FUNCTION            1
            272 LOAD_ATTR               17 (__name__)
            274 FORMAT_VALUE             0
            276 LOAD_CONST               3 (' indices should be integers, got ')
            278 LOAD_FAST                5 (key)
            280 LOAD_METHOD             11 (repr)
            282 CALL_METHOD              0
            284 FORMAT_VALUE             0
            286 BUILD_STRING             3

794         288 CALL_FUNCTION            1
            290 RAISE_VARARGS            1

797     >>  292 LOAD_FAST                2 (obj)
            294 LOAD_ATTR               18 (_data)
            296 LOAD_FAST                5 (key)
            298 LOAD_ATTR                1 (value)
            300 BINARY_SUBSCR
            302 RETURN_VALUE

798     >>  304 LOAD_GLOBAL              2 (isinstance)
            306 LOAD_FAST                2 (obj)
            308 LOAD_GLOBAL             19 (Dict)
            310 CALL_FUNCTION            2
            312 EXTENDED_ARG             1
            314 POP_JUMP_IF_FALSE      338
            316 LOAD_FAST                5 (key)
            318 LOAD_FAST                2 (obj)
            320 LOAD_ATTR               20 (_dict)
            322 CONTAINS_OP              0
            324 EXTENDED_ARG             1
            326 POP_JUMP_IF_FALSE      338

799         328 LOAD_FAST                2 (obj)
            330 LOAD_ATTR               20 (_dict)
            332 LOAD_FAST                5 (key)
            334 BINARY_SUBSCR
            336 RETURN_VALUE

801     >>  338 LOAD_GLOBAL              2 (isinstance)
            340 LOAD_FAST                2 (obj)
            342 LOAD_GLOBAL              5 (Value)
            344 CALL_FUNCTION            2

800         346 EXTENDED_ARG             1
            348 POP_JUMP_IF_FALSE      392

802         350 LOAD_GLOBAL              2 (isinstance)
            352 LOAD_FAST                2 (obj)
            354 LOAD_ATTR                1 (value)
            356 LOAD_GLOBAL              6 (str)
            358 CALL_FUNCTION            2

800         360 EXTENDED_ARG             1
            362 POP_JUMP_IF_FALSE      392

803         364 LOAD_GLOBAL              2 (isinstance)
            366 LOAD_FAST                5 (key)
            368 LOAD_GLOBAL              5 (Value)
            370 CALL_FUNCTION            2

800         372 EXTENDED_ARG             1
            374 POP_JUMP_IF_FALSE      392

805         376 LOAD_GLOBAL              5 (Value)
            378 LOAD_FAST                2 (obj)
            380 LOAD_ATTR                1 (value)
            382 LOAD_FAST                5 (key)
            384 LOAD_ATTR                1 (value)
            386 BINARY_SUBSCR
            388 CALL_FUNCTION            1
            390 RETURN_VALUE

807     >>  392 LOAD_GLOBAL              2 (isinstance)
            394 LOAD_FAST                2 (obj)
            396 LOAD_GLOBAL              5 (Value)
            398 CALL_FUNCTION            2

806         400 EXTENDED_ARG             1
            402 POP_JUMP_IF_FALSE      446

808         404 LOAD_GLOBAL              2 (isinstance)
            406 LOAD_FAST                2 (obj)
            408 LOAD_ATTR                1 (value)
            410 LOAD_GLOBAL             21 (bytes)
            412 CALL_FUNCTION            2

806         414 EXTENDED_ARG             1
            416 POP_JUMP_IF_FALSE      446

809         418 LOAD_GLOBAL              2 (isinstance)
            420 LOAD_FAST                5 (key)
            422 LOAD_GLOBAL              5 (Value)
            424 CALL_FUNCTION            2

806         426 EXTENDED_ARG             1
            428 POP_JUMP_IF_FALSE      446

811         430 LOAD_GLOBAL              5 (Value)
            432 LOAD_FAST                2 (obj)
            434 LOAD_ATTR                1 (value)
            436 LOAD_FAST                5 (key)
            438 LOAD_ATTR                1 (value)
            440 BINARY_SUBSCR
            442 CALL_FUNCTION            1
            444 RETURN_VALUE

813     >>  446 LOAD_GLOBAL             10 (InterpreterError)
            448 LOAD_GLOBAL             16 (type)
            450 LOAD_FAST                2 (obj)
            452 CALL_FUNCTION            1
            454 LOAD_ATTR               17 (__name__)
            456 FORMAT_VALUE             0
            458 LOAD_CONST               4 (' object has no key ')
            460 LOAD_FAST                5 (key)
            462 LOAD_METHOD             11 (repr)
            464 CALL_METHOD              0
            466 FORMAT_VALUE             0
            468 BUILD_STRING             3
            470 CALL_FUNCTION            1
            472 RAISE_VARARGS            1
            474 LOAD_CONST               0 (None)
            476 RETURN_VALUE

Disassembly of <code object visit_Attribute at 0x100e33a80, file "./interp.py", line 815>:
816           0 LOAD_FAST                1 (node)
              2 LOAD_ATTR                0 (attr)
              4 STORE_FAST               2 (attribute_name)

817           6 LOAD_FAST                0 (self)
              8 LOAD_METHOD              1 (visit)
             10 LOAD_FAST                1 (node)
             12 LOAD_ATTR                2 (value)
             14 CALL_METHOD              1
             16 STORE_FAST               3 (obj)

818          18 LOAD_FAST                3 (obj)
             20 LOAD_CONST               0 (None)
             22 IS_OP                    1
             24 POP_JUMP_IF_TRUE        30
             26 LOAD_ASSERTION_ERROR
             28 RAISE_VARARGS            1

820     >>   30 LOAD_FAST                2 (attribute_name)
             32 LOAD_FAST                3 (obj)
             34 LOAD_ATTR                3 (attributes)
             36 CONTAINS_OP              0
             38 POP_JUMP_IF_FALSE       50

821          40 LOAD_FAST                3 (obj)
             42 LOAD_ATTR                3 (attributes)
             44 LOAD_FAST                2 (attribute_name)
             46 BINARY_SUBSCR
             48 RETURN_VALUE

823     >>   50 LOAD_FAST                2 (attribute_name)
             52 LOAD_FAST                3 (obj)
             54 LOAD_ATTR                4 (methods)
             56 CONTAINS_OP              0
             58 POP_JUMP_IF_FALSE       70

824          60 LOAD_FAST                3 (obj)
             62 LOAD_ATTR                4 (methods)
             64 LOAD_FAST                2 (attribute_name)
             66 BINARY_SUBSCR
             68 RETURN_VALUE

826     >>   70 LOAD_GLOBAL              5 (InterpreterError)

827          72 LOAD_GLOBAL              6 (type)
             74 LOAD_FAST                3 (obj)
             76 CALL_FUNCTION            1
             78 LOAD_ATTR                7 (__name__)
             80 FORMAT_VALUE             0
             82 LOAD_CONST               1 (' object has no attribute ')
             84 LOAD_FAST                2 (attribute_name)
             86 FORMAT_VALUE             2 (repr)
             88 BUILD_STRING             3

826          90 CALL_FUNCTION            1
             92 RAISE_VARARGS            1
             94 LOAD_CONST               0 (None)
             96 RETURN_VALUE

Disassembly of <code object visit_Name at 0x100e33b30, file "./interp.py", line 830>:
831           0 LOAD_FAST                1 (node)
              2 LOAD_ATTR                0 (id)
              4 STORE_FAST               2 (name)

833           6 LOAD_FAST                0 (self)
              8 LOAD_ATTR                1 (scope)
             10 STORE_FAST               3 (current_scope)

834     >>   12 LOAD_FAST                3 (current_scope)
             14 LOAD_CONST               0 (None)
             16 IS_OP                    1
             18 POP_JUMP_IF_FALSE       52

835          20 LOAD_FAST                3 (current_scope)
             22 LOAD_METHOD              2 (get)
             24 LOAD_FAST                2 (name)
             26 CALL_METHOD              1
             28 STORE_FAST               4 (value)

836          30 LOAD_FAST                4 (value)
             32 LOAD_GLOBAL              3 (NOT_SET)
             34 IS_OP                    0
             36 POP_JUMP_IF_FALSE       46

837          38 LOAD_FAST                3 (current_scope)
             40 LOAD_ATTR                4 (parent)
             42 STORE_FAST               3 (current_scope)
             44 JUMP_ABSOLUTE           12

839     >>   46 LOAD_FAST                4 (value)
             48 RETURN_VALUE
             50 JUMP_ABSOLUTE           12

841     >>   52 LOAD_FAST                0 (self)
             54 LOAD_ATTR                5 (globals)
             56 LOAD_METHOD              2 (get)
             58 LOAD_FAST                2 (name)
             60 CALL_METHOD              1
             62 STORE_FAST               4 (value)

842          64 LOAD_FAST                4 (value)
             66 LOAD_GLOBAL              3 (NOT_SET)
             68 IS_OP                    0
             70 POP_JUMP_IF_FALSE       86

843          72 LOAD_GLOBAL              6 (InterpreterError)
             74 LOAD_FAST                2 (name)
             76 FORMAT_VALUE             2 (repr)
             78 LOAD_CONST               1 (' is not defined')
             80 BUILD_STRING             2
             82 CALL_FUNCTION            1
             84 RAISE_VARARGS            1

845     >>   86 LOAD_FAST                4 (value)
             88 RETURN_VALUE

Disassembly of <code object visit_List at 0x100e33c90, file "./interp.py", line 847>:
848           0 LOAD_CLOSURE             0 (self)
              2 BUILD_TUPLE              1
              4 LOAD_CONST               1 (<code object <listcomp> at 0x100e33be0, file "./interp.py", line 848>)
              6 LOAD_CONST               2 ('Interpreter.visit_List.<locals>.<listcomp>')
              8 MAKE_FUNCTION            8 (closure)
             10 LOAD_FAST                1 (node)
             12 LOAD_ATTR                0 (elements)
             14 GET_ITER
             16 CALL_FUNCTION            1
             18 STORE_FAST               2 (elements)

849          20 LOAD_GLOBAL              1 (List)
             22 LOAD_FAST                2 (elements)
             24 CALL_FUNCTION            1
             26 RETURN_VALUE

Disassembly of <code object <listcomp> at 0x100e33be0, file "./interp.py", line 848>:
848           0 BUILD_LIST               0
              2 LOAD_FAST                0 (.0)
        >>    4 FOR_ITER                14 (to 20)
              6 STORE_FAST               1 (element)
              8 LOAD_DEREF               0 (self)
             10 LOAD_METHOD              0 (visit)
             12 LOAD_FAST                1 (element)
             14 CALL_METHOD              1
             16 LIST_APPEND              2
             18 JUMP_ABSOLUTE            4
        >>   20 RETURN_VALUE

Disassembly of <code object visit_Tuple at 0x100e33df0, file "./interp.py", line 851>:
852           0 LOAD_CLOSURE             0 (self)
              2 BUILD_TUPLE              1
              4 LOAD_CONST               1 (<code object <listcomp> at 0x100e33d40, file "./interp.py", line 852>)
              6 LOAD_CONST               2 ('Interpreter.visit_Tuple.<locals>.<listcomp>')
              8 MAKE_FUNCTION            8 (closure)
             10 LOAD_FAST                1 (node)
             12 LOAD_ATTR                0 (elements)
             14 GET_ITER
             16 CALL_FUNCTION            1
             18 STORE_FAST               2 (elements)

853          20 LOAD_GLOBAL              1 (Tuple)
             22 LOAD_FAST                2 (elements)
             24 CALL_FUNCTION            1
             26 RETURN_VALUE

Disassembly of <code object <listcomp> at 0x100e33d40, file "./interp.py", line 852>:
852           0 BUILD_LIST               0
              2 LOAD_FAST                0 (.0)
        >>    4 FOR_ITER                14 (to 20)
              6 STORE_FAST               1 (element)
              8 LOAD_DEREF               0 (self)
             10 LOAD_METHOD              0 (visit)
             12 LOAD_FAST                1 (element)
             14 CALL_METHOD              1
             16 LIST_APPEND              2
             18 JUMP_ABSOLUTE            4
        >>   20 RETURN_VALUE

Disassembly of <code object visit_Dict at 0x100e2f030, file "./interp.py", line 855>:
856           0 LOAD_CLOSURE             0 (self)
              2 BUILD_TUPLE              1
              4 LOAD_CONST               1 (<code object <listcomp> at 0x100e33ea0, file "./interp.py", line 856>)
              6 LOAD_CONST               2 ('Interpreter.visit_Dict.<locals>.<listcomp>')
              8 MAKE_FUNCTION            8 (closure)
             10 LOAD_FAST                1 (node)
             12 LOAD_ATTR                0 (keys)
             14 GET_ITER
             16 CALL_FUNCTION            1
             18 STORE_FAST               2 (keys)

857          20 LOAD_CLOSURE             0 (self)
             22 BUILD_TUPLE              1
             24 LOAD_CONST               3 (<code object <listcomp> at 0x100e33f50, file "./interp.py", line 857>)
             26 LOAD_CONST               2 ('Interpreter.visit_Dict.<locals>.<listcomp>')
             28 MAKE_FUNCTION            8 (closure)
             30 LOAD_FAST                1 (node)
             32 LOAD_ATTR                1 (values)
             34 GET_ITER
             36 CALL_FUNCTION            1
             38 STORE_FAST               3 (values)

858          40 LOAD_GLOBAL              2 (Dict)
             42 LOAD_FAST                2 (keys)
             44 LOAD_FAST                3 (values)
             46 CALL_FUNCTION            2
             48 RETURN_VALUE

Disassembly of <code object <listcomp> at 0x100e33ea0, file "./interp.py", line 856>:
856           0 BUILD_LIST               0
              2 LOAD_FAST                0 (.0)
        >>    4 FOR_ITER                14 (to 20)
              6 STORE_FAST               1 (key)
              8 LOAD_DEREF               0 (self)
             10 LOAD_METHOD              0 (visit)
             12 LOAD_FAST                1 (key)
             14 CALL_METHOD              1
             16 LIST_APPEND              2
             18 JUMP_ABSOLUTE            4
        >>   20 RETURN_VALUE

Disassembly of <code object <listcomp> at 0x100e33f50, file "./interp.py", line 857>:
857           0 BUILD_LIST               0
              2 LOAD_FAST                0 (.0)
        >>    4 FOR_ITER                14 (to 20)
              6 STORE_FAST               1 (value)
              8 LOAD_DEREF               0 (self)
             10 LOAD_METHOD              0 (visit)
             12 LOAD_FAST                1 (value)
             14 CALL_METHOD              1
             16 LIST_APPEND              2
             18 JUMP_ABSOLUTE            4
        >>   20 RETURN_VALUE

Disassembly of <code object visit_Constant at 0x100e2f0e0, file "./interp.py", line 860>:
861           0 LOAD_GLOBAL              0 (Value)
              2 LOAD_FAST                1 (node)
              4 LOAD_ATTR                1 (value)
              6 CALL_FUNCTION            1
              8 RETURN_VALUE

Disassembly of <code object interpret at 0x100e2f240, file "./interp.py", line 864>:
865           0 LOAD_GLOBAL              0 (parse)
              2 LOAD_FAST                0 (source)
              4 CALL_FUNCTION            1
              6 STORE_FAST               1 (module)

866           8 LOAD_FAST                1 (module)
             10 LOAD_CONST               0 (None)
             12 IS_OP                    0
             14 POP_JUMP_IF_FALSE       20

867          16 LOAD_CONST               0 (None)
             18 RETURN_VALUE

869     >>   20 LOAD_GLOBAL              1 (Interpreter)
             22 CALL_FUNCTION            0
             24 LOAD_METHOD              2 (visit)
             26 LOAD_FAST                1 (module)
             28 CALL_METHOD              1
             30 POP_TOP
             32 LOAD_CONST               0 (None)
             34 RETURN_VALUE

Disassembly of <code object main at 0x100e2f3a0, file "./interp.py", line 872>:
873           0 LOAD_GLOBAL              0 (sys)
              2 LOAD_ATTR                1 (stdin)
              4 LOAD_METHOD              2 (read)
              6 CALL_METHOD              0
              8 STORE_FAST               0 (source)

874          10 LOAD_GLOBAL              3 (interpret)
             12 LOAD_FAST                0 (source)
             14 CALL_FUNCTION            1
             16 STORE_FAST               1 (module)

875          18 LOAD_FAST                1 (module)
             20 LOAD_CONST               0 (None)
             22 IS_OP                    0
             24 POP_JUMP_IF_FALSE       30

876          26 LOAD_CONST               0 (None)
             28 RETURN_VALUE

878     >>   30 LOAD_CONST               1 ('--pretty')
             32 LOAD_GLOBAL              0 (sys)
             34 LOAD_ATTR                4 (argv)
             36 CONTAINS_OP              0
             38 POP_JUMP_IF_FALSE      108

879          40 SETUP_FINALLY           12 (to 54)

880          42 LOAD_CONST               2 (0)
             44 LOAD_CONST               0 (None)
             46 IMPORT_NAME              5 (black)
             48 STORE_FAST               2 (black)
             50 POP_BLOCK
             52 JUMP_FORWARD            26 (to 80)

881     >>   54 DUP_TOP
             56 LOAD_GLOBAL              6 (ImportError)
             58 JUMP_IF_NOT_EXC_MATCH    78
             60 POP_TOP
             62 POP_TOP
             64 POP_TOP

882          66 LOAD_GLOBAL              7 (print)
             68 LOAD_CONST               3 ('Error: `black` needs to be installed for `--pretty` to work.')
             70 CALL_FUNCTION            1
             72 POP_TOP
             74 POP_EXCEPT
             76 JUMP_FORWARD             2 (to 80)
        >>   78 RERAISE

884     >>   80 LOAD_GLOBAL              7 (print)
             82 LOAD_FAST                2 (black)
             84 LOAD_ATTR                8 (format_str)
             86 LOAD_GLOBAL              9 (repr)
             88 LOAD_FAST                1 (module)
             90 CALL_FUNCTION            1
             92 LOAD_FAST                2 (black)
             94 LOAD_METHOD             10 (Mode)
             96 CALL_METHOD              0
             98 LOAD_CONST               4 (('mode',))
            100 CALL_FUNCTION_KW         2
            102 CALL_FUNCTION            1
            104 POP_TOP
            106 JUMP_FORWARD             8 (to 116)

886     >>  108 LOAD_GLOBAL              7 (print)
            110 LOAD_FAST                1 (module)
            112 CALL_FUNCTION            1
            114 POP_TOP
        >>  116 LOAD_CONST               0 (None)
            118 RETURN_VALUE
